Workbook
Name SegmentaciónDeDatos_País_de_Origen1: #N/A

Sheet Memoria
A1: REGISTRO DE ACCIONES
A2: SALA | I2: COCINA
A3: 1- Se ordenaron los datos por delimitación de comas | I3: 1- Se ordenaron los datos por delimitación de comas
A4: 2- Creada columna "Monto total", donde se recoge el precio total de la orden + propinas | I4: 2- Eliminada columna "Observaciones"
A5: 3- Reformateados los datos en columna "Propinas": Se sustituyó el punto decimal por una coma | I5: 3- Creada columna "Ganancia bruta": Precio de venta del plato * Cantidad
A6: 4- Reformateados los datos en las columnas "Hora de llegada" y "Hora de salida" a formato numérico excel | I6: 4- Creada columna "Ganancia neta: (Precio de venta- precio de coste) * Cantidad
A7: 5- Creadas columnas "Hora de llegada2" y "Hora de salida2", usado formato horario común | I7: 5- Creada columna "% de ganancia" donde se muestra el margen de beneficio respecto a la ganancia neta (neta/bruta *100)
A8: 6- Creada columna "Tiempo de permanencia" (Hsalida-Hllegada, sumados 15 min en caso de mesa ocupada) | I8: 6- Creada tabla dinámica (Agrupación por nº de orden y filtrado por el mismo)
A9: 7- Creada columna "Tiempo de preparación" (Suma total tiempo de preparación de los platos por orden)
A10: 8- Creada columna "Tiempo de degustación" (Permanencia - preparación, 0 si la suma es menor a 0)
A11: 9- Creada columna " Mesa Pagada" (Si tiempo de degustación<0, NO PAGADA)

Sheet Cocina
A1: Número de Orden | B1: Número de Mesa | C1: Nombre del Plato | D1: Descripción del Plato | E1: Costo Unitario | F1: Precio Unitario | G1: Cantidad Ordenada | H1: Tiempo de Preparación | I1: Ganancia bruta | J1: Ganancia neta | K1: Porcentaje ganancia
A2: 1 | B2: 10 | C2: Plato_2 | D2: Descripción del Plato_2 | E2: 18 | F2: 30 | G2: 3 | H2: 32 | I2: =spaces_3iWczBNnn5rbfoUlE0Jd_uploads_git_blob_d9e80ffbcef8a4adc6d29edd78618add5df6[[#This Row],[Precio Unitario]]*spaces_3iWczBNnn5rbfoUlE0Jd_uploads_git_blob_d9e80ffbcef8a4adc6d29edd78618add5df6[[#This Row],[Cantidad Ordenada]] -> 90 | J2: =(spaces_3iWczBNnn5rbfoUlE0Jd_uploads_git_blob_d9e80ffbcef8a4adc6d29edd78618add5df6[[#This Row],[Precio Unitario]]-spaces_3iWczBNnn5rbfoUlE0Jd_uploads_git_blob_d9e80ffbcef8a4adc6d29edd78618add5df6[[#This Row],[Costo Unitario]])*spaces_3iWczBNnn5rbfoUlE0Jd_uploads_git_blob_d9e80ffbcef8a4adc6d29edd78618add5df6[[#This Row],[Cantidad Ordenada]] -> 36 | K2: =(spaces_3iWczBNnn5rbfoUlE0Jd_uploads_git_blob_d9e80ffbcef8a4adc6d29edd78618add5df6[[#This Row],[Ganancia neta]]/spaces_3iWczBNnn5rbfoUlE0Jd_uploads_git_blob_d9e80ffbcef8a4adc6d29edd78618add5df6[[#This Row],[Ganancia bruta]]) -> 0.4
A3: 1 | B3: 10 | C3: Plato_7 | D3: Descripción del Plato_7 | E3: 14 | F3: 24 | G3: 2 | H3: 25 | I3: =spaces_3iWczBNnn5rbfoUlE0Jd_uploads_git_blob_d9e80ffbcef8a4adc6d29edd78618add5df6[[#This Row],[Precio Unitario]]*spaces_3iWczBNnn5rbfoUlE0Jd_uploads_git_blob_d9e80ffbcef8a4adc6d29edd78618add5df6[[#This Row],[Cantidad Ordenada]] -> 48 | J3: =(spaces_3iWczBNnn5rbfoUlE0Jd_uploads_git_blob_d9e80ffbcef8a4adc6d29edd78618add5df6[[#This Row],[Precio Unitario]]-spaces_3iWczBNnn5rbfoUlE0Jd_uploads_git_blob_d9e80ffbcef8a4adc6d29edd78618add5df6[[#This Row],[Costo Unitario]])*spaces_3iWczBNnn5rbfoUlE0Jd_uploads_git_blob_d9e80ffbcef8a4adc6d29edd78618add5df6[[#This Row],[Cantidad Ordenada]] -> 20 | K3: =(spaces_3iWczBNnn5rbfoUlE0Jd_uploads_git_blob_d9e80ffbcef8a4adc6d29edd78618add5df6[[#This Row],[Ganancia neta]]/spaces_3iWczBNnn5rbfoUlE0Jd_uploads_git_blob_d9e80ffbcef8a4adc6d29edd78618add5df6[[#This Row],[Ganancia bruta]]) -> 0.41666667
A4: 2 | B4: 6 | C4: Plato_17 | D4: Descripción del Plato_17 | E4: 19 | F4: 31 | G4: 1 | H4: 51 | I4: =spaces_3iWczBNnn5rbfoUlE0Jd_uploads_git_blob_d9e80ffbcef8a4adc6d29edd78618add5df6[[#This Row],[Precio Unitario]]*spaces_3iWczBNnn5rbfoUlE0Jd_uploads_git_blob_d9e80ffbcef8a4adc6d29edd78618add5df6[[#This Row],[Cantidad Ordenada]] -> 31 | J4: =(spaces_3iWczBNnn5rbfoUlE0Jd_uploads_git_blob_d9e80ffbcef8a4adc6d29edd78618add5df6[[#This Row],[Precio Unitario]]-spaces_3iWczBNnn5rbfoUlE0Jd_uploads_git_blob_d9e80ffbcef8a4adc6d29edd78618add5df6[[#This Row],[Costo Unitario]])*spaces_3iWczBNnn5rbfoUlE0Jd_uploads_git_blob_d9e80ffbcef8a4adc6d29edd78618add5df6[[#This Row],[Cantidad Ordenada]] -> 12 | K4: =(spaces_3iWczBNnn5rbfoUlE0Jd_uploads_git_blob_d9e80ffbcef8a4adc6d29edd78618add5df6[[#This Row],[Ganancia neta]]/spaces_3iWczBNnn5rbfoUlE0Jd_uploads_git_blob_d9e80ffbcef8a4adc6d29edd78618add5df6[[#This Row],[Ganancia bruta]]) -> 0.38709677
A5: 2 | B5: 6 | C5: Plato_6 | D5: Descripción del Plato_6 | E5: 16 | F5: 27 | G5: 1 | H5: 34 | I5: =spaces_3iWczBNnn5rbfoUlE0Jd_uploads_git_blob_d9e80ffbcef8a4adc6d29edd78618add5df6[[#This Row],[Precio Unitario]]*spaces_3iWczBNnn5rbfoUlE0Jd_uploads_git_blob_d9e80ffbcef8a4adc6d29edd78618add5df6[[#This Row],[Cantidad Ordenada]] -> 27 | J5: =(spaces_3iWczBNnn5rbfoUlE0Jd_uploads_git_blob_d9e80ffbcef8a4adc6d29edd78618add5df6[[#This Row],[Precio Unitario]]-spaces_3iWczBNnn5rbfoUlE0Jd_uploads_git_blob_d9e80ffbcef8a4adc6d29edd78618add5df6[[#This Row],[Costo Unitario]])*spaces_3iWczBNnn5rbfoUlE0Jd_uploads_git_blob_d9e80ffbcef8a4adc6d29edd78618add5df6[[#This Row],[Cantidad Ordenada]] -> 11 | K5: =(spaces_3iWczBNnn5rbfoUlE0Jd_uploads_git_blob_d9e80ffbcef8a4adc6d29edd78618add5df6[[#This Row],[Ganancia neta]]/spaces_3iWczBNnn5rbfoUlE0Jd_uploads_git_blob_d9e80ffbcef8a4adc6d29edd78618add5df6[[#This Row],[Ganancia bruta]]) -> 0.40740741
A6: 3 | B6: 20 | C6: Plato_17 | D6: Descripción del Plato_17 | E6: 19 | F6: 31 | G6: 1 | H6: 27 | I6: =spaces_3iWczBNnn5rbfoUlE0Jd_uploads_git_blob_d9e80ffbcef8a4adc6d29edd78618add5df6[[#This Row],[Precio Unitario]]*spaces_3iWczBNnn5rbfoUlE0Jd_uploads_git_blob_d9e80ffbcef8a4adc6d29edd78618add5df6[[#This Row],[Cantidad Ordenada]] -> 31 | J6: =(spaces_3iWczBNnn5rbfoUlE0Jd_uploads_git_blob_d9e80ffbcef8a4adc6d29edd78618add5df6[[#This Row],[Precio Unitario]]-spaces_3iWczBNnn5rbfoUlE0Jd_uploads_git_blob_d9e80ffbcef8a4adc6d29edd78618add5df6[[#This Row],[Costo Unitario]])*spaces_3iWczBNnn5rbfoUlE0Jd_uploads_git_blob_d9e80ffbcef8a4adc6d29edd78618add5df6[[#This Row],[Cantidad Ordenada]] -> 12 | K6: =(spaces_3iWczBNnn5rbfoUlE0Jd_uploads_git_blob_d9e80ffbcef8a4adc6d29edd78618add5df6[[#This Row],[Ganancia neta]]/spaces_3iWczBNnn5rbfoUlE0Jd_uploads_git_blob_d9e80ffbcef8a4adc6d29edd78618add5df6[[#This Row],[Ganancia bruta]]) -> 0.38709677
A7: 3 | B7: 20 | C7: Plato_19 | D7: Descripción del Plato_19 | E7: 22 | F7: 36 | G7: 1 | H7: 36 | I7: =spaces_3iWczBNnn5rbfoUlE0Jd_uploads_git_blob_d9e80ffbcef8a4adc6d29edd78618add5df6[[#This Row],[Precio Unitario]]*spaces_3iWczBNnn5rbfoUlE0Jd_uploads_git_blob_d9e80ffbcef8a4adc6d29edd78618add5df6[[#This Row],[Cantidad Ordenada]] -> 36 | J7: =(spaces_3iWczBNnn5rbfoUlE0Jd_uploads_git_blob_d9e80ffbcef8a4adc6d29edd78618add5df6[[#This Row],[Precio Unitario]]-spaces_3iWczBNnn5rbfoUlE0Jd_uploads_git_blob_d9e80ffbcef8a4adc6d29edd78618add5df6[[#This Row],[Costo Unitario]])*spaces_3iWczBNnn5rbfoUlE0Jd_uploads_git_blob_d9e80ffbcef8a4adc6d29edd78618add5df6[[#This Row],[Cantidad Ordenada]] -> 14 | K7: =(spaces_3iWczBNnn5rbfoUlE0Jd_uploads_git_blob_d9e80ffbcef8a4adc6d29edd78618add5df6[[#This Row],[Ganancia neta]]/spaces_3iWczBNnn5rbfoUlE0Jd_uploads_git_blob_d9e80ffbcef8a4adc6d29edd78618add5df6[[#This Row],[Ganancia bruta]]) -> 0.38888889
A8: 3 | B8: 20 | C8: Plato_20 | D8: Descripción del Plato_20 | E8: 25 | F8: 40 | G8: 1 | H8: 9 | I8: =spaces_3iWczBNnn5rbfoUlE0Jd_uploads_git_blob_d9e80ffbcef8a4adc6d29edd78618add5df6[[#This Row],[Precio Unitario]]*spaces_3iWczBNnn5rbfoUlE0Jd_uploads_git_blob_d9e80ffbcef8a4adc6d29edd78618add5df6[[#This Row],[Cantidad Ordenada]] -> 40 | J8: =(spaces_3iWczBNnn5rbfoUlE0Jd_uploads_git_blob_d9e80ffbcef8a4adc6d29edd78618add5df6[[#This Row],[Precio Unitario]]-spaces_3iWczBNnn5rbfoUlE0Jd_uploads_git_blob_d9e80ffbcef8a4adc6d29edd78618add5df6[[#This Row],[Costo Unitario]])*spaces_3iWczBNnn5rbfoUlE0Jd_uploads_git_blob_d9e80ffbcef8a4adc6d29edd78618add5df6[[#This Row],[Cantidad Ordenada]] -> 15 | K8: =(spaces_3iWczBNnn5rbfoUlE0Jd_uploads_git_blob_d9e80ffbcef8a4adc6d29edd78618add5df6[[#This Row],[Ganancia neta]]/spaces_3iWczBNnn5rbfoUlE0Jd_uploads_git_blob_d9e80ffbcef8a4adc6d29edd78618add5df6[[#This Row],[Ganancia bruta]]) -> 0.375
A9: 3 | B9: 20 | C9: Plato_9 | D9: Descripción del Plato_9 | E9: 17 | F9: 29 | G9: 2 | H9: 54 | I9: =spaces_3iWczBNnn5rbfoUlE0Jd_uploads_git_blob_d9e80ffbcef8a4adc6d29edd78618add5df6[[#This Row],[Precio Unitario]]*spaces_3iWczBNnn5rbfoUlE0Jd_uploads_git_blob_d9e80ffbcef8a4adc6d29edd78618add5df6[[#This Row],[Cantidad Ordenada]] -> 58 | J9: =(spaces_3iWczBNnn5rbfoUlE0Jd_uploads_git_blob_d9e80ffbcef8a4adc6d29edd78618add5df6[[#This Row],[Precio Unitario]]-spaces_3iWczBNnn5rbfoUlE0Jd_uploads_git_blob_d9e80ffbcef8a4adc6d29edd78618add5df6[[#This Row],[Costo Unitario]])*spaces_3iWczBNnn5rbfoUlE0Jd_uploads_git_blob_d9e80ffbcef8a4adc6d29edd78618add5df6[[#This Row],[Cantidad Ordenada]] -> 24 | K9: =(spaces_3iWczBNnn5rbfoUlE0Jd_uploads_git_blob_d9e80ffbcef8a4adc6d29edd78618add5df6[[#This Row],[Ganancia neta]]/spaces_3iWczBNnn5rbfoUlE0Jd_uploads_git_blob_d9e80ffbcef8a4adc6d29edd78618add5df6[[#This Row],[Ganancia bruta]]) -> 0.4137931
A10: 4 | B10: 3 | C10: Plato_11 | D10: Descripción del Plato_11 | E10: 20 | F10: 33 | G10: 3 | H10: 23 | I10: =spaces_3iWczBNnn5rbfoUlE0Jd_uploads_git_blob_d9e80ffbcef8a4adc6d29edd78618add5df6[[#This Row],[Precio Unitario]]*spaces_3iWczBNnn5rbfoUlE0Jd_uploads_git_blob_d9e80ffbcef8a4adc6d29edd78618add5df6[[#This Row],[Cantidad Ordenada]] -> 99 | J10: =(spaces_3iWczBNnn5rbfoUlE0Jd_uploads_git_blob_d9e80ffbcef8a4adc6d29edd78618add5df6[[#This Row],[Precio Unitario]]-spaces_3iWczBNnn5rbfoUlE0Jd_uploads_git_blob_d9e80ffbcef8a4adc6d29edd78618add5df6[[#This Row],[Costo Unitario]])*spaces_3iWczBNnn5rbfoUlE0Jd_uploads_git_blob_d9e80ffbcef8a4adc6d29edd78618add5df6[[#This Row],[Cantidad Ordenada]] -> 39 | K10: =(spaces_3iWczBNnn5rbfoUlE0Jd_uploads_git_blob_d9e80ffbcef8a4adc6d29edd78618add5df6[[#This Row],[Ganancia neta]]/spaces_3iWczBNnn5rbfoUlE0Jd_uploads_git_blob_d9e80ffbcef8a4adc6d29edd78618add5df6[[#This Row],[Ganancia bruta]]) -> 0.39393939
A11: 4 | B11: 3 | C11: Plato_16 | D11: Descripción del Plato_16 | E11: 16 | F11: 28 | G11: 3 | H11: 17 | I11: =spaces_3iWczBNnn5rbfoUlE0Jd_uploads_git_blob_d9e80ffbcef8a4adc6d29edd78618add5df6[[#This Row],[Precio Unitario]]*spaces_3iWczBNnn5rbfoUlE0Jd_uploads_git_blob_d9e80ffbcef8a4adc6d29edd78618add5df6[[#This Row],[Cantidad Ordenada]] -> 84 | J11: =(spaces_3iWczBNnn5rbfoUlE0Jd_uploads_git_blob_d9e80ffbcef8a4adc6d29edd78618add5df6[[#This Row],[Precio Unitario]]-spaces_3iWczBNnn5rbfoUlE0Jd_uploads_git_blob_d9e80ffbcef8a4adc6d29edd78618add5df6[[#This Row],[Costo Unitario]])*spaces_3iWczBNnn5rbfoUlE0Jd_uploads_git_blob_d9e80ffbcef8a4adc6d29edd78618add5df6[[#This Row],[Cantidad Ordenada]] -> 36 | K11: =(spaces_3iWczBNnn5rbfoUlE0Jd_uploads_git_blob_d9e80ffbcef8a4adc6d29edd78618add5df6[[#This Row],[Ganancia neta]]/spaces_3iWczBNnn5rbfoUlE0Jd_uploads_git_blob_d9e80ffbcef8a4adc6d29edd78618add5df6[[#This Row],[Ganancia bruta]]) -> 0.42857143
A12: 5 | B12: 8 | C12: Plato_12 | D12: Descripción del Plato_12 | E12: 11 | F12: 19 | G12: 1 | H12: 8 | I12: =spaces_3iWczBNnn5rbfoUlE0Jd_uploads_git_blob_d9e80ffbcef8a4adc6d29edd78618add5df6[[#This Row],[Precio Unitario]]*spaces_3iWczBNnn5rbfoUlE0Jd_uploads_git_blob_d9e80ffbcef8a4adc6d29edd78618add5df6[[#This Row],[Cantidad Ordenada]] -> 19 | J12: =(spaces_3iWczBNnn5rbfoUlE0Jd_uploads_git_blob_d9e80ffbcef8a4adc6d29edd78618add5df6[[#This Row],[Precio Unitario]]-spaces_3iWczBNnn5rbfoUlE0Jd_uploads_git_blob_d9e80ffbcef8a4adc6d29edd78618add5df6[[#This Row],[Costo Unitario]])*spaces_3iWczBNnn5rbfoUlE0Jd_uploads_git_blob_d9e80ffbcef8a4adc6d29edd78618add5df6[[#This Row],[Cantidad Ordenada]] -> 8 | K12: =(spaces_3iWczBNnn5rbfoUlE0Jd_uploads_git_blob_d9e80ffbcef8a4adc6d29edd78618add5df6[[#This Row],[Ganancia neta]]/spaces_3iWczBNnn5rbfoUlE0Jd_uploads_git_blob_d9e80ffbcef8a4adc6d29edd78618add5df6[[#This Row],[Ganancia bruta]]) -> 0.42105263
A13: 5 | B13: 8 | C13: Plato_7 | D13: Descripción del Plato_7 | E13: 14 | F13: 24 | G13: 2 | H13: 9 | I13: =spaces_3iWczBNnn5rbfoUlE0Jd_uploads_git_blob_d9e80ffbcef8a4adc6d29edd78618add5df6[[#This Row],[Precio Unitario]]*spaces_3iWczBNnn5rbfoUlE0Jd_uploads_git_blob_d9e80ffbcef8a4adc6d29edd78618add5df6[[#This Row],[Cantidad Ordenada]] -> 48 | J13: =(spaces_3iWczBNnn5rbfoUlE0Jd_uploads_git_blob_d9e80ffbcef8a4adc6d29edd78618add5df6[[#This Row],[Precio Unitario]]-spaces_3iWczBNnn5rbfoUlE0Jd_uploads_git_blob_d9e80ffbcef8a4adc6d29edd78618add5df6[[#This Row],[Costo Unitario]])*spaces_3iWczBNnn5rbfoUlE0Jd_uploads_git_blob_d9e80ffbcef8a4adc6d29edd78618add5df6[[#This Row],[Cantidad Ordenada]] -> 20 | K13: =(spaces_3iWczBNnn5rbfoUlE0Jd_uploads_git_blob_d9e80ffbcef8a4adc6d29edd78618add5df6[[#This Row],[Ganancia neta]]/spaces_3iWczBNnn5rbfoUlE0Jd_uploads_git_blob_d9e80ffbcef8a4adc6d29edd78618add5df6[[#This Row],[Ganancia bruta]]) -> 0.41666667
... A1903: 767 | B1903: 10 | C1903: Plato_9 | D1903: Descripción del Plato_9 | E1903: 17 | F1903: 29 | G1903: 2 | H1903: 12 | I1903: =spaces_3iWczBNnn5rbfoUlE0Jd_uploads_git_blob_d9e80ffbcef8a4adc6d29edd78618add5df6[[#This Row],[Precio Unitario]]*spaces_3iWczBNnn5rbfoUlE0Jd_uploads_git_blob_d9e80ffbcef8a4adc6d29edd78618add5df6[[#This Row],[Cantidad Ordenada]] -> 58 | J1903: =(spaces_3iWczBNnn5rbfoUlE0Jd_uploads_git_blob_d9e80ffbcef8a4adc6d29edd78618add5df6[[#This Row],[Precio Unitario]]-spaces_3iWczBNnn5rbfoUlE0Jd_uploads_git_blob_d9e80ffbcef8a4adc6d29edd78618add5df6[[#This Row],[Costo Unitario]])*spaces_3iWczBNnn5rbfoUlE0Jd_uploads_git_blob_d9e80ffbcef8a4adc6d29edd78618add5df6[[#This Row],[Cantidad Ordenada]] -> 24 | K1903: =(spaces_3iWczBNnn5rbfoUlE0Jd_uploads_git_blob_d9e80ffbcef8a4adc6d29edd78618add5df6[[#This Row],[Ganancia neta]]/spaces_3iWczBNnn5rbfoUlE0Jd_uploads_git_blob_d9e80ffbcef8a4adc6d29edd78618add5df6[[#This Row],[Ganancia bruta]]) -> 0.4137931

Sheet Sala
A1: Número de Mesa | B1: Nombre del Cliente | C1: Número de Comensales | D1: Hora de Llegada | E1: Hora de Salida | F1: Mesero Asignado | G1: Tipo de Servicio | H1: Método de Pago | I1: Propina | J1: Estado de la Mesa | K1: Número de Orden | L1: País de Origen | M1: Platos Ordenados | N1: Monto total | O1: Fecha de factura | P1: Hora de llegada2 | Q1: Hora de salida2 | R1: Tiempo de permanencia | S1: Tiempo de preparación total | T1: Tiempo degustación | U1: Mesa pagada
A2: 10 | B2: Cliente_724 | C2: 6 | D2: 45017.047 | E2: 45017.16 | F2: Mesero_3 | G2: Almuerzo | H2: Tarjeta de débito | I2: 48.55 | J2: Reservada | K2: 1 | L2: España | M2: Plato_7, Plato_2 | N2: =_xlfn.XLOOKUP(spaces_3iWczBNnn5rbfoUlE0Jd_uploads_git_blob_9864c7f811c613c3faab876659c6423__25[[#This Row],[Número de Orden]],Cocinadinamica!B3:B771,Cocinadinamica!C3:C771) -> 56 | O2: =spaces_3iWczBNnn5rbfoUlE0Jd_uploads_git_blob_9864c7f811c613c3faab876659c6423__25[[#This Row],[Hora de Llegada]] -> 45017.047 | P2: =spaces_3iWczBNnn5rbfoUlE0Jd_uploads_git_blob_9864c7f811c613c3faab876659c6423__25[[#This Row],[Hora de Llegada]] -> 45017.047 | Q2: =spaces_3iWczBNnn5rbfoUlE0Jd_uploads_git_blob_9864c7f811c613c3faab876659c6423__25[[#This Row],[Hora de Salida]] -> 45017.16 | R2: {=_xlfn.IFS(spaces_3iWczBNnn5rbfoUlE0Jd_uploads_git_blob_9864c7f811c613c3faab876659c6423__25[[#This Row],[Estado de la Mesa]]="Ocupada",(15/1440)+spaces_3iWczBNnn5rbfoUlE0Jd_uploads_git_blob_9864c7f811c613c3faab876659c6423__25[[#This Row],[Hora de salida2]]-spaces_3iWczBNnn5rbfoUlE0Jd_uploads_git_blob_9864c7f811c613c3faab876659c6423__25[[#This Row],[Hora de llegada2]],spaces_3iWczBNnn5rbfoUlE0Jd_uploads_git_blob_9864c7f811c613c3faab876659c6423__25[[#This Row],[Estado de la Mesa]]<>"Ocupada",spaces_3iWczBNnn5rbfoUlE0Jd_uploads_git_blob_9864c7f811c613c3faab876659c6423__25[[#This Row],[Hora de salida2]]-spaces_3iWczBNnn5rbfoUlE0Jd_uploads_git_blob_9864c7f811c613c3faab876659c6423__25[[#This Row],[Hora de llegada2]])} -> 0.11319444 | S2: =_xlfn.XLOOKUP(spaces_3iWczBNnn5rbfoUlE0Jd_uploads_git_blob_9864c7f811c613c3faab876659c6423__25[[#This Row],[Número de Orden]],Cocinadinamica!E3:E771,Cocinadinamica!F3:F771)/1440 -> 0.039583333 | T2: {=_xlfn.IFS((spaces_3iWczBNnn5rbfoUlE0Jd_uploads_git_blob_9864c7f811c613c3faab876659c6423__25[[#This Row],[Tiempo de permanencia]]-spaces_3iWczBNnn5rbfoUlE0Jd_uploads_git_blob_9864c7f811c613c3faab876659c6423__25[[#This Row],[Tiempo de preparación total]])>0,spaces_3iWczBNnn5rbfoUlE0Jd_uploads_git_blob_9864c7f811c613c3faab876659c6423__25[[#This Row],[Tiempo de permanencia]]-spaces_3iWczBNnn5rbfoUlE0Jd_uploads_git_blob_9864c7f811c613c3faab876659c6423__25[[#This Row],[Tiempo de preparación total]],spaces_3iWczBNnn5rbfoUlE0Jd_uploads_git_blob_9864c7f811c613c3faab876659c6423__25[[#This Row],[Tiempo de permanencia]]-spaces_3iWczBNnn5rbfoUlE0Jd_uploads_git_blob_9864c7f811c613c3faab876659c6423__25[[#This Row],[Tiempo de preparación total]]<0,0)} -> 0.073611111 | U2: {=_xlfn.IFS(spaces_3iWczBNnn5rbfoUlE0Jd_uploads_git_blob_9864c7f811c613c3faab876659c6423__25[[#This Row],[Tiempo degustación]]=0,"NO PAGADA",spaces_3iWczBNnn5rbfoUlE0Jd_uploads_git_blob_9864c7f811c613c3faab876659c6423__25[[#This Row],[Tiempo degustación]]>0, "PAGADA")} -> PAGADA
A3: 6 | B3: Cliente_538 | C3: 6 | D3: 45017.061 | E3: 45017.159 | F3: Mesero_1 | G3: Desayuno | H3: Efectivo | I3: 43.3 | J3: Reservada | K3: 2 | L3: Colombia | M3: Plato_17, Plato_6 | N3: =_xlfn.XLOOKUP(spaces_3iWczBNnn5rbfoUlE0Jd_uploads_git_blob_9864c7f811c613c3faab876659c6423__25[[#This Row],[Número de Orden]],Cocinadinamica!B4:B772,Cocinadinamica!C4:C772) -> 23 | O3: =spaces_3iWczBNnn5rbfoUlE0Jd_uploads_git_blob_9864c7f811c613c3faab876659c6423__25[[#This Row],[Hora de Llegada]] -> 45017.061 | P3: =spaces_3iWczBNnn5rbfoUlE0Jd_uploads_git_blob_9864c7f811c613c3faab876659c6423__25[[#This Row],[Hora de Llegada]] -> 45017.061 | Q3: =spaces_3iWczBNnn5rbfoUlE0Jd_uploads_git_blob_9864c7f811c613c3faab876659c6423__25[[#This Row],[Hora de Salida]] -> 45017.159 | R3: {=_xlfn.IFS(spaces_3iWczBNnn5rbfoUlE0Jd_uploads_git_blob_9864c7f811c613c3faab876659c6423__25[[#This Row],[Estado de la Mesa]]="Ocupada",(15/1440)+spaces_3iWczBNnn5rbfoUlE0Jd_uploads_git_blob_9864c7f811c613c3faab876659c6423__25[[#This Row],[Hora de salida2]]-spaces_3iWczBNnn5rbfoUlE0Jd_uploads_git_blob_9864c7f811c613c3faab876659c6423__25[[#This Row],[Hora de llegada2]],spaces_3iWczBNnn5rbfoUlE0Jd_uploads_git_blob_9864c7f811c613c3faab876659c6423__25[[#This Row],[Estado de la Mesa]]<>"Ocupada",spaces_3iWczBNnn5rbfoUlE0Jd_uploads_git_blob_9864c7f811c613c3faab876659c6423__25[[#This Row],[Hora de salida2]]-spaces_3iWczBNnn5rbfoUlE0Jd_uploads_git_blob_9864c7f811c613c3faab876659c6423__25[[#This Row],[Hora de llegada2]])} -> 0.097916667 | S3: =_xlfn.XLOOKUP(spaces_3iWczBNnn5rbfoUlE0Jd_uploads_git_blob_9864c7f811c613c3faab876659c6423__25[[#This Row],[Número de Orden]],Cocinadinamica!E4:E772,Cocinadinamica!F4:F772)/1440 -> 0.059027778 | T3: {=_xlfn.IFS((spaces_3iWczBNnn5rbfoUlE0Jd_uploads_git_blob_9864c7f811c613c3faab876659c6423__25[[#This Row],[Tiempo de permanencia]]-spaces_3iWczBNnn5rbfoUlE0Jd_uploads_git_blob_9864c7f811c613c3faab876659c6423__25[[#This Row],[Tiempo de preparación total]])>0,spaces_3iWczBNnn5rbfoUlE0Jd_uploads_git_blob_9864c7f811c613c3faab876659c6423__25[[#This Row],[Tiempo de permanencia]]-spaces_3iWczBNnn5rbfoUlE0Jd_uploads_git_blob_9864c7f811c613c3faab876659c6423__25[[#This Row],[Tiempo de preparación total]],spaces_3iWczBNnn5rbfoUlE0Jd_uploads_git_blob_9864c7f811c613c3faab876659c6423__25[[#This Row],[Tiempo de permanencia]]-spaces_3iWczBNnn5rbfoUlE0Jd_uploads_git_blob_9864c7f811c613c3faab876659c6423__25[[#This Row],[Tiempo de preparación total]]<0,0)} -> 0.038888889 | U3: {=_xlfn.IFS(spaces_3iWczBNnn5rbfoUlE0Jd_uploads_git_blob_9864c7f811c613c3faab876659c6423__25[[#This Row],[Tiempo degustación]]=0,"NO PAGADA",spaces_3iWczBNnn5rbfoUlE0Jd_uploads_git_blob_9864c7f811c613c3faab876659c6423__25[[#This Row],[Tiempo degustación]]>0, "PAGADA")} -> PAGADA
A4: 20 | B4: Cliente_911 | C4: 1 | D4: 45017.02 | E4: 45017.164 | F4: Mesero_2 | G4: Desayuno | H4: Tarjeta de crédito | I4: 30.87 | J4: Libre | K4: 3 | L4: Brasil | M4: Plato_20, Plato_17, Plato_19, Plato_9 | N4: =_xlfn.XLOOKUP(spaces_3iWczBNnn5rbfoUlE0Jd_uploads_git_blob_9864c7f811c613c3faab876659c6423__25[[#This Row],[Número de Orden]],Cocinadinamica!B5:B773,Cocinadinamica!C5:C773) -> 65 | O4: =spaces_3iWczBNnn5rbfoUlE0Jd_uploads_git_blob_9864c7f811c613c3faab876659c6423__25[[#This Row],[Hora de Llegada]] -> 45017.02 | P4: =spaces_3iWczBNnn5rbfoUlE0Jd_uploads_git_blob_9864c7f811c613c3faab876659c6423__25[[#This Row],[Hora de Llegada]] -> 45017.02 | Q4: =spaces_3iWczBNnn5rbfoUlE0Jd_uploads_git_blob_9864c7f811c613c3faab876659c6423__25[[#This Row],[Hora de Salida]] -> 45017.164 | R4: {=_xlfn.IFS(spaces_3iWczBNnn5rbfoUlE0Jd_uploads_git_blob_9864c7f811c613c3faab876659c6423__25[[#This Row],[Estado de la Mesa]]="Ocupada",(15/1440)+spaces_3iWczBNnn5rbfoUlE0Jd_uploads_git_blob_9864c7f811c613c3faab876659c6423__25[[#This Row],[Hora de salida2]]-spaces_3iWczBNnn5rbfoUlE0Jd_uploads_git_blob_9864c7f811c613c3faab876659c6423__25[[#This Row],[Hora de llegada2]],spaces_3iWczBNnn5rbfoUlE0Jd_uploads_git_blob_9864c7f811c613c3faab876659c6423__25[[#This Row],[Estado de la Mesa]]<>"Ocupada",spaces_3iWczBNnn5rbfoUlE0Jd_uploads_git_blob_9864c7f811c613c3faab876659c6423__25[[#This Row],[Hora de salida2]]-spaces_3iWczBNnn5rbfoUlE0Jd_uploads_git_blob_9864c7f811c613c3faab876659c6423__25[[#This Row],[Hora de llegada2]])} -> 0.14375 | S4: =_xlfn.XLOOKUP(spaces_3iWczBNnn5rbfoUlE0Jd_uploads_git_blob_9864c7f811c613c3faab876659c6423__25[[#This Row],[Número de Orden]],Cocinadinamica!E5:E773,Cocinadinamica!F5:F773)/1440 -> 0.0875 | T4: {=_xlfn.IFS((spaces_3iWczBNnn5rbfoUlE0Jd_uploads_git_blob_9864c7f811c613c3faab876659c6423__25[[#This Row],[Tiempo de permanencia]]-spaces_3iWczBNnn5rbfoUlE0Jd_uploads_git_blob_9864c7f811c613c3faab876659c6423__25[[#This Row],[Tiempo de preparación total]])>0,spaces_3iWczBNnn5rbfoUlE0Jd_uploads_git_blob_9864c7f811c613c3faab876659c6423__25[[#This Row],[Tiempo de permanencia]]-spaces_3iWczBNnn5rbfoUlE0Jd_uploads_git_blob_9864c7f811c613c3faab876659c6423__25[[#This Row],[Tiempo de preparación total]],spaces_3iWczBNnn5rbfoUlE0Jd_uploads_git_blob_9864c7f811c613c3faab876659c6423__25[[#This Row],[Tiempo de permanencia]]-spaces_3iWczBNnn5rbfoUlE0Jd_uploads_git_blob_9864c7f811c613c3faab876659c6423__25[[#This Row],[Tiempo de preparación total]]<0,0)} -> 0.05625 | U4: {=_xlfn.IFS(spaces_3iWczBNnn5rbfoUlE0Jd_uploads_git_blob_9864c7f811c613c3faab876659c6423__25[[#This Row],[Tiempo degustación]]=0,"NO PAGADA",spaces_3iWczBNnn5rbfoUlE0Jd_uploads_git_blob_9864c7f811c613c3faab876659c6423__25[[#This Row],[Tiempo degustación]]>0, "PAGADA")} -> PAGADA
A5: 3 | B5: Cliente_129 | C5: 1 | D5: 45017.127 | E5: 45017.188 | F5: Mesero_5 | G5: Almuerzo | H5: Tarjeta de crédito | I5: 34.68 | J5: Libre | K5: 4 | L5: Paraguay | M5: Plato_11, Plato_16 | N5: =_xlfn.XLOOKUP(spaces_3iWczBNnn5rbfoUlE0Jd_uploads_git_blob_9864c7f811c613c3faab876659c6423__25[[#This Row],[Número de Orden]],Cocinadinamica!B6:B774,Cocinadinamica!C6:C774) -> 75 | O5: =spaces_3iWczBNnn5rbfoUlE0Jd_uploads_git_blob_9864c7f811c613c3faab876659c6423__25[[#This Row],[Hora de Llegada]] -> 45017.127 | P5: =spaces_3iWczBNnn5rbfoUlE0Jd_uploads_git_blob_9864c7f811c613c3faab876659c6423__25[[#This Row],[Hora de Llegada]] -> 45017.127 | Q5: =spaces_3iWczBNnn5rbfoUlE0Jd_uploads_git_blob_9864c7f811c613c3faab876659c6423__25[[#This Row],[Hora de Salida]] -> 45017.188 | R5: {=_xlfn.IFS(spaces_3iWczBNnn5rbfoUlE0Jd_uploads_git_blob_9864c7f811c613c3faab876659c6423__25[[#This Row],[Estado de la Mesa]]="Ocupada",(15/1440)+spaces_3iWczBNnn5rbfoUlE0Jd_uploads_git_blob_9864c7f811c613c3faab876659c6423__25[[#This Row],[Hora de salida2]]-spaces_3iWczBNnn5rbfoUlE0Jd_uploads_git_blob_9864c7f811c613c3faab876659c6423__25[[#This Row],[Hora de llegada2]],spaces_3iWczBNnn5rbfoUlE0Jd_uploads_git_blob_9864c7f811c613c3faab876659c6423__25[[#This Row],[Estado de la Mesa]]<>"Ocupada",spaces_3iWczBNnn5rbfoUlE0Jd_uploads_git_blob_9864c7f811c613c3faab876659c6423__25[[#This Row],[Hora de salida2]]-spaces_3iWczBNnn5rbfoUlE0Jd_uploads_git_blob_9864c7f811c613c3faab876659c6423__25[[#This Row],[Hora de llegada2]])} -> 0.061111111 | S5: =_xlfn.XLOOKUP(spaces_3iWczBNnn5rbfoUlE0Jd_uploads_git_blob_9864c7f811c613c3faab876659c6423__25[[#This Row],[Número de Orden]],Cocinadinamica!E6:E774,Cocinadinamica!F6:F774)/1440 -> 0.027777778 | T5: {=_xlfn.IFS((spaces_3iWczBNnn5rbfoUlE0Jd_uploads_git_blob_9864c7f811c613c3faab876659c6423__25[[#This Row],[Tiempo de permanencia]]-spaces_3iWczBNnn5rbfoUlE0Jd_uploads_git_blob_9864c7f811c613c3faab876659c6423__25[[#This Row],[Tiempo de preparación total]])>0,spaces_3iWczBNnn5rbfoUlE0Jd_uploads_git_blob_9864c7f811c613c3faab876659c6423__25[[#This Row],[Tiempo de permanencia]]-spaces_3iWczBNnn5rbfoUlE0Jd_uploads_git_blob_9864c7f811c613c3faab876659c6423__25[[#This Row],[Tiempo de preparación total]],spaces_3iWczBNnn5rbfoUlE0Jd_uploads_git_blob_9864c7f811c613c3faab876659c6423__25[[#This Row],[Tiempo de permanencia]]-spaces_3iWczBNnn5rbfoUlE0Jd_uploads_git_blob_9864c7f811c613c3faab876659c6423__25[[#This Row],[Tiempo de preparación total]]<0,0)} -> 0.033333333 | U5: {=_xlfn.IFS(spaces_3iWczBNnn5rbfoUlE0Jd_uploads_git_blob_9864c7f811c613c3faab876659c6423__25[[#This Row],[Tiempo degustación]]=0,"NO PAGADA",spaces_3iWczBNnn5rbfoUlE0Jd_uploads_git_blob_9864c7f811c613c3faab876659c6423__25[[#This Row],[Tiempo degustación]]>0, "PAGADA")} -> PAGADA
A6: 8 | B6: Cliente_938 | C6: 2 | D6: 45017.001 | E6: 45017.088 | F6: Mesero_4 | G6: Almuerzo | H6: Tarjeta de crédito | I6: 24.33 | J6: Libre | K6: 5 | L6: Perú | M6: Plato_12, Plato_7 | N6: =_xlfn.XLOOKUP(spaces_3iWczBNnn5rbfoUlE0Jd_uploads_git_blob_9864c7f811c613c3faab876659c6423__25[[#This Row],[Número de Orden]],Cocinadinamica!B7:B775,Cocinadinamica!C7:C775) -> 28 | O6: =spaces_3iWczBNnn5rbfoUlE0Jd_uploads_git_blob_9864c7f811c613c3faab876659c6423__25[[#This Row],[Hora de Llegada]] -> 45017.001 | P6: =spaces_3iWczBNnn5rbfoUlE0Jd_uploads_git_blob_9864c7f811c613c3faab876659c6423__25[[#This Row],[Hora de Llegada]] -> 45017.001 | Q6: =spaces_3iWczBNnn5rbfoUlE0Jd_uploads_git_blob_9864c7f811c613c3faab876659c6423__25[[#This Row],[Hora de Salida]] -> 45017.088 | R6: {=_xlfn.IFS(spaces_3iWczBNnn5rbfoUlE0Jd_uploads_git_blob_9864c7f811c613c3faab876659c6423__25[[#This Row],[Estado de la Mesa]]="Ocupada",(15/1440)+spaces_3iWczBNnn5rbfoUlE0Jd_uploads_git_blob_9864c7f811c613c3faab876659c6423__25[[#This Row],[Hora de salida2]]-spaces_3iWczBNnn5rbfoUlE0Jd_uploads_git_blob_9864c7f811c613c3faab876659c6423__25[[#This Row],[Hora de llegada2]],spaces_3iWczBNnn5rbfoUlE0Jd_uploads_git_blob_9864c7f811c613c3faab876659c6423__25[[#This Row],[Estado de la Mesa]]<>"Ocupada",spaces_3iWczBNnn5rbfoUlE0Jd_uploads_git_blob_9864c7f811c613c3faab876659c6423__25[[#This Row],[Hora de salida2]]-spaces_3iWczBNnn5rbfoUlE0Jd_uploads_git_blob_9864c7f811c613c3faab876659c6423__25[[#This Row],[Hora de llegada2]])} -> 0.086805556 | S6: =_xlfn.XLOOKUP(spaces_3iWczBNnn5rbfoUlE0Jd_uploads_git_blob_9864c7f811c613c3faab876659c6423__25[[#This Row],[Número de Orden]],Cocinadinamica!E7:E775,Cocinadinamica!F7:F775)/1440 -> 0.011805556 | T6: {=_xlfn.IFS((spaces_3iWczBNnn5rbfoUlE0Jd_uploads_git_blob_9864c7f811c613c3faab876659c6423__25[[#This Row],[Tiempo de permanencia]]-spaces_3iWczBNnn5rbfoUlE0Jd_uploads_git_blob_9864c7f811c613c3faab876659c6423__25[[#This Row],[Tiempo de preparación total]])>0,spaces_3iWczBNnn5rbfoUlE0Jd_uploads_git_blob_9864c7f811c613c3faab876659c6423__25[[#This Row],[Tiempo de permanencia]]-spaces_3iWczBNnn5rbfoUlE0Jd_uploads_git_blob_9864c7f811c613c3faab876659c6423__25[[#This Row],[Tiempo de preparación total]],spaces_3iWczBNnn5rbfoUlE0Jd_uploads_git_blob_9864c7f811c613c3faab876659c6423__25[[#This Row],[Tiempo de permanencia]]-spaces_3iWczBNnn5rbfoUlE0Jd_uploads_git_blob_9864c7f811c613c3faab876659c6423__25[[#This Row],[Tiempo de preparación total]]<0,0)} -> 0.075 | U6: {=_xlfn.IFS(spaces_3iWczBNnn5rbfoUlE0Jd_uploads_git_blob_9864c7f811c613c3faab876659c6423__25[[#This Row],[Tiempo degustación]]=0,"NO PAGADA",spaces_3iWczBNnn5rbfoUlE0Jd_uploads_git_blob_9864c7f811c613c3faab876659c6423__25[[#This Row],[Tiempo degustación]]>0, "PAGADA")} -> PAGADA
A7: 7 | B7: Cliente_965 | C7: 5 | D7: 45017.058 | E7: 45017.147 | F7: Mesero_4 | G7: Cena | H7: Tarjeta de crédito | I7: 26.57 | J7: Libre | K7: 6 | L7: Perú | M7: Plato_8 | N7: =_xlfn.XLOOKUP(spaces_3iWczBNnn5rbfoUlE0Jd_uploads_git_blob_9864c7f811c613c3faab876659c6423__25[[#This Row],[Número de Orden]],Cocinadinamica!B8:B776,Cocinadinamica!C8:C776) -> 28 | O7: =spaces_3iWczBNnn5rbfoUlE0Jd_uploads_git_blob_9864c7f811c613c3faab876659c6423__25[[#This Row],[Hora de Llegada]] -> 45017.058 | P7: =spaces_3iWczBNnn5rbfoUlE0Jd_uploads_git_blob_9864c7f811c613c3faab876659c6423__25[[#This Row],[Hora de Llegada]] -> 45017.058 | Q7: =spaces_3iWczBNnn5rbfoUlE0Jd_uploads_git_blob_9864c7f811c613c3faab876659c6423__25[[#This Row],[Hora de Salida]] -> 45017.147 | R7: {=_xlfn.IFS(spaces_3iWczBNnn5rbfoUlE0Jd_uploads_git_blob_9864c7f811c613c3faab876659c6423__25[[#This Row],[Estado de la Mesa]]="Ocupada",(15/1440)+spaces_3iWczBNnn5rbfoUlE0Jd_uploads_git_blob_9864c7f811c613c3faab876659c6423__25[[#This Row],[Hora de salida2]]-spaces_3iWczBNnn5rbfoUlE0Jd_uploads_git_blob_9864c7f811c613c3faab876659c6423__25[[#This Row],[Hora de llegada2]],spaces_3iWczBNnn5rbfoUlE0Jd_uploads_git_blob_9864c7f811c613c3faab876659c6423__25[[#This Row],[Estado de la Mesa]]<>"Ocupada",spaces_3iWczBNnn5rbfoUlE0Jd_uploads_git_blob_9864c7f811c613c3faab876659c6423__25[[#This Row],[Hora de salida2]]-spaces_3iWczBNnn5rbfoUlE0Jd_uploads_git_blob_9864c7f811c613c3faab876659c6423__25[[#This Row],[Hora de llegada2]])} -> 0.088888889 | S7: =_xlfn.XLOOKUP(spaces_3iWczBNnn5rbfoUlE0Jd_uploads_git_blob_9864c7f811c613c3faab876659c6423__25[[#This Row],[Número de Orden]],Cocinadinamica!E8:E776,Cocinadinamica!F8:F776)/1440 -> 0.0076388889 | T7: {=_xlfn.IFS((spaces_3iWczBNnn5rbfoUlE0Jd_uploads_git_blob_9864c7f811c613c3faab876659c6423__25[[#This Row],[Tiempo de permanencia]]-spaces_3iWczBNnn5rbfoUlE0Jd_uploads_git_blob_9864c7f811c613c3faab876659c6423__25[[#This Row],[Tiempo de preparación total]])>0,spaces_3iWczBNnn5rbfoUlE0Jd_uploads_git_blob_9864c7f811c613c3faab876659c6423__25[[#This Row],[Tiempo de permanencia]]-spaces_3iWczBNnn5rbfoUlE0Jd_uploads_git_blob_9864c7f811c613c3faab876659c6423__25[[#This Row],[Tiempo de preparación total]],spaces_3iWczBNnn5rbfoUlE0Jd_uploads_git_blob_9864c7f811c613c3faab876659c6423__25[[#This Row],[Tiempo de permanencia]]-spaces_3iWczBNnn5rbfoUlE0Jd_uploads_git_blob_9864c7f811c613c3faab876659c6423__25[[#This Row],[Tiempo de preparación total]]<0,0)} -> 0.08125 | U7: {=_xlfn.IFS(spaces_3iWczBNnn5rbfoUlE0Jd_uploads_git_blob_9864c7f811c613c3faab876659c6423__25[[#This Row],[Tiempo degustación]]=0,"NO PAGADA",spaces_3iWczBNnn5rbfoUlE0Jd_uploads_git_blob_9864c7f811c613c3faab876659c6423__25[[#This Row],[Tiempo degustación]]>0, "PAGADA")} -> PAGADA
A8: 17 | B8: Cliente_306 | C8: 6 | D8: 45017.081 | E8: 45017.182 | F8: Mesero_2 | G8: Cena | H8: Tarjeta de crédito | I8: 10.54 | J8: Ocupada | K8: 7 | L8: Venezuela | M8: Plato_15, Plato_19 | N8: =_xlfn.XLOOKUP(spaces_3iWczBNnn5rbfoUlE0Jd_uploads_git_blob_9864c7f811c613c3faab876659c6423__25[[#This Row],[Número de Orden]],Cocinadinamica!B9:B777,Cocinadinamica!C9:C777) -> 68 | O8: =spaces_3iWczBNnn5rbfoUlE0Jd_uploads_git_blob_9864c7f811c613c3faab876659c6423__25[[#This Row],[Hora de Llegada]] -> 45017.081 | P8: =spaces_3iWczBNnn5rbfoUlE0Jd_uploads_git_blob_9864c7f811c613c3faab876659c6423__25[[#This Row],[Hora de Llegada]] -> 45017.081 | Q8: =spaces_3iWczBNnn5rbfoUlE0Jd_uploads_git_blob_9864c7f811c613c3faab876659c6423__25[[#This Row],[Hora de Salida]] -> 45017.182 | R8: {=_xlfn.IFS(spaces_3iWczBNnn5rbfoUlE0Jd_uploads_git_blob_9864c7f811c613c3faab876659c6423__25[[#This Row],[Estado de la Mesa]]="Ocupada",(15/1440)+spaces_3iWczBNnn5rbfoUlE0Jd_uploads_git_blob_9864c7f811c613c3faab876659c6423__25[[#This Row],[Hora de salida2]]-spaces_3iWczBNnn5rbfoUlE0Jd_uploads_git_blob_9864c7f811c613c3faab876659c6423__25[[#This Row],[Hora de llegada2]],spaces_3iWczBNnn5rbfoUlE0Jd_uploads_git_blob_9864c7f811c613c3faab876659c6423__25[[#This Row],[Estado de la Mesa]]<>"Ocupada",spaces_3iWczBNnn5rbfoUlE0Jd_uploads_git_blob_9864c7f811c613c3faab876659c6423__25[[#This Row],[Hora de salida2]]-spaces_3iWczBNnn5rbfoUlE0Jd_uploads_git_blob_9864c7f811c613c3faab876659c6423__25[[#This Row],[Hora de llegada2]])} -> 0.11111111 | S8: =_xlfn.XLOOKUP(spaces_3iWczBNnn5rbfoUlE0Jd_uploads_git_blob_9864c7f811c613c3faab876659c6423__25[[#This Row],[Número de Orden]],Cocinadinamica!E9:E777,Cocinadinamica!F9:F777)/1440 -> 0.028472222 | T8: {=_xlfn.IFS((spaces_3iWczBNnn5rbfoUlE0Jd_uploads_git_blob_9864c7f811c613c3faab876659c6423__25[[#This Row],[Tiempo de permanencia]]-spaces_3iWczBNnn5rbfoUlE0Jd_uploads_git_blob_9864c7f811c613c3faab876659c6423__25[[#This Row],[Tiempo de preparación total]])>0,spaces_3iWczBNnn5rbfoUlE0Jd_uploads_git_blob_9864c7f811c613c3faab876659c6423__25[[#This Row],[Tiempo de permanencia]]-spaces_3iWczBNnn5rbfoUlE0Jd_uploads_git_blob_9864c7f811c613c3faab876659c6423__25[[#This Row],[Tiempo de preparación total]],spaces_3iWczBNnn5rbfoUlE0Jd_uploads_git_blob_9864c7f811c613c3faab876659c6423__25[[#This Row],[Tiempo de permanencia]]-spaces_3iWczBNnn5rbfoUlE0Jd_uploads_git_blob_9864c7f811c613c3faab876659c6423__25[[#This Row],[Tiempo de preparación total]]<0,0)} -> 0.082638889 | U8: {=_xlfn.IFS(spaces_3iWczBNnn5rbfoUlE0Jd_uploads_git_blob_9864c7f811c613c3faab876659c6423__25[[#This Row],[Tiempo degustación]]=0,"NO PAGADA",spaces_3iWczBNnn5rbfoUlE0Jd_uploads_git_blob_9864c7f811c613c3faab876659c6423__25[[#This Row],[Tiempo degustación]]>0, "PAGADA")} -> PAGADA
A9: 11 | B9: Cliente_974 | C9: 1 | D9: 45017.091 | E9: 45017.201 | F9: Mesero_2 | G9: Desayuno | H9: Tarjeta de crédito | I9: 49.18 | J9: Reservada | K9: 8 | L9: Paraguay | M9: Plato_5, Plato_16, Plato_20 | N9: =_xlfn.XLOOKUP(spaces_3iWczBNnn5rbfoUlE0Jd_uploads_git_blob_9864c7f811c613c3faab876659c6423__25[[#This Row],[Número de Orden]],Cocinadinamica!B10:B778,Cocinadinamica!C10:C778) -> 96 | O9: =spaces_3iWczBNnn5rbfoUlE0Jd_uploads_git_blob_9864c7f811c613c3faab876659c6423__25[[#This Row],[Hora de Llegada]] -> 45017.091 | P9: =spaces_3iWczBNnn5rbfoUlE0Jd_uploads_git_blob_9864c7f811c613c3faab876659c6423__25[[#This Row],[Hora de Llegada]] -> 45017.091 | Q9: =spaces_3iWczBNnn5rbfoUlE0Jd_uploads_git_blob_9864c7f811c613c3faab876659c6423__25[[#This Row],[Hora de Salida]] -> 45017.201 | R9: {=_xlfn.IFS(spaces_3iWczBNnn5rbfoUlE0Jd_uploads_git_blob_9864c7f811c613c3faab876659c6423__25[[#This Row],[Estado de la Mesa]]="Ocupada",(15/1440)+spaces_3iWczBNnn5rbfoUlE0Jd_uploads_git_blob_9864c7f811c613c3faab876659c6423__25[[#This Row],[Hora de salida2]]-spaces_3iWczBNnn5rbfoUlE0Jd_uploads_git_blob_9864c7f811c613c3faab876659c6423__25[[#This Row],[Hora de llegada2]],spaces_3iWczBNnn5rbfoUlE0Jd_uploads_git_blob_9864c7f811c613c3faab876659c6423__25[[#This Row],[Estado de la Mesa]]<>"Ocupada",spaces_3iWczBNnn5rbfoUlE0Jd_uploads_git_blob_9864c7f811c613c3faab876659c6423__25[[#This Row],[Hora de salida2]]-spaces_3iWczBNnn5rbfoUlE0Jd_uploads_git_blob_9864c7f811c613c3faab876659c6423__25[[#This Row],[Hora de llegada2]])} -> 0.10972222 | S9: =_xlfn.XLOOKUP(spaces_3iWczBNnn5rbfoUlE0Jd_uploads_git_blob_9864c7f811c613c3faab876659c6423__25[[#This Row],[Número de Orden]],Cocinadinamica!E10:E778,Cocinadinamica!F10:F778)/1440 -> 0.038194444 | T9: {=_xlfn.IFS((spaces_3iWczBNnn5rbfoUlE0Jd_uploads_git_blob_9864c7f811c613c3faab876659c6423__25[[#This Row],[Tiempo de permanencia]]-spaces_3iWczBNnn5rbfoUlE0Jd_uploads_git_blob_9864c7f811c613c3faab876659c6423__25[[#This Row],[Tiempo de preparación total]])>0,spaces_3iWczBNnn5rbfoUlE0Jd_uploads_git_blob_9864c7f811c613c3faab876659c6423__25[[#This Row],[Tiempo de permanencia]]-spaces_3iWczBNnn5rbfoUlE0Jd_uploads_git_blob_9864c7f811c613c3faab876659c6423__25[[#This Row],[Tiempo de preparación total]],spaces_3iWczBNnn5rbfoUlE0Jd_uploads_git_blob_9864c7f811c613c3faab876659c6423__25[[#This Row],[Tiempo de permanencia]]-spaces_3iWczBNnn5rbfoUlE0Jd_uploads_git_blob_9864c7f811c613c3faab876659c6423__25[[#This Row],[Tiempo de preparación total]]<0,0)} -> 0.071527778 | U9: {=_xlfn.IFS(spaces_3iWczBNnn5rbfoUlE0Jd_uploads_git_blob_9864c7f811c613c3faab876659c6423__25[[#This Row],[Tiempo degustación]]=0,"NO PAGADA",spaces_3iWczBNnn5rbfoUlE0Jd_uploads_git_blob_9864c7f811c613c3faab876659c6423__25[[#This Row],[Tiempo degustación]]>0, "PAGADA")} -> PAGADA
A10: 15 | B10: Cliente_740 | C10: 5 | D10: 45017.085 | E10: 45017.184 | F10: Mesero_2 | G10: Almuerzo | H10: Tarjeta de débito | I10: 46.85 | J10: Libre | K10: 9 | L10: Bolivia | M10: Plato_2, Plato_7, Plato_12, Plato_15 | N10: =_xlfn.XLOOKUP(spaces_3iWczBNnn5rbfoUlE0Jd_uploads_git_blob_9864c7f811c613c3faab876659c6423__25[[#This Row],[Número de Orden]],Cocinadinamica!B11:B779,Cocinadinamica!C11:C779) -> 69 | O10: =spaces_3iWczBNnn5rbfoUlE0Jd_uploads_git_blob_9864c7f811c613c3faab876659c6423__25[[#This Row],[Hora de Llegada]] -> 45017.085 | P10: =spaces_3iWczBNnn5rbfoUlE0Jd_uploads_git_blob_9864c7f811c613c3faab876659c6423__25[[#This Row],[Hora de Llegada]] -> 45017.085 | Q10: =spaces_3iWczBNnn5rbfoUlE0Jd_uploads_git_blob_9864c7f811c613c3faab876659c6423__25[[#This Row],[Hora de Salida]] -> 45017.184 | R10: {=_xlfn.IFS(spaces_3iWczBNnn5rbfoUlE0Jd_uploads_git_blob_9864c7f811c613c3faab876659c6423__25[[#This Row],[Estado de la Mesa]]="Ocupada",(15/1440)+spaces_3iWczBNnn5rbfoUlE0Jd_uploads_git_blob_9864c7f811c613c3faab876659c6423__25[[#This Row],[Hora de salida2]]-spaces_3iWczBNnn5rbfoUlE0Jd_uploads_git_blob_9864c7f811c613c3faab876659c6423__25[[#This Row],[Hora de llegada2]],spaces_3iWczBNnn5rbfoUlE0Jd_uploads_git_blob_9864c7f811c613c3faab876659c6423__25[[#This Row],[Estado de la Mesa]]<>"Ocupada",spaces_3iWczBNnn5rbfoUlE0Jd_uploads_git_blob_9864c7f811c613c3faab876659c6423__25[[#This Row],[Hora de salida2]]-spaces_3iWczBNnn5rbfoUlE0Jd_uploads_git_blob_9864c7f811c613c3faab876659c6423__25[[#This Row],[Hora de llegada2]])} -> 0.098611111 | S10: =_xlfn.XLOOKUP(spaces_3iWczBNnn5rbfoUlE0Jd_uploads_git_blob_9864c7f811c613c3faab876659c6423__25[[#This Row],[Número de Orden]],Cocinadinamica!E11:E779,Cocinadinamica!F11:F779)/1440 -> 0.10138889 | T10: {=_xlfn.IFS((spaces_3iWczBNnn5rbfoUlE0Jd_uploads_git_blob_9864c7f811c613c3faab876659c6423__25[[#This Row],[Tiempo de permanencia]]-spaces_3iWczBNnn5rbfoUlE0Jd_uploads_git_blob_9864c7f811c613c3faab876659c6423__25[[#This Row],[Tiempo de preparación total]])>0,spaces_3iWczBNnn5rbfoUlE0Jd_uploads_git_blob_9864c7f811c613c3faab876659c6423__25[[#This Row],[Tiempo de permanencia]]-spaces_3iWczBNnn5rbfoUlE0Jd_uploads_git_blob_9864c7f811c613c3faab876659c6423__25[[#This Row],[Tiempo de preparación total]],spaces_3iWczBNnn5rbfoUlE0Jd_uploads_git_blob_9864c7f811c613c3faab876659c6423__25[[#This Row],[Tiempo de permanencia]]-spaces_3iWczBNnn5rbfoUlE0Jd_uploads_git_blob_9864c7f811c613c3faab876659c6423__25[[#This Row],[Tiempo de preparación total]]<0,0)} -> 0 | U10: {=_xlfn.IFS(spaces_3iWczBNnn5rbfoUlE0Jd_uploads_git_blob_9864c7f811c613c3faab876659c6423__25[[#This Row],[Tiempo degustación]]=0,"NO PAGADA",spaces_3iWczBNnn5rbfoUlE0Jd_uploads_git_blob_9864c7f811c613c3faab876659c6423__25[[#This Row],[Tiempo degustación]]>0, "PAGADA")} -> NO PAGADA
A11: 17 | B11: Cliente_33 | C11: 1 | D11: 45017.001 | E11: 45017.078 | F11: Mesero_4 | G11: Almuerzo | H11: Tarjeta de crédito | I11: 16.6 | J11: Ocupada | K11: 10 | L11: Uruguay | M11: Plato_18, Plato_20 | N11: =_xlfn.XLOOKUP(spaces_3iWczBNnn5rbfoUlE0Jd_uploads_git_blob_9864c7f811c613c3faab876659c6423__25[[#This Row],[Número de Orden]],Cocinadinamica!B12:B780,Cocinadinamica!C12:C780) -> 58 | O11: =spaces_3iWczBNnn5rbfoUlE0Jd_uploads_git_blob_9864c7f811c613c3faab876659c6423__25[[#This Row],[Hora de Llegada]] -> 45017.001 | P11: =spaces_3iWczBNnn5rbfoUlE0Jd_uploads_git_blob_9864c7f811c613c3faab876659c6423__25[[#This Row],[Hora de Llegada]] -> 45017.001 | Q11: =spaces_3iWczBNnn5rbfoUlE0Jd_uploads_git_blob_9864c7f811c613c3faab876659c6423__25[[#This Row],[Hora de Salida]] -> 45017.078 | R11: {=_xlfn.IFS(spaces_3iWczBNnn5rbfoUlE0Jd_uploads_git_blob_9864c7f811c613c3faab876659c6423__25[[#This Row],[Estado de la Mesa]]="Ocupada",(15/1440)+spaces_3iWczBNnn5rbfoUlE0Jd_uploads_git_blob_9864c7f811c613c3faab876659c6423__25[[#This Row],[Hora de salida2]]-spaces_3iWczBNnn5rbfoUlE0Jd_uploads_git_blob_9864c7f811c613c3faab876659c6423__25[[#This Row],[Hora de llegada2]],spaces_3iWczBNnn5rbfoUlE0Jd_uploads_git_blob_9864c7f811c613c3faab876659c6423__25[[#This Row],[Estado de la Mesa]]<>"Ocupada",spaces_3iWczBNnn5rbfoUlE0Jd_uploads_git_blob_9864c7f811c613c3faab876659c6423__25[[#This Row],[Hora de salida2]]-spaces_3iWczBNnn5rbfoUlE0Jd_uploads_git_blob_9864c7f811c613c3faab876659c6423__25[[#This Row],[Hora de llegada2]])} -> 0.0875 | S11: =_xlfn.XLOOKUP(spaces_3iWczBNnn5rbfoUlE0Jd_uploads_git_blob_9864c7f811c613c3faab876659c6423__25[[#This Row],[Número de Orden]],Cocinadinamica!E12:E780,Cocinadinamica!F12:F780)/1440 -> 0.020138889 | T11: {=_xlfn.IFS((spaces_3iWczBNnn5rbfoUlE0Jd_uploads_git_blob_9864c7f811c613c3faab876659c6423__25[[#This Row],[Tiempo de permanencia]]-spaces_3iWczBNnn5rbfoUlE0Jd_uploads_git_blob_9864c7f811c613c3faab876659c6423__25[[#This Row],[Tiempo de preparación total]])>0,spaces_3iWczBNnn5rbfoUlE0Jd_uploads_git_blob_9864c7f811c613c3faab876659c6423__25[[#This Row],[Tiempo de permanencia]]-spaces_3iWczBNnn5rbfoUlE0Jd_uploads_git_blob_9864c7f811c613c3faab876659c6423__25[[#This Row],[Tiempo de preparación total]],spaces_3iWczBNnn5rbfoUlE0Jd_uploads_git_blob_9864c7f811c613c3faab876659c6423__25[[#This Row],[Tiempo de permanencia]]-spaces_3iWczBNnn5rbfoUlE0Jd_uploads_git_blob_9864c7f811c613c3faab876659c6423__25[[#This Row],[Tiempo de preparación total]]<0,0)} -> 0.067361111 | U11: {=_xlfn.IFS(spaces_3iWczBNnn5rbfoUlE0Jd_uploads_git_blob_9864c7f811c613c3faab876659c6423__25[[#This Row],[Tiempo degustación]]=0,"NO PAGADA",spaces_3iWczBNnn5rbfoUlE0Jd_uploads_git_blob_9864c7f811c613c3faab876659c6423__25[[#This Row],[Tiempo degustación]]>0, "PAGADA")} -> PAGADA
A12: 14 | B12: Cliente_881 | C12: 1 | D12: 45017.157 | E12: 45017.273 | F12: Mesero_1 | G12: Almuerzo | H12: Tarjeta de crédito | I12: 32.89 | J12: Libre | K12: 11 | L12: Perú | M12: Plato_16, Plato_2 | N12: =_xlfn.XLOOKUP(spaces_3iWczBNnn5rbfoUlE0Jd_uploads_git_blob_9864c7f811c613c3faab876659c6423__25[[#This Row],[Número de Orden]],Cocinadinamica!B13:B781,Cocinadinamica!C13:C781) -> 36 | O12: =spaces_3iWczBNnn5rbfoUlE0Jd_uploads_git_blob_9864c7f811c613c3faab876659c6423__25[[#This Row],[Hora de Llegada]] -> 45017.157 | P12: =spaces_3iWczBNnn5rbfoUlE0Jd_uploads_git_blob_9864c7f811c613c3faab876659c6423__25[[#This Row],[Hora de Llegada]] -> 45017.157 | Q12: =spaces_3iWczBNnn5rbfoUlE0Jd_uploads_git_blob_9864c7f811c613c3faab876659c6423__25[[#This Row],[Hora de Salida]] -> 45017.273 | R12: {=_xlfn.IFS(spaces_3iWczBNnn5rbfoUlE0Jd_uploads_git_blob_9864c7f811c613c3faab876659c6423__25[[#This Row],[Estado de la Mesa]]="Ocupada",(15/1440)+spaces_3iWczBNnn5rbfoUlE0Jd_uploads_git_blob_9864c7f811c613c3faab876659c6423__25[[#This Row],[Hora de salida2]]-spaces_3iWczBNnn5rbfoUlE0Jd_uploads_git_blob_9864c7f811c613c3faab876659c6423__25[[#This Row],[Hora de llegada2]],spaces_3iWczBNnn5rbfoUlE0Jd_uploads_git_blob_9864c7f811c613c3faab876659c6423__25[[#This Row],[Estado de la Mesa]]<>"Ocupada",spaces_3iWczBNnn5rbfoUlE0Jd_uploads_git_blob_9864c7f811c613c3faab876659c6423__25[[#This Row],[Hora de salida2]]-spaces_3iWczBNnn5rbfoUlE0Jd_uploads_git_blob_9864c7f811c613c3faab876659c6423__25[[#This Row],[Hora de llegada2]])} -> 0.11597222 | S12: =_xlfn.XLOOKUP(spaces_3iWczBNnn5rbfoUlE0Jd_uploads_git_blob_9864c7f811c613c3faab876659c6423__25[[#This Row],[Número de Orden]],Cocinadinamica!E13:E781,Cocinadinamica!F13:F781)/1440 -> 0.038888889 | T12: {=_xlfn.IFS((spaces_3iWczBNnn5rbfoUlE0Jd_uploads_git_blob_9864c7f811c613c3faab876659c6423__25[[#This Row],[Tiempo de permanencia]]-spaces_3iWczBNnn5rbfoUlE0Jd_uploads_git_blob_9864c7f811c613c3faab876659c6423__25[[#This Row],[Tiempo de preparación total]])>0,spaces_3iWczBNnn5rbfoUlE0Jd_uploads_git_blob_9864c7f811c613c3faab876659c6423__25[[#This Row],[Tiempo de permanencia]]-spaces_3iWczBNnn5rbfoUlE0Jd_uploads_git_blob_9864c7f811c613c3faab876659c6423__25[[#This Row],[Tiempo de preparación total]],spaces_3iWczBNnn5rbfoUlE0Jd_uploads_git_blob_9864c7f811c613c3faab876659c6423__25[[#This Row],[Tiempo de permanencia]]-spaces_3iWczBNnn5rbfoUlE0Jd_uploads_git_blob_9864c7f811c613c3faab876659c6423__25[[#This Row],[Tiempo de preparación total]]<0,0)} -> 0.077083333 | U12: {=_xlfn.IFS(spaces_3iWczBNnn5rbfoUlE0Jd_uploads_git_blob_9864c7f811c613c3faab876659c6423__25[[#This Row],[Tiempo degustación]]=0,"NO PAGADA",spaces_3iWczBNnn5rbfoUlE0Jd_uploads_git_blob_9864c7f811c613c3faab876659c6423__25[[#This Row],[Tiempo degustación]]>0, "PAGADA")} -> PAGADA
A13: 14 | B13: Cliente_890 | C13: 6 | D13: 45017.003 | E13: 45017.141 | F13: Mesero_4 | G13: Cena | H13: Tarjeta de crédito | I13: 45.27 | J13: Ocupada | K13: 12 | L13: Colombia | M13: Plato_16, Plato_19, Plato_8, Plato_20 | N13: =_xlfn.XLOOKUP(spaces_3iWczBNnn5rbfoUlE0Jd_uploads_git_blob_9864c7f811c613c3faab876659c6423__25[[#This Row],[Número de Orden]],Cocinadinamica!B14:B782,Cocinadinamica!C14:C782) -> 127 | O13: =spaces_3iWczBNnn5rbfoUlE0Jd_uploads_git_blob_9864c7f811c613c3faab876659c6423__25[[#This Row],[Hora de Llegada]] -> 45017.003 | P13: =spaces_3iWczBNnn5rbfoUlE0Jd_uploads_git_blob_9864c7f811c613c3faab876659c6423__25[[#This Row],[Hora de Llegada]] -> 45017.003 | Q13: =spaces_3iWczBNnn5rbfoUlE0Jd_uploads_git_blob_9864c7f811c613c3faab876659c6423__25[[#This Row],[Hora de Salida]] -> 45017.141 | R13: {=_xlfn.IFS(spaces_3iWczBNnn5rbfoUlE0Jd_uploads_git_blob_9864c7f811c613c3faab876659c6423__25[[#This Row],[Estado de la Mesa]]="Ocupada",(15/1440)+spaces_3iWczBNnn5rbfoUlE0Jd_uploads_git_blob_9864c7f811c613c3faab876659c6423__25[[#This Row],[Hora de salida2]]-spaces_3iWczBNnn5rbfoUlE0Jd_uploads_git_blob_9864c7f811c613c3faab876659c6423__25[[#This Row],[Hora de llegada2]],spaces_3iWczBNnn5rbfoUlE0Jd_uploads_git_blob_9864c7f811c613c3faab876659c6423__25[[#This Row],[Estado de la Mesa]]<>"Ocupada",spaces_3iWczBNnn5rbfoUlE0Jd_uploads_git_blob_9864c7f811c613c3faab876659c6423__25[[#This Row],[Hora de salida2]]-spaces_3iWczBNnn5rbfoUlE0Jd_uploads_git_blob_9864c7f811c613c3faab876659c6423__25[[#This Row],[Hora de llegada2]])} -> 0.14861111 | S13: =_xlfn.XLOOKUP(spaces_3iWczBNnn5rbfoUlE0Jd_uploads_git_blob_9864c7f811c613c3faab876659c6423__25[[#This Row],[Número de Orden]],Cocinadinamica!E14:E782,Cocinadinamica!F14:F782)/1440 -> 0.065972222 | T13: {=_xlfn.IFS((spaces_3iWczBNnn5rbfoUlE0Jd_uploads_git_blob_9864c7f811c613c3faab876659c6423__25[[#This Row],[Tiempo de permanencia]]-spaces_3iWczBNnn5rbfoUlE0Jd_uploads_git_blob_9864c7f811c613c3faab876659c6423__25[[#This Row],[Tiempo de preparación total]])>0,spaces_3iWczBNnn5rbfoUlE0Jd_uploads_git_blob_9864c7f811c613c3faab876659c6423__25[[#This Row],[Tiempo de permanencia]]-spaces_3iWczBNnn5rbfoUlE0Jd_uploads_git_blob_9864c7f811c613c3faab876659c6423__25[[#This Row],[Tiempo de preparación total]],spaces_3iWczBNnn5rbfoUlE0Jd_uploads_git_blob_9864c7f811c613c3faab876659c6423__25[[#This Row],[Tiempo de permanencia]]-spaces_3iWczBNnn5rbfoUlE0Jd_uploads_git_blob_9864c7f811c613c3faab876659c6423__25[[#This Row],[Tiempo de preparación total]]<0,0)} -> 0.082638889 | U13: {=_xlfn.IFS(spaces_3iWczBNnn5rbfoUlE0Jd_uploads_git_blob_9864c7f811c613c3faab876659c6423__25[[#This Row],[Tiempo degustación]]=0,"NO PAGADA",spaces_3iWczBNnn5rbfoUlE0Jd_uploads_git_blob_9864c7f811c613c3faab876659c6423__25[[#This Row],[Tiempo degustación]]>0, "PAGADA")} -> PAGADA
A14: 2 | B14: Cliente_873 | C14: 1 | D14: 45017.131 | E14: 45017.231 | F14: Mesero_5 | G14: Almuerzo | H14: Efectivo | I14: 22.06 | J14: Ocupada | K14: 13 | L14: Brasil | M14: Plato_9 | N14: =_xlfn.XLOOKUP(spaces_3iWczBNnn5rbfoUlE0Jd_uploads_git_blob_9864c7f811c613c3faab876659c6423__25[[#This Row],[Número de Orden]],Cocinadinamica!B15:B783,Cocinadinamica!C15:C783) -> 36 | O14: =spaces_3iWczBNnn5rbfoUlE0Jd_uploads_git_blob_9864c7f811c613c3faab876659c6423__25[[#This Row],[Hora de Llegada]] -> 45017.131 | P14: =spaces_3iWczBNnn5rbfoUlE0Jd_uploads_git_blob_9864c7f811c613c3faab876659c6423__25[[#This Row],[Hora de Llegada]] -> 45017.131 | Q14: =spaces_3iWczBNnn5rbfoUlE0Jd_uploads_git_blob_9864c7f811c613c3faab876659c6423__25[[#This Row],[Hora de Salida]] -> 45017.231 | R14: {=_xlfn.IFS(spaces_3iWczBNnn5rbfoUlE0Jd_uploads_git_blob_9864c7f811c613c3faab876659c6423__25[[#This Row],[Estado de la Mesa]]="Ocupada",(15/1440)+spaces_3iWczBNnn5rbfoUlE0Jd_uploads_git_blob_9864c7f811c613c3faab876659c6423__25[[#This Row],[Hora de salida2]]-spaces_3iWczBNnn5rbfoUlE0Jd_uploads_git_blob_9864c7f811c613c3faab876659c6423__25[[#This Row],[Hora de llegada2]],spaces_3iWczBNnn5rbfoUlE0Jd_uploads_git_blob_9864c7f811c613c3faab876659c6423__25[[#This Row],[Estado de la Mesa]]<>"Ocupada",spaces_3iWczBNnn5rbfoUlE0Jd_uploads_git_blob_9864c7f811c613c3faab876659c6423__25[[#This Row],[Hora de salida2]]-spaces_3iWczBNnn5rbfoUlE0Jd_uploads_git_blob_9864c7f811c613c3faab876659c6423__25[[#This Row],[Hora de llegada2]])} -> 0.10972222 | S14: =_xlfn.XLOOKUP(spaces_3iWczBNnn5rbfoUlE0Jd_uploads_git_blob_9864c7f811c613c3faab876659c6423__25[[#This Row],[Número de Orden]],Cocinadinamica!E15:E783,Cocinadinamica!F15:F783)/1440 -> 0.040972222 | T14: {=_xlfn.IFS((spaces_3iWczBNnn5rbfoUlE0Jd_uploads_git_blob_9864c7f811c613c3faab876659c6423__25[[#This Row],[Tiempo de permanencia]]-spaces_3iWczBNnn5rbfoUlE0Jd_uploads_git_blob_9864c7f811c613c3faab876659c6423__25[[#This Row],[Tiempo de preparación total]])>0,spaces_3iWczBNnn5rbfoUlE0Jd_uploads_git_blob_9864c7f811c613c3faab876659c6423__25[[#This Row],[Tiempo de permanencia]]-spaces_3iWczBNnn5rbfoUlE0Jd_uploads_git_blob_9864c7f811c613c3faab876659c6423__25[[#This Row],[Tiempo de preparación total]],spaces_3iWczBNnn5rbfoUlE0Jd_uploads_git_blob_9864c7f811c613c3faab876659c6423__25[[#This Row],[Tiempo de permanencia]]-spaces_3iWczBNnn5rbfoUlE0Jd_uploads_git_blob_9864c7f811c613c3faab876659c6423__25[[#This Row],[Tiempo de preparación total]]<0,0)} -> 0.06875 | U14: {=_xlfn.IFS(spaces_3iWczBNnn5rbfoUlE0Jd_uploads_git_blob_9864c7f811c613c3faab876659c6423__25[[#This Row],[Tiempo degustación]]=0,"NO PAGADA",spaces_3iWczBNnn5rbfoUlE0Jd_uploads_git_blob_9864c7f811c613c3faab876659c6423__25[[#This Row],[Tiempo degustación]]>0, "PAGADA")} -> PAGADA
A15: 16 | B15: Cliente_780 | C15: 6 | D15: 45017.012 | E15: 45017.082 | F15: Mesero_2 | G15: Almuerzo | H15: Efectivo | I15: 48.76 | J15: Libre | K15: 14 | L15: Perú | M15: Plato_3, Plato_11, Plato_14, Plato_2 | N15: =_xlfn.XLOOKUP(spaces_3iWczBNnn5rbfoUlE0Jd_uploads_git_blob_9864c7f811c613c3faab876659c6423__25[[#This Row],[Número de Orden]],Cocinadinamica!B16:B784,Cocinadinamica!C16:C784) -> 51 | O15: =spaces_3iWczBNnn5rbfoUlE0Jd_uploads_git_blob_9864c7f811c613c3faab876659c6423__25[[#This Row],[Hora de Llegada]] -> 45017.012 | P15: =spaces_3iWczBNnn5rbfoUlE0Jd_uploads_git_blob_9864c7f811c613c3faab876659c6423__25[[#This Row],[Hora de Llegada]] -> 45017.012 | Q15: =spaces_3iWczBNnn5rbfoUlE0Jd_uploads_git_blob_9864c7f811c613c3faab876659c6423__25[[#This Row],[Hora de Salida]] -> 45017.082 | R15: {=_xlfn.IFS(spaces_3iWczBNnn5rbfoUlE0Jd_uploads_git_blob_9864c7f811c613c3faab876659c6423__25[[#This Row],[Estado de la Mesa]]="Ocupada",(15/1440)+spaces_3iWczBNnn5rbfoUlE0Jd_uploads_git_blob_9864c7f811c613c3faab876659c6423__25[[#This Row],[Hora de salida2]]-spaces_3iWczBNnn5rbfoUlE0Jd_uploads_git_blob_9864c7f811c613c3faab876659c6423__25[[#This Row],[Hora de llegada2]],spaces_3iWczBNnn5rbfoUlE0Jd_uploads_git_blob_9864c7f811c613c3faab876659c6423__25[[#This Row],[Estado de la Mesa]]<>"Ocupada",spaces_3iWczBNnn5rbfoUlE0Jd_uploads_git_blob_9864c7f811c613c3faab876659c6423__25[[#This Row],[Hora de salida2]]-spaces_3iWczBNnn5rbfoUlE0Jd_uploads_git_blob_9864c7f811c613c3faab876659c6423__25[[#This Row],[Hora de llegada2]])} -> 0.069444444 | S15: =_xlfn.XLOOKUP(spaces_3iWczBNnn5rbfoUlE0Jd_uploads_git_blob_9864c7f811c613c3faab876659c6423__25[[#This Row],[Número de Orden]],Cocinadinamica!E16:E784,Cocinadinamica!F16:F784)/1440 -> 0.10694444 | T15: {=_xlfn.IFS((spaces_3iWczBNnn5rbfoUlE0Jd_uploads_git_blob_9864c7f811c613c3faab876659c6423__25[[#This Row],[Tiempo de permanencia]]-spaces_3iWczBNnn5rbfoUlE0Jd_uploads_git_blob_9864c7f811c613c3faab876659c6423__25[[#This Row],[Tiempo de preparación total]])>0,spaces_3iWczBNnn5rbfoUlE0Jd_uploads_git_blob_9864c7f811c613c3faab876659c6423__25[[#This Row],[Tiempo de permanencia]]-spaces_3iWczBNnn5rbfoUlE0Jd_uploads_git_blob_9864c7f811c613c3faab876659c6423__25[[#This Row],[Tiempo de preparación total]],spaces_3iWczBNnn5rbfoUlE0Jd_uploads_git_blob_9864c7f811c613c3faab876659c6423__25[[#This Row],[Tiempo de permanencia]]-spaces_3iWczBNnn5rbfoUlE0Jd_uploads_git_blob_9864c7f811c613c3faab876659c6423__25[[#This Row],[Tiempo de preparación total]]<0,0)} -> 0 | U15: {=_xlfn.IFS(spaces_3iWczBNnn5rbfoUlE0Jd_uploads_git_blob_9864c7f811c613c3faab876659c6423__25[[#This Row],[Tiempo degustación]]=0,"NO PAGADA",spaces_3iWczBNnn5rbfoUlE0Jd_uploads_git_blob_9864c7f811c613c3faab876659c6423__25[[#This Row],[Tiempo degustación]]>0, "PAGADA")} -> NO PAGADA
A16: 6 | B16: Cliente_728 | C16: 4 | D16: 45017.142 | E16: 45017.208 | F16: Mesero_1 | G16: Desayuno | H16: Tarjeta de crédito | I16: 28.77 | J16: Ocupada | K16: 15 | L16: Uruguay | M16: Plato_16, Plato_13, Plato_8 | N16: =_xlfn.XLOOKUP(spaces_3iWczBNnn5rbfoUlE0Jd_uploads_git_blob_9864c7f811c613c3faab876659c6423__25[[#This Row],[Número de Orden]],Cocinadinamica!B17:B785,Cocinadinamica!C17:C785) -> 90 | O16: =spaces_3iWczBNnn5rbfoUlE0Jd_uploads_git_blob_9864c7f811c613c3faab876659c6423__25[[#This Row],[Hora de Llegada]] -> 45017.142 | P16: =spaces_3iWczBNnn5rbfoUlE0Jd_uploads_git_blob_9864c7f811c613c3faab876659c6423__25[[#This Row],[Hora de Llegada]] -> 45017.142 | Q16: =spaces_3iWczBNnn5rbfoUlE0Jd_uploads_git_blob_9864c7f811c613c3faab876659c6423__25[[#This Row],[Hora de Salida]] -> 45017.208 | R16: {=_xlfn.IFS(spaces_3iWczBNnn5rbfoUlE0Jd_uploads_git_blob_9864c7f811c613c3faab876659c6423__25[[#This Row],[Estado de la Mesa]]="Ocupada",(15/1440)+spaces_3iWczBNnn5rbfoUlE0Jd_uploads_git_blob_9864c7f811c613c3faab876659c6423__25[[#This Row],[Hora de salida2]]-spaces_3iWczBNnn5rbfoUlE0Jd_uploads_git_blob_9864c7f811c613c3faab876659c6423__25[[#This Row],[Hora de llegada2]],spaces_3iWczBNnn5rbfoUlE0Jd_uploads_git_blob_9864c7f811c613c3faab876659c6423__25[[#This Row],[Estado de la Mesa]]<>"Ocupada",spaces_3iWczBNnn5rbfoUlE0Jd_uploads_git_blob_9864c7f811c613c3faab876659c6423__25[[#This Row],[Hora de salida2]]-spaces_3iWczBNnn5rbfoUlE0Jd_uploads_git_blob_9864c7f811c613c3faab876659c6423__25[[#This Row],[Hora de llegada2]])} -> 0.076388889 | S16: =_xlfn.XLOOKUP(spaces_3iWczBNnn5rbfoUlE0Jd_uploads_git_blob_9864c7f811c613c3faab876659c6423__25[[#This Row],[Número de Orden]],Cocinadinamica!E17:E785,Cocinadinamica!F17:F785)/1440 -> 0.071527778 | T16: {=_xlfn.IFS((spaces_3iWczBNnn5rbfoUlE0Jd_uploads_git_blob_9864c7f811c613c3faab876659c6423__25[[#This Row],[Tiempo de permanencia]]-spaces_3iWczBNnn5rbfoUlE0Jd_uploads_git_blob_9864c7f811c613c3faab876659c6423__25[[#This Row],[Tiempo de preparación total]])>0,spaces_3iWczBNnn5rbfoUlE0Jd_uploads_git_blob_9864c7f811c613c3faab876659c6423__25[[#This Row],[Tiempo de permanencia]]-spaces_3iWczBNnn5rbfoUlE0Jd_uploads_git_blob_9864c7f811c613c3faab876659c6423__25[[#This Row],[Tiempo de preparación total]],spaces_3iWczBNnn5rbfoUlE0Jd_uploads_git_blob_9864c7f811c613c3faab876659c6423__25[[#This Row],[Tiempo de permanencia]]-spaces_3iWczBNnn5rbfoUlE0Jd_uploads_git_blob_9864c7f811c613c3faab876659c6423__25[[#This Row],[Tiempo de preparación total]]<0,0)} -> 0.0048611111 | U16: {=_xlfn.IFS(spaces_3iWczBNnn5rbfoUlE0Jd_uploads_git_blob_9864c7f811c613c3faab876659c6423__25[[#This Row],[Tiempo degustación]]=0,"NO PAGADA",spaces_3iWczBNnn5rbfoUlE0Jd_uploads_git_blob_9864c7f811c613c3faab876659c6423__25[[#This Row],[Tiempo degustación]]>0, "PAGADA")} -> PAGADA
A17: 20 | B17: Cliente_175 | C17: 5 | D17: 45017.105 | E17: 45017.183 | F17: Mesero_4 | G17: Almuerzo | H17: Efectivo | I17: 3.79 | J17: Reservada | K17: 16 | L17: Bolivia | M17: Plato_16 | N17: =_xlfn.XLOOKUP(spaces_3iWczBNnn5rbfoUlE0Jd_uploads_git_blob_9864c7f811c613c3faab876659c6423__25[[#This Row],[Número de Orden]],Cocinadinamica!B18:B786,Cocinadinamica!C18:C786) -> 12 | O17: =spaces_3iWczBNnn5rbfoUlE0Jd_uploads_git_blob_9864c7f811c613c3faab876659c6423__25[[#This Row],[Hora de Llegada]] -> 45017.105 | P17: =spaces_3iWczBNnn5rbfoUlE0Jd_uploads_git_blob_9864c7f811c613c3faab876659c6423__25[[#This Row],[Hora de Llegada]] -> 45017.105 | Q17: =spaces_3iWczBNnn5rbfoUlE0Jd_uploads_git_blob_9864c7f811c613c3faab876659c6423__25[[#This Row],[Hora de Salida]] -> 45017.183 | R17: {=_xlfn.IFS(spaces_3iWczBNnn5rbfoUlE0Jd_uploads_git_blob_9864c7f811c613c3faab876659c6423__25[[#This Row],[Estado de la Mesa]]="Ocupada",(15/1440)+spaces_3iWczBNnn5rbfoUlE0Jd_uploads_git_blob_9864c7f811c613c3faab876659c6423__25[[#This Row],[Hora de salida2]]-spaces_3iWczBNnn5rbfoUlE0Jd_uploads_git_blob_9864c7f811c613c3faab876659c6423__25[[#This Row],[Hora de llegada2]],spaces_3iWczBNnn5rbfoUlE0Jd_uploads_git_blob_9864c7f811c613c3faab876659c6423__25[[#This Row],[Estado de la Mesa]]<>"Ocupada",spaces_3iWczBNnn5rbfoUlE0Jd_uploads_git_blob_9864c7f811c613c3faab876659c6423__25[[#This Row],[Hora de salida2]]-spaces_3iWczBNnn5rbfoUlE0Jd_uploads_git_blob_9864c7f811c613c3faab876659c6423__25[[#This Row],[Hora de llegada2]])} -> 0.078472222 | S17: =_xlfn.XLOOKUP(spaces_3iWczBNnn5rbfoUlE0Jd_uploads_git_blob_9864c7f811c613c3faab876659c6423__25[[#This Row],[Número de Orden]],Cocinadinamica!E18:E786,Cocinadinamica!F18:F786)/1440 -> 0.026388889 | T17: {=_xlfn.IFS((spaces_3iWczBNnn5rbfoUlE0Jd_uploads_git_blob_9864c7f811c613c3faab876659c6423__25[[#This Row],[Tiempo de permanencia]]-spaces_3iWczBNnn5rbfoUlE0Jd_uploads_git_blob_9864c7f811c613c3faab876659c6423__25[[#This Row],[Tiempo de preparación total]])>0,spaces_3iWczBNnn5rbfoUlE0Jd_uploads_git_blob_9864c7f811c613c3faab876659c6423__25[[#This Row],[Tiempo de permanencia]]-spaces_3iWczBNnn5rbfoUlE0Jd_uploads_git_blob_9864c7f811c613c3faab876659c6423__25[[#This Row],[Tiempo de preparación total]],spaces_3iWczBNnn5rbfoUlE0Jd_uploads_git_blob_9864c7f811c613c3faab876659c6423__25[[#This Row],[Tiempo de permanencia]]-spaces_3iWczBNnn5rbfoUlE0Jd_uploads_git_blob_9864c7f811c613c3faab876659c6423__25[[#This Row],[Tiempo de preparación total]]<0,0)} -> 0.052083333 | U17: {=_xlfn.IFS(spaces_3iWczBNnn5rbfoUlE0Jd_uploads_git_blob_9864c7f811c613c3faab876659c6423__25[[#This Row],[Tiempo degustación]]=0,"NO PAGADA",spaces_3iWczBNnn5rbfoUlE0Jd_uploads_git_blob_9864c7f811c613c3faab876659c6423__25[[#This Row],[Tiempo degustación]]>0, "PAGADA")} -> PAGADA
A18: 14 | B18: Cliente_200 | C18: 6 | D18: 45017.006 | E18: 45017.144 | F18: Mesero_2 | G18: Desayuno | H18: Tarjeta de crédito | I18: 12.17 | J18: Libre | K18: 17 | L18: Ecuador | M18: Plato_8, Plato_4, Plato_5 | N18: =_xlfn.XLOOKUP(spaces_3iWczBNnn5rbfoUlE0Jd_uploads_git_blob_9864c7f811c613c3faab876659c6423__25[[#This Row],[Número de Orden]],Cocinadinamica!B19:B787,Cocinadinamica!C19:C787) -> 57 | O18: =spaces_3iWczBNnn5rbfoUlE0Jd_uploads_git_blob_9864c7f811c613c3faab876659c6423__25[[#This Row],[Hora de Llegada]] -> 45017.006 | P18: =spaces_3iWczBNnn5rbfoUlE0Jd_uploads_git_blob_9864c7f811c613c3faab876659c6423__25[[#This Row],[Hora de Llegada]] -> 45017.006 | Q18: =spaces_3iWczBNnn5rbfoUlE0Jd_uploads_git_blob_9864c7f811c613c3faab876659c6423__25[[#This Row],[Hora de Salida]] -> 45017.144 | R18: {=_xlfn.IFS(spaces_3iWczBNnn5rbfoUlE0Jd_uploads_git_blob_9864c7f811c613c3faab876659c6423__25[[#This Row],[Estado de la Mesa]]="Ocupada",(15/1440)+spaces_3iWczBNnn5rbfoUlE0Jd_uploads_git_blob_9864c7f811c613c3faab876659c6423__25[[#This Row],[Hora de salida2]]-spaces_3iWczBNnn5rbfoUlE0Jd_uploads_git_blob_9864c7f811c613c3faab876659c6423__25[[#This Row],[Hora de llegada2]],spaces_3iWczBNnn5rbfoUlE0Jd_uploads_git_blob_9864c7f811c613c3faab876659c6423__25[[#This Row],[Estado de la Mesa]]<>"Ocupada",spaces_3iWczBNnn5rbfoUlE0Jd_uploads_git_blob_9864c7f811c613c3faab876659c6423__25[[#This Row],[Hora de salida2]]-spaces_3iWczBNnn5rbfoUlE0Jd_uploads_git_blob_9864c7f811c613c3faab876659c6423__25[[#This Row],[Hora de llegada2]])} -> 0.1375 | S18: =_xlfn.XLOOKUP(spaces_3iWczBNnn5rbfoUlE0Jd_uploads_git_blob_9864c7f811c613c3faab876659c6423__25[[#This Row],[Número de Orden]],Cocinadinamica!E19:E787,Cocinadinamica!F19:F787)/1440 -> 0.10972222 | T18: {=_xlfn.IFS((spaces_3iWczBNnn5rbfoUlE0Jd_uploads_git_blob_9864c7f811c613c3faab876659c6423__25[[#This Row],[Tiempo de permanencia]]-spaces_3iWczBNnn5rbfoUlE0Jd_uploads_git_blob_9864c7f811c613c3faab876659c6423__25[[#This Row],[Tiempo de preparación total]])>0,spaces_3iWczBNnn5rbfoUlE0Jd_uploads_git_blob_9864c7f811c613c3faab876659c6423__25[[#This Row],[Tiempo de permanencia]]-spaces_3iWczBNnn5rbfoUlE0Jd_uploads_git_blob_9864c7f811c613c3faab876659c6423__25[[#This Row],[Tiempo de preparación total]],spaces_3iWczBNnn5rbfoUlE0Jd_uploads_git_blob_9864c7f811c613c3faab876659c6423__25[[#This Row],[Tiempo de permanencia]]-spaces_3iWczBNnn5rbfoUlE0Jd_uploads_git_blob_9864c7f811c613c3faab876659c6423__25[[#This Row],[Tiempo de preparación total]]<0,0)} -> 0.027777778 | U18: {=_xlfn.IFS(spaces_3iWczBNnn5rbfoUlE0Jd_uploads_git_blob_9864c7f811c613c3faab876659c6423__25[[#This Row],[Tiempo degustación]]=0,"NO PAGADA",spaces_3iWczBNnn5rbfoUlE0Jd_uploads_git_blob_9864c7f811c613c3faab876659c6423__25[[#This Row],[Tiempo degustación]]>0, "PAGADA")} -> PAGADA
A19: 9 | B19: Cliente_190 | C19: 2 | D19: 45017.088 | E19: 45017.185 | F19: Mesero_2 | G19: Desayuno | H19: Tarjeta de crédito | I19: 33.09 | J19: Libre | K19: 18 | L19: Colombia | M19: Plato_9, Plato_20, Plato_10, Plato_15 | N19: =_xlfn.XLOOKUP(spaces_3iWczBNnn5rbfoUlE0Jd_uploads_git_blob_9864c7f811c613c3faab876659c6423__25[[#This Row],[Número de Orden]],Cocinadinamica!B20:B788,Cocinadinamica!C20:C788) -> 101 | O19: =spaces_3iWczBNnn5rbfoUlE0Jd_uploads_git_blob_9864c7f811c613c3faab876659c6423__25[[#This Row],[Hora de Llegada]] -> 45017.088 | P19: =spaces_3iWczBNnn5rbfoUlE0Jd_uploads_git_blob_9864c7f811c613c3faab876659c6423__25[[#This Row],[Hora de Llegada]] -> 45017.088 | Q19: =spaces_3iWczBNnn5rbfoUlE0Jd_uploads_git_blob_9864c7f811c613c3faab876659c6423__25[[#This Row],[Hora de Salida]] -> 45017.185 | R19: {=_xlfn.IFS(spaces_3iWczBNnn5rbfoUlE0Jd_uploads_git_blob_9864c7f811c613c3faab876659c6423__25[[#This Row],[Estado de la Mesa]]="Ocupada",(15/1440)+spaces_3iWczBNnn5rbfoUlE0Jd_uploads_git_blob_9864c7f811c613c3faab876659c6423__25[[#This Row],[Hora de salida2]]-spaces_3iWczBNnn5rbfoUlE0Jd_uploads_git_blob_9864c7f811c613c3faab876659c6423__25[[#This Row],[Hora de llegada2]],spaces_3iWczBNnn5rbfoUlE0Jd_uploads_git_blob_9864c7f811c613c3faab876659c6423__25[[#This Row],[Estado de la Mesa]]<>"Ocupada",spaces_3iWczBNnn5rbfoUlE0Jd_uploads_git_blob_9864c7f811c613c3faab876659c6423__25[[#This Row],[Hora de salida2]]-spaces_3iWczBNnn5rbfoUlE0Jd_uploads_git_blob_9864c7f811c613c3faab876659c6423__25[[#This Row],[Hora de llegada2]])} -> 0.097222222 | S19: =_xlfn.XLOOKUP(spaces_3iWczBNnn5rbfoUlE0Jd_uploads_git_blob_9864c7f811c613c3faab876659c6423__25[[#This Row],[Número de Orden]],Cocinadinamica!E20:E788,Cocinadinamica!F20:F788)/1440 -> 0.093055556 | T19: {=_xlfn.IFS((spaces_3iWczBNnn5rbfoUlE0Jd_uploads_git_blob_9864c7f811c613c3faab876659c6423__25[[#This Row],[Tiempo de permanencia]]-spaces_3iWczBNnn5rbfoUlE0Jd_uploads_git_blob_9864c7f811c613c3faab876659c6423__25[[#This Row],[Tiempo de preparación total]])>0,spaces_3iWczBNnn5rbfoUlE0Jd_uploads_git_blob_9864c7f811c613c3faab876659c6423__25[[#This Row],[Tiempo de permanencia]]-spaces_3iWczBNnn5rbfoUlE0Jd_uploads_git_blob_9864c7f811c613c3faab876659c6423__25[[#This Row],[Tiempo de preparación total]],spaces_3iWczBNnn5rbfoUlE0Jd_uploads_git_blob_9864c7f811c613c3faab876659c6423__25[[#This Row],[Tiempo de permanencia]]-spaces_3iWczBNnn5rbfoUlE0Jd_uploads_git_blob_9864c7f811c613c3faab876659c6423__25[[#This Row],[Tiempo de preparación total]]<0,0)} -> 0.0041666667 | U19: {=_xlfn.IFS(spaces_3iWczBNnn5rbfoUlE0Jd_uploads_git_blob_9864c7f811c613c3faab876659c6423__25[[#This Row],[Tiempo degustación]]=0,"NO PAGADA",spaces_3iWczBNnn5rbfoUlE0Jd_uploads_git_blob_9864c7f811c613c3faab876659c6423__25[[#This Row],[Tiempo degustación]]>0, "PAGADA")} -> PAGADA
A20: 18 | B20: Cliente_290 | C20: 3 | D20: 45017.024 | E20: 45017.145 | F20: Mesero_2 | G20: Almuerzo | H20: Tarjeta de crédito | I20: 17.45 | J20: Libre | K20: 19 | L20: Chile | M20: Plato_20 | N20: =_xlfn.XLOOKUP(spaces_3iWczBNnn5rbfoUlE0Jd_uploads_git_blob_9864c7f811c613c3faab876659c6423__25[[#This Row],[Número de Orden]],Cocinadinamica!B21:B789,Cocinadinamica!C21:C789) -> 30 | O20: =spaces_3iWczBNnn5rbfoUlE0Jd_uploads_git_blob_9864c7f811c613c3faab876659c6423__25[[#This Row],[Hora de Llegada]] -> 45017.024 | P20: =spaces_3iWczBNnn5rbfoUlE0Jd_uploads_git_blob_9864c7f811c613c3faab876659c6423__25[[#This Row],[Hora de Llegada]] -> 45017.024 | Q20: =spaces_3iWczBNnn5rbfoUlE0Jd_uploads_git_blob_9864c7f811c613c3faab876659c6423__25[[#This Row],[Hora de Salida]] -> 45017.145 | R20: {=_xlfn.IFS(spaces_3iWczBNnn5rbfoUlE0Jd_uploads_git_blob_9864c7f811c613c3faab876659c6423__25[[#This Row],[Estado de la Mesa]]="Ocupada",(15/1440)+spaces_3iWczBNnn5rbfoUlE0Jd_uploads_git_blob_9864c7f811c613c3faab876659c6423__25[[#This Row],[Hora de salida2]]-spaces_3iWczBNnn5rbfoUlE0Jd_uploads_git_blob_9864c7f811c613c3faab876659c6423__25[[#This Row],[Hora de llegada2]],spaces_3iWczBNnn5rbfoUlE0Jd_uploads_git_blob_9864c7f811c613c3faab876659c6423__25[[#This Row],[Estado de la Mesa]]<>"Ocupada",spaces_3iWczBNnn5rbfoUlE0Jd_uploads_git_blob_9864c7f811c613c3faab876659c6423__25[[#This Row],[Hora de salida2]]-spaces_3iWczBNnn5rbfoUlE0Jd_uploads_git_blob_9864c7f811c613c3faab876659c6423__25[[#This Row],[Hora de llegada2]])} -> 0.12083333 | S20: =_xlfn.XLOOKUP(spaces_3iWczBNnn5rbfoUlE0Jd_uploads_git_blob_9864c7f811c613c3faab876659c6423__25[[#This Row],[Número de Orden]],Cocinadinamica!E21:E789,Cocinadinamica!F21:F789)/1440 -> 0.030555556 | T20: {=_xlfn.IFS((spaces_3iWczBNnn5rbfoUlE0Jd_uploads_git_blob_9864c7f811c613c3faab876659c6423__25[[#This Row],[Tiempo de permanencia]]-spaces_3iWczBNnn5rbfoUlE0Jd_uploads_git_blob_9864c7f811c613c3faab876659c6423__25[[#This Row],[Tiempo de preparación total]])>0,spaces_3iWczBNnn5rbfoUlE0Jd_uploads_git_blob_9864c7f811c613c3faab876659c6423__25[[#This Row],[Tiempo de permanencia]]-spaces_3iWczBNnn5rbfoUlE0Jd_uploads_git_blob_9864c7f811c613c3faab876659c6423__25[[#This Row],[Tiempo de preparación total]],spaces_3iWczBNnn5rbfoUlE0Jd_uploads_git_blob_9864c7f811c613c3faab876659c6423__25[[#This Row],[Tiempo de permanencia]]-spaces_3iWczBNnn5rbfoUlE0Jd_uploads_git_blob_9864c7f811c613c3faab876659c6423__25[[#This Row],[Tiempo de preparación total]]<0,0)} -> 0.090277778 | U20: {=_xlfn.IFS(spaces_3iWczBNnn5rbfoUlE0Jd_uploads_git_blob_9864c7f811c613c3faab876659c6423__25[[#This Row],[Tiempo degustación]]=0,"NO PAGADA",spaces_3iWczBNnn5rbfoUlE0Jd_uploads_git_blob_9864c7f811c613c3faab876659c6423__25[[#This Row],[Tiempo degustación]]>0, "PAGADA")} -> PAGADA
A21: 8 | B21: Cliente_972 | C21: 2 | D21: 45017.059 | E21: 45017.217 | F21: Mesero_3 | G21: Almuerzo | H21: Tarjeta de crédito | I21: 31.7 | J21: Reservada | K21: 20 | L21: Chile | M21: Plato_8, Plato_1, Plato_14 | N21: =_xlfn.XLOOKUP(spaces_3iWczBNnn5rbfoUlE0Jd_uploads_git_blob_9864c7f811c613c3faab876659c6423__25[[#This Row],[Número de Orden]],Cocinadinamica!B22:B790,Cocinadinamica!C22:C790) -> 71 | O21: =spaces_3iWczBNnn5rbfoUlE0Jd_uploads_git_blob_9864c7f811c613c3faab876659c6423__25[[#This Row],[Hora de Llegada]] -> 45017.059 | P21: =spaces_3iWczBNnn5rbfoUlE0Jd_uploads_git_blob_9864c7f811c613c3faab876659c6423__25[[#This Row],[Hora de Llegada]] -> 45017.059 | Q21: =spaces_3iWczBNnn5rbfoUlE0Jd_uploads_git_blob_9864c7f811c613c3faab876659c6423__25[[#This Row],[Hora de Salida]] -> 45017.217 | R21: {=_xlfn.IFS(spaces_3iWczBNnn5rbfoUlE0Jd_uploads_git_blob_9864c7f811c613c3faab876659c6423__25[[#This Row],[Estado de la Mesa]]="Ocupada",(15/1440)+spaces_3iWczBNnn5rbfoUlE0Jd_uploads_git_blob_9864c7f811c613c3faab876659c6423__25[[#This Row],[Hora de salida2]]-spaces_3iWczBNnn5rbfoUlE0Jd_uploads_git_blob_9864c7f811c613c3faab876659c6423__25[[#This Row],[Hora de llegada2]],spaces_3iWczBNnn5rbfoUlE0Jd_uploads_git_blob_9864c7f811c613c3faab876659c6423__25[[#This Row],[Estado de la Mesa]]<>"Ocupada",spaces_3iWczBNnn5rbfoUlE0Jd_uploads_git_blob_9864c7f811c613c3faab876659c6423__25[[#This Row],[Hora de salida2]]-spaces_3iWczBNnn5rbfoUlE0Jd_uploads_git_blob_9864c7f811c613c3faab876659c6423__25[[#This Row],[Hora de llegada2]])} -> 0.15763889 | S21: =_xlfn.XLOOKUP(spaces_3iWczBNnn5rbfoUlE0Jd_uploads_git_blob_9864c7f811c613c3faab876659c6423__25[[#This Row],[Número de Orden]],Cocinadinamica!E22:E790,Cocinadinamica!F22:F790)/1440 -> 0.048611111 | T21: {=_xlfn.IFS((spaces_3iWczBNnn5rbfoUlE0Jd_uploads_git_blob_9864c7f811c613c3faab876659c6423__25[[#This Row],[Tiempo de permanencia]]-spaces_3iWczBNnn5rbfoUlE0Jd_uploads_git_blob_9864c7f811c613c3faab876659c6423__25[[#This Row],[Tiempo de preparación total]])>0,spaces_3iWczBNnn5rbfoUlE0Jd_uploads_git_blob_9864c7f811c613c3faab876659c6423__25[[#This Row],[Tiempo de permanencia]]-spaces_3iWczBNnn5rbfoUlE0Jd_uploads_git_blob_9864c7f811c613c3faab876659c6423__25[[#This Row],[Tiempo de preparación total]],spaces_3iWczBNnn5rbfoUlE0Jd_uploads_git_blob_9864c7f811c613c3faab876659c6423__25[[#This Row],[Tiempo de permanencia]]-spaces_3iWczBNnn5rbfoUlE0Jd_uploads_git_blob_9864c7f811c613c3faab876659c6423__25[[#This Row],[Tiempo de preparación total]]<0,0)} -> 0.10902778 | U21: {=_xlfn.IFS(spaces_3iWczBNnn5rbfoUlE0Jd_uploads_git_blob_9864c7f811c613c3faab876659c6423__25[[#This Row],[Tiempo degustación]]=0,"NO PAGADA",spaces_3iWczBNnn5rbfoUlE0Jd_uploads_git_blob_9864c7f811c613c3faab876659c6423__25[[#This Row],[Tiempo degustación]]>0, "PAGADA")} -> PAGADA
A22: 12 | B22: Cliente_210 | C22: 2 | D22: 45017.152 | E22: 45017.244 | F22: Mesero_3 | G22: Almuerzo | H22: Tarjeta de crédito | I22: 20.53 | J22: Reservada | K22: 21 | L22: Uruguay | M22: Plato_20, Plato_3, Plato_15, Plato_1 | N22: =_xlfn.XLOOKUP(spaces_3iWczBNnn5rbfoUlE0Jd_uploads_git_blob_9864c7f811c613c3faab876659c6423__25[[#This Row],[Número de Orden]],Cocinadinamica!B23:B791,Cocinadinamica!C23:C791) -> 107 | O22: =spaces_3iWczBNnn5rbfoUlE0Jd_uploads_git_blob_9864c7f811c613c3faab876659c6423__25[[#This Row],[Hora de Llegada]] -> 45017.152 | P22: =spaces_3iWczBNnn5rbfoUlE0Jd_uploads_git_blob_9864c7f811c613c3faab876659c6423__25[[#This Row],[Hora de Llegada]] -> 45017.152 | Q22: =spaces_3iWczBNnn5rbfoUlE0Jd_uploads_git_blob_9864c7f811c613c3faab876659c6423__25[[#This Row],[Hora de Salida]] -> 45017.244 | R22: {=_xlfn.IFS(spaces_3iWczBNnn5rbfoUlE0Jd_uploads_git_blob_9864c7f811c613c3faab876659c6423__25[[#This Row],[Estado de la Mesa]]="Ocupada",(15/1440)+spaces_3iWczBNnn5rbfoUlE0Jd_uploads_git_blob_9864c7f811c613c3faab876659c6423__25[[#This Row],[Hora de salida2]]-spaces_3iWczBNnn5rbfoUlE0Jd_uploads_git_blob_9864c7f811c613c3faab876659c6423__25[[#This Row],[Hora de llegada2]],spaces_3iWczBNnn5rbfoUlE0Jd_uploads_git_blob_9864c7f811c613c3faab876659c6423__25[[#This Row],[Estado de la Mesa]]<>"Ocupada",spaces_3iWczBNnn5rbfoUlE0Jd_uploads_git_blob_9864c7f811c613c3faab876659c6423__25[[#This Row],[Hora de salida2]]-spaces_3iWczBNnn5rbfoUlE0Jd_uploads_git_blob_9864c7f811c613c3faab876659c6423__25[[#This Row],[Hora de llegada2]])} -> 0.092361111 | S22: =_xlfn.XLOOKUP(spaces_3iWczBNnn5rbfoUlE0Jd_uploads_git_blob_9864c7f811c613c3faab876659c6423__25[[#This Row],[Número de Orden]],Cocinadinamica!E23:E791,Cocinadinamica!F23:F791)/1440 -> 0.10555556 | T22: {=_xlfn.IFS((spaces_3iWczBNnn5rbfoUlE0Jd_uploads_git_blob_9864c7f811c613c3faab876659c6423__25[[#This Row],[Tiempo de permanencia]]-spaces_3iWczBNnn5rbfoUlE0Jd_uploads_git_blob_9864c7f811c613c3faab876659c6423__25[[#This Row],[Tiempo de preparación total]])>0,spaces_3iWczBNnn5rbfoUlE0Jd_uploads_git_blob_9864c7f811c613c3faab876659c6423__25[[#This Row],[Tiempo de permanencia]]-spaces_3iWczBNnn5rbfoUlE0Jd_uploads_git_blob_9864c7f811c613c3faab876659c6423__25[[#This Row],[Tiempo de preparación total]],spaces_3iWczBNnn5rbfoUlE0Jd_uploads_git_blob_9864c7f811c613c3faab876659c6423__25[[#This Row],[Tiempo de permanencia]]-spaces_3iWczBNnn5rbfoUlE0Jd_uploads_git_blob_9864c7f811c613c3faab876659c6423__25[[#This Row],[Tiempo de preparación total]]<0,0)} -> 0 | U22: {=_xlfn.IFS(spaces_3iWczBNnn5rbfoUlE0Jd_uploads_git_blob_9864c7f811c613c3faab876659c6423__25[[#This Row],[Tiempo degustación]]=0,"NO PAGADA",spaces_3iWczBNnn5rbfoUlE0Jd_uploads_git_blob_9864c7f811c613c3faab876659c6423__25[[#This Row],[Tiempo degustación]]>0, "PAGADA")} -> NO PAGADA
A23: 15 | B23: Cliente_88 | C23: 1 | D23: 45017.094 | E23: 45017.199 | F23: Mesero_4 | G23: Almuerzo | H23: Tarjeta de crédito | I23: 45.41 | J23: Libre | K23: 22 | L23: Ecuador | M23: Plato_4, Plato_18, Plato_9, Plato_8 | N23: =_xlfn.XLOOKUP(spaces_3iWczBNnn5rbfoUlE0Jd_uploads_git_blob_9864c7f811c613c3faab876659c6423__25[[#This Row],[Número de Orden]],Cocinadinamica!B24:B792,Cocinadinamica!C24:C792) -> 88 | O23: =spaces_3iWczBNnn5rbfoUlE0Jd_uploads_git_blob_9864c7f811c613c3faab876659c6423__25[[#This Row],[Hora de Llegada]] -> 45017.094 | P23: =spaces_3iWczBNnn5rbfoUlE0Jd_uploads_git_blob_9864c7f811c613c3faab876659c6423__25[[#This Row],[Hora de Llegada]] -> 45017.094 | Q23: =spaces_3iWczBNnn5rbfoUlE0Jd_uploads_git_blob_9864c7f811c613c3faab876659c6423__25[[#This Row],[Hora de Salida]] -> 45017.199 | R23: {=_xlfn.IFS(spaces_3iWczBNnn5rbfoUlE0Jd_uploads_git_blob_9864c7f811c613c3faab876659c6423__25[[#This Row],[Estado de la Mesa]]="Ocupada",(15/1440)+spaces_3iWczBNnn5rbfoUlE0Jd_uploads_git_blob_9864c7f811c613c3faab876659c6423__25[[#This Row],[Hora de salida2]]-spaces_3iWczBNnn5rbfoUlE0Jd_uploads_git_blob_9864c7f811c613c3faab876659c6423__25[[#This Row],[Hora de llegada2]],spaces_3iWczBNnn5rbfoUlE0Jd_uploads_git_blob_9864c7f811c613c3faab876659c6423__25[[#This Row],[Estado de la Mesa]]<>"Ocupada",spaces_3iWczBNnn5rbfoUlE0Jd_uploads_git_blob_9864c7f811c613c3faab876659c6423__25[[#This Row],[Hora de salida2]]-spaces_3iWczBNnn5rbfoUlE0Jd_uploads_git_blob_9864c7f811c613c3faab876659c6423__25[[#This Row],[Hora de llegada2]])} -> 0.10486111 | S23: =_xlfn.XLOOKUP(spaces_3iWczBNnn5rbfoUlE0Jd_uploads_git_blob_9864c7f811c613c3faab876659c6423__25[[#This Row],[Número de Orden]],Cocinadinamica!E24:E792,Cocinadinamica!F24:F792)/1440 -> 0.085416667 | T23: {=_xlfn.IFS((spaces_3iWczBNnn5rbfoUlE0Jd_uploads_git_blob_9864c7f811c613c3faab876659c6423__25[[#This Row],[Tiempo de permanencia]]-spaces_3iWczBNnn5rbfoUlE0Jd_uploads_git_blob_9864c7f811c613c3faab876659c6423__25[[#This Row],[Tiempo de preparación total]])>0,spaces_3iWczBNnn5rbfoUlE0Jd_uploads_git_blob_9864c7f811c613c3faab876659c6423__25[[#This Row],[Tiempo de permanencia]]-spaces_3iWczBNnn5rbfoUlE0Jd_uploads_git_blob_9864c7f811c613c3faab876659c6423__25[[#This Row],[Tiempo de preparación total]],spaces_3iWczBNnn5rbfoUlE0Jd_uploads_git_blob_9864c7f811c613c3faab876659c6423__25[[#This Row],[Tiempo de permanencia]]-spaces_3iWczBNnn5rbfoUlE0Jd_uploads_git_blob_9864c7f811c613c3faab876659c6423__25[[#This Row],[Tiempo de preparación total]]<0,0)} -> 0.019444444 | U23: {=_xlfn.IFS(spaces_3iWczBNnn5rbfoUlE0Jd_uploads_git_blob_9864c7f811c613c3faab876659c6423__25[[#This Row],[Tiempo degustación]]=0,"NO PAGADA",spaces_3iWczBNnn5rbfoUlE0Jd_uploads_git_blob_9864c7f811c613c3faab876659c6423__25[[#This Row],[Tiempo degustación]]>0, "PAGADA")} -> PAGADA
A24: 1 | B24: Cliente_427 | C24: 5 | D24: 45017.114 | E24: 45017.173 | F24: Mesero_5 | G24: Cena | H24: Tarjeta de crédito | I24: 38.46 | J24: Libre | K24: 23 | L24: Chile | M24: Plato_12, Plato_6 | N24: =_xlfn.XLOOKUP(spaces_3iWczBNnn5rbfoUlE0Jd_uploads_git_blob_9864c7f811c613c3faab876659c6423__25[[#This Row],[Número de Orden]],Cocinadinamica!B25:B793,Cocinadinamica!C25:C793) -> 57 | O24: =spaces_3iWczBNnn5rbfoUlE0Jd_uploads_git_blob_9864c7f811c613c3faab876659c6423__25[[#This Row],[Hora de Llegada]] -> 45017.114 | P24: =spaces_3iWczBNnn5rbfoUlE0Jd_uploads_git_blob_9864c7f811c613c3faab876659c6423__25[[#This Row],[Hora de Llegada]] -> 45017.114 | Q24: =spaces_3iWczBNnn5rbfoUlE0Jd_uploads_git_blob_9864c7f811c613c3faab876659c6423__25[[#This Row],[Hora de Salida]] -> 45017.173 | R24: {=_xlfn.IFS(spaces_3iWczBNnn5rbfoUlE0Jd_uploads_git_blob_9864c7f811c613c3faab876659c6423__25[[#This Row],[Estado de la Mesa]]="Ocupada",(15/1440)+spaces_3iWczBNnn5rbfoUlE0Jd_uploads_git_blob_9864c7f811c613c3faab876659c6423__25[[#This Row],[Hora de salida2]]-spaces_3iWczBNnn5rbfoUlE0Jd_uploads_git_blob_9864c7f811c613c3faab876659c6423__25[[#This Row],[Hora de llegada2]],spaces_3iWczBNnn5rbfoUlE0Jd_uploads_git_blob_9864c7f811c613c3faab876659c6423__25[[#This Row],[Estado de la Mesa]]<>"Ocupada",spaces_3iWczBNnn5rbfoUlE0Jd_uploads_git_blob_9864c7f811c613c3faab876659c6423__25[[#This Row],[Hora de salida2]]-spaces_3iWczBNnn5rbfoUlE0Jd_uploads_git_blob_9864c7f811c613c3faab876659c6423__25[[#This Row],[Hora de llegada2]])} -> 0.059027778 | S24: =_xlfn.XLOOKUP(spaces_3iWczBNnn5rbfoUlE0Jd_uploads_git_blob_9864c7f811c613c3faab876659c6423__25[[#This Row],[Número de Orden]],Cocinadinamica!E25:E793,Cocinadinamica!F25:F793)/1440 -> 0.04375 | T24: {=_xlfn.IFS((spaces_3iWczBNnn5rbfoUlE0Jd_uploads_git_blob_9864c7f811c613c3faab876659c6423__25[[#This Row],[Tiempo de permanencia]]-spaces_3iWczBNnn5rbfoUlE0Jd_uploads_git_blob_9864c7f811c613c3faab876659c6423__25[[#This Row],[Tiempo de preparación total]])>0,spaces_3iWczBNnn5rbfoUlE0Jd_uploads_git_blob_9864c7f811c613c3faab876659c6423__25[[#This Row],[Tiempo de permanencia]]-spaces_3iWczBNnn5rbfoUlE0Jd_uploads_git_blob_9864c7f811c613c3faab876659c6423__25[[#This Row],[Tiempo de preparación total]],spaces_3iWczBNnn5rbfoUlE0Jd_uploads_git_blob_9864c7f811c613c3faab876659c6423__25[[#This Row],[Tiempo de permanencia]]-spaces_3iWczBNnn5rbfoUlE0Jd_uploads_git_blob_9864c7f811c613c3faab876659c6423__25[[#This Row],[Tiempo de preparación total]]<0,0)} -> 0.015277778 | U24: {=_xlfn.IFS(spaces_3iWczBNnn5rbfoUlE0Jd_uploads_git_blob_9864c7f811c613c3faab876659c6423__25[[#This Row],[Tiempo degustación]]=0,"NO PAGADA",spaces_3iWczBNnn5rbfoUlE0Jd_uploads_git_blob_9864c7f811c613c3faab876659c6423__25[[#This Row],[Tiempo degustación]]>0, "PAGADA")} -> PAGADA
A25: 5 | B25: Cliente_424 | C25: 5 | D25: 45017.126 | E25: 45017.264 | F25: Mesero_3 | G25: Almuerzo | H25: Tarjeta de crédito | I25: 38.18 | J25: Ocupada | K25: 24 | L25: Venezuela | M25: Plato_10, Plato_9, Plato_14, Plato_20 | N25: =_xlfn.XLOOKUP(spaces_3iWczBNnn5rbfoUlE0Jd_uploads_git_blob_9864c7f811c613c3faab876659c6423__25[[#This Row],[Número de Orden]],Cocinadinamica!B26:B794,Cocinadinamica!C26:C794) -> 93 | O25: =spaces_3iWczBNnn5rbfoUlE0Jd_uploads_git_blob_9864c7f811c613c3faab876659c6423__25[[#This Row],[Hora de Llegada]] -> 45017.126 | P25: =spaces_3iWczBNnn5rbfoUlE0Jd_uploads_git_blob_9864c7f811c613c3faab876659c6423__25[[#This Row],[Hora de Llegada]] -> 45017.126 | Q25: =spaces_3iWczBNnn5rbfoUlE0Jd_uploads_git_blob_9864c7f811c613c3faab876659c6423__25[[#This Row],[Hora de Salida]] -> 45017.264 | R25: {=_xlfn.IFS(spaces_3iWczBNnn5rbfoUlE0Jd_uploads_git_blob_9864c7f811c613c3faab876659c6423__25[[#This Row],[Estado de la Mesa]]="Ocupada",(15/1440)+spaces_3iWczBNnn5rbfoUlE0Jd_uploads_git_blob_9864c7f811c613c3faab876659c6423__25[[#This Row],[Hora de salida2]]-spaces_3iWczBNnn5rbfoUlE0Jd_uploads_git_blob_9864c7f811c613c3faab876659c6423__25[[#This Row],[Hora de llegada2]],spaces_3iWczBNnn5rbfoUlE0Jd_uploads_git_blob_9864c7f811c613c3faab876659c6423__25[[#This Row],[Estado de la Mesa]]<>"Ocupada",spaces_3iWczBNnn5rbfoUlE0Jd_uploads_git_blob_9864c7f811c613c3faab876659c6423__25[[#This Row],[Hora de salida2]]-spaces_3iWczBNnn5rbfoUlE0Jd_uploads_git_blob_9864c7f811c613c3faab876659c6423__25[[#This Row],[Hora de llegada2]])} -> 0.14861111 | S25: =_xlfn.XLOOKUP(spaces_3iWczBNnn5rbfoUlE0Jd_uploads_git_blob_9864c7f811c613c3faab876659c6423__25[[#This Row],[Número de Orden]],Cocinadinamica!E26:E794,Cocinadinamica!F26:F794)/1440 -> 0.125 | T25: {=_xlfn.IFS((spaces_3iWczBNnn5rbfoUlE0Jd_uploads_git_blob_9864c7f811c613c3faab876659c6423__25[[#This Row],[Tiempo de permanencia]]-spaces_3iWczBNnn5rbfoUlE0Jd_uploads_git_blob_9864c7f811c613c3faab876659c6423__25[[#This Row],[Tiempo de preparación total]])>0,spaces_3iWczBNnn5rbfoUlE0Jd_uploads_git_blob_9864c7f811c613c3faab876659c6423__25[[#This Row],[Tiempo de permanencia]]-spaces_3iWczBNnn5rbfoUlE0Jd_uploads_git_blob_9864c7f811c613c3faab876659c6423__25[[#This Row],[Tiempo de preparación total]],spaces_3iWczBNnn5rbfoUlE0Jd_uploads_git_blob_9864c7f811c613c3faab876659c6423__25[[#This Row],[Tiempo de permanencia]]-spaces_3iWczBNnn5rbfoUlE0Jd_uploads_git_blob_9864c7f811c613c3faab876659c6423__25[[#This Row],[Tiempo de preparación total]]<0,0)} -> 0.023611111 | U25: {=_xlfn.IFS(spaces_3iWczBNnn5rbfoUlE0Jd_uploads_git_blob_9864c7f811c613c3faab876659c6423__25[[#This Row],[Tiempo degustación]]=0,"NO PAGADA",spaces_3iWczBNnn5rbfoUlE0Jd_uploads_git_blob_9864c7f811c613c3faab876659c6423__25[[#This Row],[Tiempo degustación]]>0, "PAGADA")} -> PAGADA
A26: 12 | B26: Cliente_824 | C26: 5 | D26: 45017.126 | E26: 45017.208 | F26: Mesero_5 | G26: Cena | H26: Tarjeta de débito | I26: 46.15 | J26: Ocupada | K26: 25 | L26: Colombia | M26: Plato_18 | N26: =_xlfn.XLOOKUP(spaces_3iWczBNnn5rbfoUlE0Jd_uploads_git_blob_9864c7f811c613c3faab876659c6423__25[[#This Row],[Número de Orden]],Cocinadinamica!B27:B795,Cocinadinamica!C27:C795) -> 14 | O26: =spaces_3iWczBNnn5rbfoUlE0Jd_uploads_git_blob_9864c7f811c613c3faab876659c6423__25[[#This Row],[Hora de Llegada]] -> 45017.126 | P26: =spaces_3iWczBNnn5rbfoUlE0Jd_uploads_git_blob_9864c7f811c613c3faab876659c6423__25[[#This Row],[Hora de Llegada]] -> 45017.126 | Q26: =spaces_3iWczBNnn5rbfoUlE0Jd_uploads_git_blob_9864c7f811c613c3faab876659c6423__25[[#This Row],[Hora de Salida]] -> 45017.208 | R26: {=_xlfn.IFS(spaces_3iWczBNnn5rbfoUlE0Jd_uploads_git_blob_9864c7f811c613c3faab876659c6423__25[[#This Row],[Estado de la Mesa]]="Ocupada",(15/1440)+spaces_3iWczBNnn5rbfoUlE0Jd_uploads_git_blob_9864c7f811c613c3faab876659c6423__25[[#This Row],[Hora de salida2]]-spaces_3iWczBNnn5rbfoUlE0Jd_uploads_git_blob_9864c7f811c613c3faab876659c6423__25[[#This Row],[Hora de llegada2]],spaces_3iWczBNnn5rbfoUlE0Jd_uploads_git_blob_9864c7f811c613c3faab876659c6423__25[[#This Row],[Estado de la Mesa]]<>"Ocupada",spaces_3iWczBNnn5rbfoUlE0Jd_uploads_git_blob_9864c7f811c613c3faab876659c6423__25[[#This Row],[Hora de salida2]]-spaces_3iWczBNnn5rbfoUlE0Jd_uploads_git_blob_9864c7f811c613c3faab876659c6423__25[[#This Row],[Hora de llegada2]])} -> 0.092361111 | S26: =_xlfn.XLOOKUP(spaces_3iWczBNnn5rbfoUlE0Jd_uploads_git_blob_9864c7f811c613c3faab876659c6423__25[[#This Row],[Número de Orden]],Cocinadinamica!E27:E795,Cocinadinamica!F27:F795)/1440 -> 0.024305556 | T26: {=_xlfn.IFS((spaces_3iWczBNnn5rbfoUlE0Jd_uploads_git_blob_9864c7f811c613c3faab876659c6423__25[[#This Row],[Tiempo de permanencia]]-spaces_3iWczBNnn5rbfoUlE0Jd_uploads_git_blob_9864c7f811c613c3faab876659c6423__25[[#This Row],[Tiempo de preparación total]])>0,spaces_3iWczBNnn5rbfoUlE0Jd_uploads_git_blob_9864c7f811c613c3faab876659c6423__25[[#This Row],[Tiempo de permanencia]]-spaces_3iWczBNnn5rbfoUlE0Jd_uploads_git_blob_9864c7f811c613c3faab876659c6423__25[[#This Row],[Tiempo de preparación total]],spaces_3iWczBNnn5rbfoUlE0Jd_uploads_git_blob_9864c7f811c613c3faab876659c6423__25[[#This Row],[Tiempo de permanencia]]-spaces_3iWczBNnn5rbfoUlE0Jd_uploads_git_blob_9864c7f811c613c3faab876659c6423__25[[#This Row],[Tiempo de preparación total]]<0,0)} -> 0.068055556 | U26: {=_xlfn.IFS(spaces_3iWczBNnn5rbfoUlE0Jd_uploads_git_blob_9864c7f811c613c3faab876659c6423__25[[#This Row],[Tiempo degustación]]=0,"NO PAGADA",spaces_3iWczBNnn5rbfoUlE0Jd_uploads_git_blob_9864c7f811c613c3faab876659c6423__25[[#This Row],[Tiempo degustación]]>0, "PAGADA")} -> PAGADA
A27: 18 | B27: Cliente_107 | C27: 2 | D27: 45017.086 | E27: 45017.241 | F27: Mesero_5 | G27: Desayuno | H27: Tarjeta de crédito | I27: 10.37 | J27: Ocupada | K27: 26 | L27: Uruguay | M27: Plato_4, Plato_13, Plato_7 | N27: =_xlfn.XLOOKUP(spaces_3iWczBNnn5rbfoUlE0Jd_uploads_git_blob_9864c7f811c613c3faab876659c6423__25[[#This Row],[Número de Orden]],Cocinadinamica!B28:B796,Cocinadinamica!C28:C796) -> 52 | O27: =spaces_3iWczBNnn5rbfoUlE0Jd_uploads_git_blob_9864c7f811c613c3faab876659c6423__25[[#This Row],[Hora de Llegada]] -> 45017.086 | P27: =spaces_3iWczBNnn5rbfoUlE0Jd_uploads_git_blob_9864c7f811c613c3faab876659c6423__25[[#This Row],[Hora de Llegada]] -> 45017.086 | Q27: =spaces_3iWczBNnn5rbfoUlE0Jd_uploads_git_blob_9864c7f811c613c3faab876659c6423__25[[#This Row],[Hora de Salida]] -> 45017.241 | R27: {=_xlfn.IFS(spaces_3iWczBNnn5rbfoUlE0Jd_uploads_git_blob_9864c7f811c613c3faab876659c6423__25[[#This Row],[Estado de la Mesa]]="Ocupada",(15/1440)+spaces_3iWczBNnn5rbfoUlE0Jd_uploads_git_blob_9864c7f811c613c3faab876659c6423__25[[#This Row],[Hora de salida2]]-spaces_3iWczBNnn5rbfoUlE0Jd_uploads_git_blob_9864c7f811c613c3faab876659c6423__25[[#This Row],[Hora de llegada2]],spaces_3iWczBNnn5rbfoUlE0Jd_uploads_git_blob_9864c7f811c613c3faab876659c6423__25[[#This Row],[Estado de la Mesa]]<>"Ocupada",spaces_3iWczBNnn5rbfoUlE0Jd_uploads_git_blob_9864c7f811c613c3faab876659c6423__25[[#This Row],[Hora de salida2]]-spaces_3iWczBNnn5rbfoUlE0Jd_uploads_git_blob_9864c7f811c613c3faab876659c6423__25[[#This Row],[Hora de llegada2]])} -> 0.16527778 | S27: =_xlfn.XLOOKUP(spaces_3iWczBNnn5rbfoUlE0Jd_uploads_git_blob_9864c7f811c613c3faab876659c6423__25[[#This Row],[Número de Orden]],Cocinadinamica!E28:E796,Cocinadinamica!F28:F796)/1440 -> 0.075694444 | T27: {=_xlfn.IFS((spaces_3iWczBNnn5rbfoUlE0Jd_uploads_git_blob_9864c7f811c613c3faab876659c6423__25[[#This Row],[Tiempo de permanencia]]-spaces_3iWczBNnn5rbfoUlE0Jd_uploads_git_blob_9864c7f811c613c3faab876659c6423__25[[#This Row],[Tiempo de preparación total]])>0,spaces_3iWczBNnn5rbfoUlE0Jd_uploads_git_blob_9864c7f811c613c3faab876659c6423__25[[#This Row],[Tiempo de permanencia]]-spaces_3iWczBNnn5rbfoUlE0Jd_uploads_git_blob_9864c7f811c613c3faab876659c6423__25[[#This Row],[Tiempo de preparación total]],spaces_3iWczBNnn5rbfoUlE0Jd_uploads_git_blob_9864c7f811c613c3faab876659c6423__25[[#This Row],[Tiempo de permanencia]]-spaces_3iWczBNnn5rbfoUlE0Jd_uploads_git_blob_9864c7f811c613c3faab876659c6423__25[[#This Row],[Tiempo de preparación total]]<0,0)} -> 0.089583333 | U27: {=_xlfn.IFS(spaces_3iWczBNnn5rbfoUlE0Jd_uploads_git_blob_9864c7f811c613c3faab876659c6423__25[[#This Row],[Tiempo degustación]]=0,"NO PAGADA",spaces_3iWczBNnn5rbfoUlE0Jd_uploads_git_blob_9864c7f811c613c3faab876659c6423__25[[#This Row],[Tiempo degustación]]>0, "PAGADA")} -> PAGADA
A28: 4 | B28: Cliente_775 | C28: 2 | D28: 45017.055 | E28: 45017.102 | F28: Mesero_5 | G28: Almuerzo | H28: Tarjeta de crédito | I28: 19.27 | J28: Ocupada | K28: 27 | L28: Brasil | M28: Plato_8, Plato_10 | N28: =_xlfn.XLOOKUP(spaces_3iWczBNnn5rbfoUlE0Jd_uploads_git_blob_9864c7f811c613c3faab876659c6423__25[[#This Row],[Número de Orden]],Cocinadinamica!B29:B797,Cocinadinamica!C29:C797) -> 25 | O28: =spaces_3iWczBNnn5rbfoUlE0Jd_uploads_git_blob_9864c7f811c613c3faab876659c6423__25[[#This Row],[Hora de Llegada]] -> 45017.055 | P28: =spaces_3iWczBNnn5rbfoUlE0Jd_uploads_git_blob_9864c7f811c613c3faab876659c6423__25[[#This Row],[Hora de Llegada]] -> 45017.055 | Q28: =spaces_3iWczBNnn5rbfoUlE0Jd_uploads_git_blob_9864c7f811c613c3faab876659c6423__25[[#This Row],[Hora de Salida]] -> 45017.102 | R28: {=_xlfn.IFS(spaces_3iWczBNnn5rbfoUlE0Jd_uploads_git_blob_9864c7f811c613c3faab876659c6423__25[[#This Row],[Estado de la Mesa]]="Ocupada",(15/1440)+spaces_3iWczBNnn5rbfoUlE0Jd_uploads_git_blob_9864c7f811c613c3faab876659c6423__25[[#This Row],[Hora de salida2]]-spaces_3iWczBNnn5rbfoUlE0Jd_uploads_git_blob_9864c7f811c613c3faab876659c6423__25[[#This Row],[Hora de llegada2]],spaces_3iWczBNnn5rbfoUlE0Jd_uploads_git_blob_9864c7f811c613c3faab876659c6423__25[[#This Row],[Estado de la Mesa]]<>"Ocupada",spaces_3iWczBNnn5rbfoUlE0Jd_uploads_git_blob_9864c7f811c613c3faab876659c6423__25[[#This Row],[Hora de salida2]]-spaces_3iWczBNnn5rbfoUlE0Jd_uploads_git_blob_9864c7f811c613c3faab876659c6423__25[[#This Row],[Hora de llegada2]])} -> 0.057638889 | S28: =_xlfn.XLOOKUP(spaces_3iWczBNnn5rbfoUlE0Jd_uploads_git_blob_9864c7f811c613c3faab876659c6423__25[[#This Row],[Número de Orden]],Cocinadinamica!E29:E797,Cocinadinamica!F29:F797)/1440 -> 0.038194444 | T28: {=_xlfn.IFS((spaces_3iWczBNnn5rbfoUlE0Jd_uploads_git_blob_9864c7f811c613c3faab876659c6423__25[[#This Row],[Tiempo de permanencia]]-spaces_3iWczBNnn5rbfoUlE0Jd_uploads_git_blob_9864c7f811c613c3faab876659c6423__25[[#This Row],[Tiempo de preparación total]])>0,spaces_3iWczBNnn5rbfoUlE0Jd_uploads_git_blob_9864c7f811c613c3faab876659c6423__25[[#This Row],[Tiempo de permanencia]]-spaces_3iWczBNnn5rbfoUlE0Jd_uploads_git_blob_9864c7f811c613c3faab876659c6423__25[[#This Row],[Tiempo de preparación total]],spaces_3iWczBNnn5rbfoUlE0Jd_uploads_git_blob_9864c7f811c613c3faab876659c6423__25[[#This Row],[Tiempo de permanencia]]-spaces_3iWczBNnn5rbfoUlE0Jd_uploads_git_blob_9864c7f811c613c3faab876659c6423__25[[#This Row],[Tiempo de preparación total]]<0,0)} -> 0.019444444 | U28: {=_xlfn.IFS(spaces_3iWczBNnn5rbfoUlE0Jd_uploads_git_blob_9864c7f811c613c3faab876659c6423__25[[#This Row],[Tiempo degustación]]=0,"NO PAGADA",spaces_3iWczBNnn5rbfoUlE0Jd_uploads_git_blob_9864c7f811c613c3faab876659c6423__25[[#This Row],[Tiempo degustación]]>0, "PAGADA")} -> PAGADA
A29: 2 | B29: Cliente_358 | C29: 2 | D29: 45017.034 | E29: 45017.136 | F29: Mesero_4 | G29: Cena | H29: Tarjeta de crédito | I29: 41.22 | J29: Reservada | K29: 28 | L29: Argentina | M29: Plato_4, Plato_9 | N29: =_xlfn.XLOOKUP(spaces_3iWczBNnn5rbfoUlE0Jd_uploads_git_blob_9864c7f811c613c3faab876659c6423__25[[#This Row],[Número de Orden]],Cocinadinamica!B30:B798,Cocinadinamica!C30:C798) -> 40 | O29: =spaces_3iWczBNnn5rbfoUlE0Jd_uploads_git_blob_9864c7f811c613c3faab876659c6423__25[[#This Row],[Hora de Llegada]] -> 45017.034 | P29: =spaces_3iWczBNnn5rbfoUlE0Jd_uploads_git_blob_9864c7f811c613c3faab876659c6423__25[[#This Row],[Hora de Llegada]] -> 45017.034 | Q29: =spaces_3iWczBNnn5rbfoUlE0Jd_uploads_git_blob_9864c7f811c613c3faab876659c6423__25[[#This Row],[Hora de Salida]] -> 45017.136 | R29: {=_xlfn.IFS(spaces_3iWczBNnn5rbfoUlE0Jd_uploads_git_blob_9864c7f811c613c3faab876659c6423__25[[#This Row],[Estado de la Mesa]]="Ocupada",(15/1440)+spaces_3iWczBNnn5rbfoUlE0Jd_uploads_git_blob_9864c7f811c613c3faab876659c6423__25[[#This Row],[Hora de salida2]]-spaces_3iWczBNnn5rbfoUlE0Jd_uploads_git_blob_9864c7f811c613c3faab876659c6423__25[[#This Row],[Hora de llegada2]],spaces_3iWczBNnn5rbfoUlE0Jd_uploads_git_blob_9864c7f811c613c3faab876659c6423__25[[#This Row],[Estado de la Mesa]]<>"Ocupada",spaces_3iWczBNnn5rbfoUlE0Jd_uploads_git_blob_9864c7f811c613c3faab876659c6423__25[[#This Row],[Hora de salida2]]-spaces_3iWczBNnn5rbfoUlE0Jd_uploads_git_blob_9864c7f811c613c3faab876659c6423__25[[#This Row],[Hora de llegada2]])} -> 0.10208333 | S29: =_xlfn.XLOOKUP(spaces_3iWczBNnn5rbfoUlE0Jd_uploads_git_blob_9864c7f811c613c3faab876659c6423__25[[#This Row],[Número de Orden]],Cocinadinamica!E30:E798,Cocinadinamica!F30:F798)/1440 -> 0.038888889 | T29: {=_xlfn.IFS((spaces_3iWczBNnn5rbfoUlE0Jd_uploads_git_blob_9864c7f811c613c3faab876659c6423__25[[#This Row],[Tiempo de permanencia]]-spaces_3iWczBNnn5rbfoUlE0Jd_uploads_git_blob_9864c7f811c613c3faab876659c6423__25[[#This Row],[Tiempo de preparación total]])>0,spaces_3iWczBNnn5rbfoUlE0Jd_uploads_git_blob_9864c7f811c613c3faab876659c6423__25[[#This Row],[Tiempo de permanencia]]-spaces_3iWczBNnn5rbfoUlE0Jd_uploads_git_blob_9864c7f811c613c3faab876659c6423__25[[#This Row],[Tiempo de preparación total]],spaces_3iWczBNnn5rbfoUlE0Jd_uploads_git_blob_9864c7f811c613c3faab876659c6423__25[[#This Row],[Tiempo de permanencia]]-spaces_3iWczBNnn5rbfoUlE0Jd_uploads_git_blob_9864c7f811c613c3faab876659c6423__25[[#This Row],[Tiempo de preparación total]]<0,0)} -> 0.063194444 | U29: {=_xlfn.IFS(spaces_3iWczBNnn5rbfoUlE0Jd_uploads_git_blob_9864c7f811c613c3faab876659c6423__25[[#This Row],[Tiempo degustación]]=0,"NO PAGADA",spaces_3iWczBNnn5rbfoUlE0Jd_uploads_git_blob_9864c7f811c613c3faab876659c6423__25[[#This Row],[Tiempo degustación]]>0, "PAGADA")} -> PAGADA
A30: 20 | B30: Cliente_377 | C30: 5 | D30: 45017.126 | E30: 45017.257 | F30: Mesero_2 | G30: Almuerzo | H30: Tarjeta de crédito | I30: 14.83 | J30: Ocupada | K30: 29 | L30: Ecuador | M30: Plato_1, Plato_4, Plato_17 | N30: =_xlfn.XLOOKUP(spaces_3iWczBNnn5rbfoUlE0Jd_uploads_git_blob_9864c7f811c613c3faab876659c6423__25[[#This Row],[Número de Orden]],Cocinadinamica!B31:B799,Cocinadinamica!C31:C799) -> 70 | O30: =spaces_3iWczBNnn5rbfoUlE0Jd_uploads_git_blob_9864c7f811c613c3faab876659c6423__25[[#This Row],[Hora de Llegada]] -> 45017.126 | P30: =spaces_3iWczBNnn5rbfoUlE0Jd_uploads_git_blob_9864c7f811c613c3faab876659c6423__25[[#This Row],[Hora de Llegada]] -> 45017.126 | Q30: =spaces_3iWczBNnn5rbfoUlE0Jd_uploads_git_blob_9864c7f811c613c3faab876659c6423__25[[#This Row],[Hora de Salida]] -> 45017.257 | R30: {=_xlfn.IFS(spaces_3iWczBNnn5rbfoUlE0Jd_uploads_git_blob_9864c7f811c613c3faab876659c6423__25[[#This Row],[Estado de la Mesa]]="Ocupada",(15/1440)+spaces_3iWczBNnn5rbfoUlE0Jd_uploads_git_blob_9864c7f811c613c3faab876659c6423__25[[#This Row],[Hora de salida2]]-spaces_3iWczBNnn5rbfoUlE0Jd_uploads_git_blob_9864c7f811c613c3faab876659c6423__25[[#This Row],[Hora de llegada2]],spaces_3iWczBNnn5rbfoUlE0Jd_uploads_git_blob_9864c7f811c613c3faab876659c6423__25[[#This Row],[Estado de la Mesa]]<>"Ocupada",spaces_3iWczBNnn5rbfoUlE0Jd_uploads_git_blob_9864c7f811c613c3faab876659c6423__25[[#This Row],[Hora de salida2]]-spaces_3iWczBNnn5rbfoUlE0Jd_uploads_git_blob_9864c7f811c613c3faab876659c6423__25[[#This Row],[Hora de llegada2]])} -> 0.14097222 | S30: =_xlfn.XLOOKUP(spaces_3iWczBNnn5rbfoUlE0Jd_uploads_git_blob_9864c7f811c613c3faab876659c6423__25[[#This Row],[Número de Orden]],Cocinadinamica!E31:E799,Cocinadinamica!F31:F799)/1440 -> 0.049305556 | T30: {=_xlfn.IFS((spaces_3iWczBNnn5rbfoUlE0Jd_uploads_git_blob_9864c7f811c613c3faab876659c6423__25[[#This Row],[Tiempo de permanencia]]-spaces_3iWczBNnn5rbfoUlE0Jd_uploads_git_blob_9864c7f811c613c3faab876659c6423__25[[#This Row],[Tiempo de preparación total]])>0,spaces_3iWczBNnn5rbfoUlE0Jd_uploads_git_blob_9864c7f811c613c3faab876659c6423__25[[#This Row],[Tiempo de permanencia]]-spaces_3iWczBNnn5rbfoUlE0Jd_uploads_git_blob_9864c7f811c613c3faab876659c6423__25[[#This Row],[Tiempo de preparación total]],spaces_3iWczBNnn5rbfoUlE0Jd_uploads_git_blob_9864c7f811c613c3faab876659c6423__25[[#This Row],[Tiempo de permanencia]]-spaces_3iWczBNnn5rbfoUlE0Jd_uploads_git_blob_9864c7f811c613c3faab876659c6423__25[[#This Row],[Tiempo de preparación total]]<0,0)} -> 0.091666667 | U30: {=_xlfn.IFS(spaces_3iWczBNnn5rbfoUlE0Jd_uploads_git_blob_9864c7f811c613c3faab876659c6423__25[[#This Row],[Tiempo degustación]]=0,"NO PAGADA",spaces_3iWczBNnn5rbfoUlE0Jd_uploads_git_blob_9864c7f811c613c3faab876659c6423__25[[#This Row],[Tiempo degustación]]>0, "PAGADA")} -> PAGADA
A31: 14 | B31: Cliente_361 | C31: 4 | D31: 45017.122 | E31: 45017.259 | F31: Mesero_4 | G31: Almuerzo | H31: Efectivo | I31: 26.29 | J31: Libre | K31: 30 | L31: Venezuela | M31: Plato_10, Plato_3 | N31: =_xlfn.XLOOKUP(spaces_3iWczBNnn5rbfoUlE0Jd_uploads_git_blob_9864c7f811c613c3faab876659c6423__25[[#This Row],[Número de Orden]],Cocinadinamica!B32:B800,Cocinadinamica!C32:C800) -> 46 | O31: =spaces_3iWczBNnn5rbfoUlE0Jd_uploads_git_blob_9864c7f811c613c3faab876659c6423__25[[#This Row],[Hora de Llegada]] -> 45017.122 | P31: =spaces_3iWczBNnn5rbfoUlE0Jd_uploads_git_blob_9864c7f811c613c3faab876659c6423__25[[#This Row],[Hora de Llegada]] -> 45017.122 | Q31: =spaces_3iWczBNnn5rbfoUlE0Jd_uploads_git_blob_9864c7f811c613c3faab876659c6423__25[[#This Row],[Hora de Salida]] -> 45017.259 | R31: {=_xlfn.IFS(spaces_3iWczBNnn5rbfoUlE0Jd_uploads_git_blob_9864c7f811c613c3faab876659c6423__25[[#This Row],[Estado de la Mesa]]="Ocupada",(15/1440)+spaces_3iWczBNnn5rbfoUlE0Jd_uploads_git_blob_9864c7f811c613c3faab876659c6423__25[[#This Row],[Hora de salida2]]-spaces_3iWczBNnn5rbfoUlE0Jd_uploads_git_blob_9864c7f811c613c3faab876659c6423__25[[#This Row],[Hora de llegada2]],spaces_3iWczBNnn5rbfoUlE0Jd_uploads_git_blob_9864c7f811c613c3faab876659c6423__25[[#This Row],[Estado de la Mesa]]<>"Ocupada",spaces_3iWczBNnn5rbfoUlE0Jd_uploads_git_blob_9864c7f811c613c3faab876659c6423__25[[#This Row],[Hora de salida2]]-spaces_3iWczBNnn5rbfoUlE0Jd_uploads_git_blob_9864c7f811c613c3faab876659c6423__25[[#This Row],[Hora de llegada2]])} -> 0.1375 | S31: =_xlfn.XLOOKUP(spaces_3iWczBNnn5rbfoUlE0Jd_uploads_git_blob_9864c7f811c613c3faab876659c6423__25[[#This Row],[Número de Orden]],Cocinadinamica!E32:E800,Cocinadinamica!F32:F800)/1440 -> 0.047916667 | T31: {=_xlfn.IFS((spaces_3iWczBNnn5rbfoUlE0Jd_uploads_git_blob_9864c7f811c613c3faab876659c6423__25[[#This Row],[Tiempo de permanencia]]-spaces_3iWczBNnn5rbfoUlE0Jd_uploads_git_blob_9864c7f811c613c3faab876659c6423__25[[#This Row],[Tiempo de preparación total]])>0,spaces_3iWczBNnn5rbfoUlE0Jd_uploads_git_blob_9864c7f811c613c3faab876659c6423__25[[#This Row],[Tiempo de permanencia]]-spaces_3iWczBNnn5rbfoUlE0Jd_uploads_git_blob_9864c7f811c613c3faab876659c6423__25[[#This Row],[Tiempo de preparación total]],spaces_3iWczBNnn5rbfoUlE0Jd_uploads_git_blob_9864c7f811c613c3faab876659c6423__25[[#This Row],[Tiempo de permanencia]]-spaces_3iWczBNnn5rbfoUlE0Jd_uploads_git_blob_9864c7f811c613c3faab876659c6423__25[[#This Row],[Tiempo de preparación total]]<0,0)} -> 0.089583333 | U31: {=_xlfn.IFS(spaces_3iWczBNnn5rbfoUlE0Jd_uploads_git_blob_9864c7f811c613c3faab876659c6423__25[[#This Row],[Tiempo degustación]]=0,"NO PAGADA",spaces_3iWczBNnn5rbfoUlE0Jd_uploads_git_blob_9864c7f811c613c3faab876659c6423__25[[#This Row],[Tiempo degustación]]>0, "PAGADA")} -> PAGADA
A32: 13 | B32: Cliente_229 | C32: 3 | D32: 45017.119 | E32: 45017.251 | F32: Mesero_2 | G32: Desayuno | H32: Tarjeta de crédito | I32: 19.81 | J32: Ocupada | K32: 31 | L32: Argentina | M32: Plato_9, Plato_12 | N32: =_xlfn.XLOOKUP(spaces_3iWczBNnn5rbfoUlE0Jd_uploads_git_blob_9864c7f811c613c3faab876659c6423__25[[#This Row],[Número de Orden]],Cocinadinamica!B33:B801,Cocinadinamica!C33:C801) -> 28 | O32: =spaces_3iWczBNnn5rbfoUlE0Jd_uploads_git_blob_9864c7f811c613c3faab876659c6423__25[[#This Row],[Hora de Llegada]] -> 45017.119 | P32: =spaces_3iWczBNnn5rbfoUlE0Jd_uploads_git_blob_9864c7f811c613c3faab876659c6423__25[[#This Row],[Hora de Llegada]] -> 45017.119 | Q32: =spaces_3iWczBNnn5rbfoUlE0Jd_uploads_git_blob_9864c7f811c613c3faab876659c6423__25[[#This Row],[Hora de Salida]] -> 45017.251 | R32: {=_xlfn.IFS(spaces_3iWczBNnn5rbfoUlE0Jd_uploads_git_blob_9864c7f811c613c3faab876659c6423__25[[#This Row],[Estado de la Mesa]]="Ocupada",(15/1440)+spaces_3iWczBNnn5rbfoUlE0Jd_uploads_git_blob_9864c7f811c613c3faab876659c6423__25[[#This Row],[Hora de salida2]]-spaces_3iWczBNnn5rbfoUlE0Jd_uploads_git_blob_9864c7f811c613c3faab876659c6423__25[[#This Row],[Hora de llegada2]],spaces_3iWczBNnn5rbfoUlE0Jd_uploads_git_blob_9864c7f811c613c3faab876659c6423__25[[#This Row],[Estado de la Mesa]]<>"Ocupada",spaces_3iWczBNnn5rbfoUlE0Jd_uploads_git_blob_9864c7f811c613c3faab876659c6423__25[[#This Row],[Hora de salida2]]-spaces_3iWczBNnn5rbfoUlE0Jd_uploads_git_blob_9864c7f811c613c3faab876659c6423__25[[#This Row],[Hora de llegada2]])} -> 0.14305556 | S32: =_xlfn.XLOOKUP(spaces_3iWczBNnn5rbfoUlE0Jd_uploads_git_blob_9864c7f811c613c3faab876659c6423__25[[#This Row],[Número de Orden]],Cocinadinamica!E33:E801,Cocinadinamica!F33:F801)/1440 -> 0.072916667 | T32: {=_xlfn.IFS((spaces_3iWczBNnn5rbfoUlE0Jd_uploads_git_blob_9864c7f811c613c3faab876659c6423__25[[#This Row],[Tiempo de permanencia]]-spaces_3iWczBNnn5rbfoUlE0Jd_uploads_git_blob_9864c7f811c613c3faab876659c6423__25[[#This Row],[Tiempo de preparación total]])>0,spaces_3iWczBNnn5rbfoUlE0Jd_uploads_git_blob_9864c7f811c613c3faab876659c6423__25[[#This Row],[Tiempo de permanencia]]-spaces_3iWczBNnn5rbfoUlE0Jd_uploads_git_blob_9864c7f811c613c3faab876659c6423__25[[#This Row],[Tiempo de preparación total]],spaces_3iWczBNnn5rbfoUlE0Jd_uploads_git_blob_9864c7f811c613c3faab876659c6423__25[[#This Row],[Tiempo de permanencia]]-spaces_3iWczBNnn5rbfoUlE0Jd_uploads_git_blob_9864c7f811c613c3faab876659c6423__25[[#This Row],[Tiempo de preparación total]]<0,0)} -> 0.070138889 | U32: {=_xlfn.IFS(spaces_3iWczBNnn5rbfoUlE0Jd_uploads_git_blob_9864c7f811c613c3faab876659c6423__25[[#This Row],[Tiempo degustación]]=0,"NO PAGADA",spaces_3iWczBNnn5rbfoUlE0Jd_uploads_git_blob_9864c7f811c613c3faab876659c6423__25[[#This Row],[Tiempo degustación]]>0, "PAGADA")} -> PAGADA
A33: 5 | B33: Cliente_27 | C33: 1 | D33: 45017.131 | E33: 45017.284 | F33: Mesero_1 | G33: Almuerzo | H33: Tarjeta de crédito | I33: 28.25 | J33: Ocupada | K33: 32 | L33: Uruguay | M33: Plato_15, Plato_11, Plato_10, Plato_4 | N33: =_xlfn.XLOOKUP(spaces_3iWczBNnn5rbfoUlE0Jd_uploads_git_blob_9864c7f811c613c3faab876659c6423__25[[#This Row],[Número de Orden]],Cocinadinamica!B34:B802,Cocinadinamica!C34:C802) -> 88 | O33: =spaces_3iWczBNnn5rbfoUlE0Jd_uploads_git_blob_9864c7f811c613c3faab876659c6423__25[[#This Row],[Hora de Llegada]] -> 45017.131 | P33: =spaces_3iWczBNnn5rbfoUlE0Jd_uploads_git_blob_9864c7f811c613c3faab876659c6423__25[[#This Row],[Hora de Llegada]] -> 45017.131 | Q33: =spaces_3iWczBNnn5rbfoUlE0Jd_uploads_git_blob_9864c7f811c613c3faab876659c6423__25[[#This Row],[Hora de Salida]] -> 45017.284 | R33: {=_xlfn.IFS(spaces_3iWczBNnn5rbfoUlE0Jd_uploads_git_blob_9864c7f811c613c3faab876659c6423__25[[#This Row],[Estado de la Mesa]]="Ocupada",(15/1440)+spaces_3iWczBNnn5rbfoUlE0Jd_uploads_git_blob_9864c7f811c613c3faab876659c6423__25[[#This Row],[Hora de salida2]]-spaces_3iWczBNnn5rbfoUlE0Jd_uploads_git_blob_9864c7f811c613c3faab876659c6423__25[[#This Row],[Hora de llegada2]],spaces_3iWczBNnn5rbfoUlE0Jd_uploads_git_blob_9864c7f811c613c3faab876659c6423__25[[#This Row],[Estado de la Mesa]]<>"Ocupada",spaces_3iWczBNnn5rbfoUlE0Jd_uploads_git_blob_9864c7f811c613c3faab876659c6423__25[[#This Row],[Hora de salida2]]-spaces_3iWczBNnn5rbfoUlE0Jd_uploads_git_blob_9864c7f811c613c3faab876659c6423__25[[#This Row],[Hora de llegada2]])} -> 0.16388889 | S33: =_xlfn.XLOOKUP(spaces_3iWczBNnn5rbfoUlE0Jd_uploads_git_blob_9864c7f811c613c3faab876659c6423__25[[#This Row],[Número de Orden]],Cocinadinamica!E34:E802,Cocinadinamica!F34:F802)/1440 -> 0.088888889 | T33: {=_xlfn.IFS((spaces_3iWczBNnn5rbfoUlE0Jd_uploads_git_blob_9864c7f811c613c3faab876659c6423__25[[#This Row],[Tiempo de permanencia]]-spaces_3iWczBNnn5rbfoUlE0Jd_uploads_git_blob_9864c7f811c613c3faab876659c6423__25[[#This Row],[Tiempo de preparación total]])>0,spaces_3iWczBNnn5rbfoUlE0Jd_uploads_git_blob_9864c7f811c613c3faab876659c6423__25[[#This Row],[Tiempo de permanencia]]-spaces_3iWczBNnn5rbfoUlE0Jd_uploads_git_blob_9864c7f811c613c3faab876659c6423__25[[#This Row],[Tiempo de preparación total]],spaces_3iWczBNnn5rbfoUlE0Jd_uploads_git_blob_9864c7f811c613c3faab876659c6423__25[[#This Row],[Tiempo de permanencia]]-spaces_3iWczBNnn5rbfoUlE0Jd_uploads_git_blob_9864c7f811c613c3faab876659c6423__25[[#This Row],[Tiempo de preparación total]]<0,0)} -> 0.075 | U33: {=_xlfn.IFS(spaces_3iWczBNnn5rbfoUlE0Jd_uploads_git_blob_9864c7f811c613c3faab876659c6423__25[[#This Row],[Tiempo degustación]]=0,"NO PAGADA",spaces_3iWczBNnn5rbfoUlE0Jd_uploads_git_blob_9864c7f811c613c3faab876659c6423__25[[#This Row],[Tiempo degustación]]>0, "PAGADA")} -> PAGADA
A34: 4 | B34: Cliente_103 | C34: 5 | D34: 45017.148 | E34: 45017.265 | F34: Mesero_4 | G34: Cena | H34: Tarjeta de débito | I34: 20.38 | J34: Ocupada | K34: 33 | L34: Perú | M34: Plato_8, Plato_6, Plato_15, Plato_10 | N34: =_xlfn.XLOOKUP(spaces_3iWczBNnn5rbfoUlE0Jd_uploads_git_blob_9864c7f811c613c3faab876659c6423__25[[#This Row],[Número de Orden]],Cocinadinamica!B35:B803,Cocinadinamica!C35:C803) -> 125 | O34: =spaces_3iWczBNnn5rbfoUlE0Jd_uploads_git_blob_9864c7f811c613c3faab876659c6423__25[[#This Row],[Hora de Llegada]] -> 45017.148 | P34: =spaces_3iWczBNnn5rbfoUlE0Jd_uploads_git_blob_9864c7f811c613c3faab876659c6423__25[[#This Row],[Hora de Llegada]] -> 45017.148 | Q34: =spaces_3iWczBNnn5rbfoUlE0Jd_uploads_git_blob_9864c7f811c613c3faab876659c6423__25[[#This Row],[Hora de Salida]] -> 45017.265 | R34: {=_xlfn.IFS(spaces_3iWczBNnn5rbfoUlE0Jd_uploads_git_blob_9864c7f811c613c3faab876659c6423__25[[#This Row],[Estado de la Mesa]]="Ocupada",(15/1440)+spaces_3iWczBNnn5rbfoUlE0Jd_uploads_git_blob_9864c7f811c613c3faab876659c6423__25[[#This Row],[Hora de salida2]]-spaces_3iWczBNnn5rbfoUlE0Jd_uploads_git_blob_9864c7f811c613c3faab876659c6423__25[[#This Row],[Hora de llegada2]],spaces_3iWczBNnn5rbfoUlE0Jd_uploads_git_blob_9864c7f811c613c3faab876659c6423__25[[#This Row],[Estado de la Mesa]]<>"Ocupada",spaces_3iWczBNnn5rbfoUlE0Jd_uploads_git_blob_9864c7f811c613c3faab876659c6423__25[[#This Row],[Hora de salida2]]-spaces_3iWczBNnn5rbfoUlE0Jd_uploads_git_blob_9864c7f811c613c3faab876659c6423__25[[#This Row],[Hora de llegada2]])} -> 0.12708333 | S34: =_xlfn.XLOOKUP(spaces_3iWczBNnn5rbfoUlE0Jd_uploads_git_blob_9864c7f811c613c3faab876659c6423__25[[#This Row],[Número de Orden]],Cocinadinamica!E35:E803,Cocinadinamica!F35:F803)/1440 -> 0.090277778 | T34: {=_xlfn.IFS((spaces_3iWczBNnn5rbfoUlE0Jd_uploads_git_blob_9864c7f811c613c3faab876659c6423__25[[#This Row],[Tiempo de permanencia]]-spaces_3iWczBNnn5rbfoUlE0Jd_uploads_git_blob_9864c7f811c613c3faab876659c6423__25[[#This Row],[Tiempo de preparación total]])>0,spaces_3iWczBNnn5rbfoUlE0Jd_uploads_git_blob_9864c7f811c613c3faab876659c6423__25[[#This Row],[Tiempo de permanencia]]-spaces_3iWczBNnn5rbfoUlE0Jd_uploads_git_blob_9864c7f811c613c3faab876659c6423__25[[#This Row],[Tiempo de preparación total]],spaces_3iWczBNnn5rbfoUlE0Jd_uploads_git_blob_9864c7f811c613c3faab876659c6423__25[[#This Row],[Tiempo de permanencia]]-spaces_3iWczBNnn5rbfoUlE0Jd_uploads_git_blob_9864c7f811c613c3faab876659c6423__25[[#This Row],[Tiempo de preparación total]]<0,0)} -> 0.036805556 | U34: {=_xlfn.IFS(spaces_3iWczBNnn5rbfoUlE0Jd_uploads_git_blob_9864c7f811c613c3faab876659c6423__25[[#This Row],[Tiempo degustación]]=0,"NO PAGADA",spaces_3iWczBNnn5rbfoUlE0Jd_uploads_git_blob_9864c7f811c613c3faab876659c6423__25[[#This Row],[Tiempo degustación]]>0, "PAGADA")} -> PAGADA
A35: 15 | B35: Cliente_1 | C35: 1 | D35: 45017.094 | E35: 45017.255 | F35: Mesero_4 | G35: Desayuno | H35: Tarjeta de crédito | I35: 13.08 | J35: Libre | K35: 34 | L35: Perú | M35: Plato_18, Plato_10 | N35: =_xlfn.XLOOKUP(spaces_3iWczBNnn5rbfoUlE0Jd_uploads_git_blob_9864c7f811c613c3faab876659c6423__25[[#This Row],[Número de Orden]],Cocinadinamica!B36:B804,Cocinadinamica!C36:C804) -> 47 | O35: =spaces_3iWczBNnn5rbfoUlE0Jd_uploads_git_blob_9864c7f811c613c3faab876659c6423__25[[#This Row],[Hora de Llegada]] -> 45017.094 | P35: =spaces_3iWczBNnn5rbfoUlE0Jd_uploads_git_blob_9864c7f811c613c3faab876659c6423__25[[#This Row],[Hora de Llegada]] -> 45017.094 | Q35: =spaces_3iWczBNnn5rbfoUlE0Jd_uploads_git_blob_9864c7f811c613c3faab876659c6423__25[[#This Row],[Hora de Salida]] -> 45017.255 | R35: {=_xlfn.IFS(spaces_3iWczBNnn5rbfoUlE0Jd_uploads_git_blob_9864c7f811c613c3faab876659c6423__25[[#This Row],[Estado de la Mesa]]="Ocupada",(15/1440)+spaces_3iWczBNnn5rbfoUlE0Jd_uploads_git_blob_9864c7f811c613c3faab876659c6423__25[[#This Row],[Hora de salida2]]-spaces_3iWczBNnn5rbfoUlE0Jd_uploads_git_blob_9864c7f811c613c3faab876659c6423__25[[#This Row],[Hora de llegada2]],spaces_3iWczBNnn5rbfoUlE0Jd_uploads_git_blob_9864c7f811c613c3faab876659c6423__25[[#This Row],[Estado de la Mesa]]<>"Ocupada",spaces_3iWczBNnn5rbfoUlE0Jd_uploads_git_blob_9864c7f811c613c3faab876659c6423__25[[#This Row],[Hora de salida2]]-spaces_3iWczBNnn5rbfoUlE0Jd_uploads_git_blob_9864c7f811c613c3faab876659c6423__25[[#This Row],[Hora de llegada2]])} -> 0.16041667 | S35: =_xlfn.XLOOKUP(spaces_3iWczBNnn5rbfoUlE0Jd_uploads_git_blob_9864c7f811c613c3faab876659c6423__25[[#This Row],[Número de Orden]],Cocinadinamica!E36:E804,Cocinadinamica!F36:F804)/1440 -> 0.045138889 | T35: {=_xlfn.IFS((spaces_3iWczBNnn5rbfoUlE0Jd_uploads_git_blob_9864c7f811c613c3faab876659c6423__25[[#This Row],[Tiempo de permanencia]]-spaces_3iWczBNnn5rbfoUlE0Jd_uploads_git_blob_9864c7f811c613c3faab876659c6423__25[[#This Row],[Tiempo de preparación total]])>0,spaces_3iWczBNnn5rbfoUlE0Jd_uploads_git_blob_9864c7f811c613c3faab876659c6423__25[[#This Row],[Tiempo de permanencia]]-spaces_3iWczBNnn5rbfoUlE0Jd_uploads_git_blob_9864c7f811c613c3faab876659c6423__25[[#This Row],[Tiempo de preparación total]],spaces_3iWczBNnn5rbfoUlE0Jd_uploads_git_blob_9864c7f811c613c3faab876659c6423__25[[#This Row],[Tiempo de permanencia]]-spaces_3iWczBNnn5rbfoUlE0Jd_uploads_git_blob_9864c7f811c613c3faab876659c6423__25[[#This Row],[Tiempo de preparación total]]<0,0)} -> 0.11527778 | U35: {=_xlfn.IFS(spaces_3iWczBNnn5rbfoUlE0Jd_uploads_git_blob_9864c7f811c613c3faab876659c6423__25[[#This Row],[Tiempo degustación]]=0,"NO PAGADA",spaces_3iWczBNnn5rbfoUlE0Jd_uploads_git_blob_9864c7f811c613c3faab876659c6423__25[[#This Row],[Tiempo degustación]]>0, "PAGADA")} -> PAGADA
A36: 13 | B36: Cliente_828 | C36: 2 | D36: 45017.137 | E36: 45017.247 | F36: Mesero_3 | G36: Almuerzo | H36: Tarjeta de crédito | I36: 15.75 | J36: Ocupada | K36: 35 | L36: Perú | M36: Plato_2, Plato_9, Plato_11, Plato_17 | N36: =_xlfn.XLOOKUP(spaces_3iWczBNnn5rbfoUlE0Jd_uploads_git_blob_9864c7f811c613c3faab876659c6423__25[[#This Row],[Número de Orden]],Cocinadinamica!B37:B805,Cocinadinamica!C37:C805) -> 85 | O36: =spaces_3iWczBNnn5rbfoUlE0Jd_uploads_git_blob_9864c7f811c613c3faab876659c6423__25[[#This Row],[Hora de Llegada]] -> 45017.137 | P36: =spaces_3iWczBNnn5rbfoUlE0Jd_uploads_git_blob_9864c7f811c613c3faab876659c6423__25[[#This Row],[Hora de Llegada]] -> 45017.137 | Q36: =spaces_3iWczBNnn5rbfoUlE0Jd_uploads_git_blob_9864c7f811c613c3faab876659c6423__25[[#This Row],[Hora de Salida]] -> 45017.247 | R36: {=_xlfn.IFS(spaces_3iWczBNnn5rbfoUlE0Jd_uploads_git_blob_9864c7f811c613c3faab876659c6423__25[[#This Row],[Estado de la Mesa]]="Ocupada",(15/1440)+spaces_3iWczBNnn5rbfoUlE0Jd_uploads_git_blob_9864c7f811c613c3faab876659c6423__25[[#This Row],[Hora de salida2]]-spaces_3iWczBNnn5rbfoUlE0Jd_uploads_git_blob_9864c7f811c613c3faab876659c6423__25[[#This Row],[Hora de llegada2]],spaces_3iWczBNnn5rbfoUlE0Jd_uploads_git_blob_9864c7f811c613c3faab876659c6423__25[[#This Row],[Estado de la Mesa]]<>"Ocupada",spaces_3iWczBNnn5rbfoUlE0Jd_uploads_git_blob_9864c7f811c613c3faab876659c6423__25[[#This Row],[Hora de salida2]]-spaces_3iWczBNnn5rbfoUlE0Jd_uploads_git_blob_9864c7f811c613c3faab876659c6423__25[[#This Row],[Hora de llegada2]])} -> 0.11944444 | S36: =_xlfn.XLOOKUP(spaces_3iWczBNnn5rbfoUlE0Jd_uploads_git_blob_9864c7f811c613c3faab876659c6423__25[[#This Row],[Número de Orden]],Cocinadinamica!E37:E805,Cocinadinamica!F37:F805)/1440 -> 0.045138889 | T36: {=_xlfn.IFS((spaces_3iWczBNnn5rbfoUlE0Jd_uploads_git_blob_9864c7f811c613c3faab876659c6423__25[[#This Row],[Tiempo de permanencia]]-spaces_3iWczBNnn5rbfoUlE0Jd_uploads_git_blob_9864c7f811c613c3faab876659c6423__25[[#This Row],[Tiempo de preparación total]])>0,spaces_3iWczBNnn5rbfoUlE0Jd_uploads_git_blob_9864c7f811c613c3faab876659c6423__25[[#This Row],[Tiempo de permanencia]]-spaces_3iWczBNnn5rbfoUlE0Jd_uploads_git_blob_9864c7f811c613c3faab876659c6423__25[[#This Row],[Tiempo de preparación total]],spaces_3iWczBNnn5rbfoUlE0Jd_uploads_git_blob_9864c7f811c613c3faab876659c6423__25[[#This Row],[Tiempo de permanencia]]-spaces_3iWczBNnn5rbfoUlE0Jd_uploads_git_blob_9864c7f811c613c3faab876659c6423__25[[#This Row],[Tiempo de preparación total]]<0,0)} -> 0.074305556 | U36: {=_xlfn.IFS(spaces_3iWczBNnn5rbfoUlE0Jd_uploads_git_blob_9864c7f811c613c3faab876659c6423__25[[#This Row],[Tiempo degustación]]=0,"NO PAGADA",spaces_3iWczBNnn5rbfoUlE0Jd_uploads_git_blob_9864c7f811c613c3faab876659c6423__25[[#This Row],[Tiempo degustación]]>0, "PAGADA")} -> PAGADA
A37: 5 | B37: Cliente_874 | C37: 5 | D37: 45017.144 | E37: 45017.268 | F37: Mesero_2 | G37: Almuerzo | H37: Tarjeta de crédito | I37: 45.28 | J37: Ocupada | K37: 36 | L37: Bolivia | M37: Plato_2 | N37: =_xlfn.XLOOKUP(spaces_3iWczBNnn5rbfoUlE0Jd_uploads_git_blob_9864c7f811c613c3faab876659c6423__25[[#This Row],[Número de Orden]],Cocinadinamica!B38:B806,Cocinadinamica!C38:C806) -> 12 | O37: =spaces_3iWczBNnn5rbfoUlE0Jd_uploads_git_blob_9864c7f811c613c3faab876659c6423__25[[#This Row],[Hora de Llegada]] -> 45017.144 | P37: =spaces_3iWczBNnn5rbfoUlE0Jd_uploads_git_blob_9864c7f811c613c3faab876659c6423__25[[#This Row],[Hora de Llegada]] -> 45017.144 | Q37: =spaces_3iWczBNnn5rbfoUlE0Jd_uploads_git_blob_9864c7f811c613c3faab876659c6423__25[[#This Row],[Hora de Salida]] -> 45017.268 | R37: {=_xlfn.IFS(spaces_3iWczBNnn5rbfoUlE0Jd_uploads_git_blob_9864c7f811c613c3faab876659c6423__25[[#This Row],[Estado de la Mesa]]="Ocupada",(15/1440)+spaces_3iWczBNnn5rbfoUlE0Jd_uploads_git_blob_9864c7f811c613c3faab876659c6423__25[[#This Row],[Hora de salida2]]-spaces_3iWczBNnn5rbfoUlE0Jd_uploads_git_blob_9864c7f811c613c3faab876659c6423__25[[#This Row],[Hora de llegada2]],spaces_3iWczBNnn5rbfoUlE0Jd_uploads_git_blob_9864c7f811c613c3faab876659c6423__25[[#This Row],[Estado de la Mesa]]<>"Ocupada",spaces_3iWczBNnn5rbfoUlE0Jd_uploads_git_blob_9864c7f811c613c3faab876659c6423__25[[#This Row],[Hora de salida2]]-spaces_3iWczBNnn5rbfoUlE0Jd_uploads_git_blob_9864c7f811c613c3faab876659c6423__25[[#This Row],[Hora de llegada2]])} -> 0.13472222 | S37: =_xlfn.XLOOKUP(spaces_3iWczBNnn5rbfoUlE0Jd_uploads_git_blob_9864c7f811c613c3faab876659c6423__25[[#This Row],[Número de Orden]],Cocinadinamica!E38:E806,Cocinadinamica!F38:F806)/1440 -> 0.026388889 | T37: {=_xlfn.IFS((spaces_3iWczBNnn5rbfoUlE0Jd_uploads_git_blob_9864c7f811c613c3faab876659c6423__25[[#This Row],[Tiempo de permanencia]]-spaces_3iWczBNnn5rbfoUlE0Jd_uploads_git_blob_9864c7f811c613c3faab876659c6423__25[[#This Row],[Tiempo de preparación total]])>0,spaces_3iWczBNnn5rbfoUlE0Jd_uploads_git_blob_9864c7f811c613c3faab876659c6423__25[[#This Row],[Tiempo de permanencia]]-spaces_3iWczBNnn5rbfoUlE0Jd_uploads_git_blob_9864c7f811c613c3faab876659c6423__25[[#This Row],[Tiempo de preparación total]],spaces_3iWczBNnn5rbfoUlE0Jd_uploads_git_blob_9864c7f811c613c3faab876659c6423__25[[#This Row],[Tiempo de permanencia]]-spaces_3iWczBNnn5rbfoUlE0Jd_uploads_git_blob_9864c7f811c613c3faab876659c6423__25[[#This Row],[Tiempo de preparación total]]<0,0)} -> 0.10833333 | U37: {=_xlfn.IFS(spaces_3iWczBNnn5rbfoUlE0Jd_uploads_git_blob_9864c7f811c613c3faab876659c6423__25[[#This Row],[Tiempo degustación]]=0,"NO PAGADA",spaces_3iWczBNnn5rbfoUlE0Jd_uploads_git_blob_9864c7f811c613c3faab876659c6423__25[[#This Row],[Tiempo degustación]]>0, "PAGADA")} -> PAGADA
A38: 20 | B38: Cliente_999 | C38: 1 | D38: 45017.142 | E38: 45017.251 | F38: Mesero_5 | G38: Cena | H38: Tarjeta de crédito | I38: 10.39 | J38: Ocupada | K38: 37 | L38: Brasil | M38: Plato_13 | N38: =_xlfn.XLOOKUP(spaces_3iWczBNnn5rbfoUlE0Jd_uploads_git_blob_9864c7f811c613c3faab876659c6423__25[[#This Row],[Número de Orden]],Cocinadinamica!B39:B807,Cocinadinamica!C39:C807) -> 8 | O38: =spaces_3iWczBNnn5rbfoUlE0Jd_uploads_git_blob_9864c7f811c613c3faab876659c6423__25[[#This Row],[Hora de Llegada]] -> 45017.142 | P38: =spaces_3iWczBNnn5rbfoUlE0Jd_uploads_git_blob_9864c7f811c613c3faab876659c6423__25[[#This Row],[Hora de Llegada]] -> 45017.142 | Q38: =spaces_3iWczBNnn5rbfoUlE0Jd_uploads_git_blob_9864c7f811c613c3faab876659c6423__25[[#This Row],[Hora de Salida]] -> 45017.251 | R38: {=_xlfn.IFS(spaces_3iWczBNnn5rbfoUlE0Jd_uploads_git_blob_9864c7f811c613c3faab876659c6423__25[[#This Row],[Estado de la Mesa]]="Ocupada",(15/1440)+spaces_3iWczBNnn5rbfoUlE0Jd_uploads_git_blob_9864c7f811c613c3faab876659c6423__25[[#This Row],[Hora de salida2]]-spaces_3iWczBNnn5rbfoUlE0Jd_uploads_git_blob_9864c7f811c613c3faab876659c6423__25[[#This Row],[Hora de llegada2]],spaces_3iWczBNnn5rbfoUlE0Jd_uploads_git_blob_9864c7f811c613c3faab876659c6423__25[[#This Row],[Estado de la Mesa]]<>"Ocupada",spaces_3iWczBNnn5rbfoUlE0Jd_uploads_git_blob_9864c7f811c613c3faab876659c6423__25[[#This Row],[Hora de salida2]]-spaces_3iWczBNnn5rbfoUlE0Jd_uploads_git_blob_9864c7f811c613c3faab876659c6423__25[[#This Row],[Hora de llegada2]])} -> 0.12013889 | S38: =_xlfn.XLOOKUP(spaces_3iWczBNnn5rbfoUlE0Jd_uploads_git_blob_9864c7f811c613c3faab876659c6423__25[[#This Row],[Número de Orden]],Cocinadinamica!E39:E807,Cocinadinamica!F39:F807)/1440 -> 0.032638889 | T38: {=_xlfn.IFS((spaces_3iWczBNnn5rbfoUlE0Jd_uploads_git_blob_9864c7f811c613c3faab876659c6423__25[[#This Row],[Tiempo de permanencia]]-spaces_3iWczBNnn5rbfoUlE0Jd_uploads_git_blob_9864c7f811c613c3faab876659c6423__25[[#This Row],[Tiempo de preparación total]])>0,spaces_3iWczBNnn5rbfoUlE0Jd_uploads_git_blob_9864c7f811c613c3faab876659c6423__25[[#This Row],[Tiempo de permanencia]]-spaces_3iWczBNnn5rbfoUlE0Jd_uploads_git_blob_9864c7f811c613c3faab876659c6423__25[[#This Row],[Tiempo de preparación total]],spaces_3iWczBNnn5rbfoUlE0Jd_uploads_git_blob_9864c7f811c613c3faab876659c6423__25[[#This Row],[Tiempo de permanencia]]-spaces_3iWczBNnn5rbfoUlE0Jd_uploads_git_blob_9864c7f811c613c3faab876659c6423__25[[#This Row],[Tiempo de preparación total]]<0,0)} -> 0.0875 | U38: {=_xlfn.IFS(spaces_3iWczBNnn5rbfoUlE0Jd_uploads_git_blob_9864c7f811c613c3faab876659c6423__25[[#This Row],[Tiempo degustación]]=0,"NO PAGADA",spaces_3iWczBNnn5rbfoUlE0Jd_uploads_git_blob_9864c7f811c613c3faab876659c6423__25[[#This Row],[Tiempo degustación]]>0, "PAGADA")} -> PAGADA
A39: 10 | B39: Cliente_167 | C39: 6 | D39: 45017.11 | E39: 45017.162 | F39: Mesero_4 | G39: Almuerzo | H39: Tarjeta de débito | I39: 16.31 | J39: Reservada | K39: 38 | L39: Chile | M39: Plato_17, Plato_8, Plato_19 | N39: =_xlfn.XLOOKUP(spaces_3iWczBNnn5rbfoUlE0Jd_uploads_git_blob_9864c7f811c613c3faab876659c6423__25[[#This Row],[Número de Orden]],Cocinadinamica!B40:B808,Cocinadinamica!C40:C808) -> 92 | O39: =spaces_3iWczBNnn5rbfoUlE0Jd_uploads_git_blob_9864c7f811c613c3faab876659c6423__25[[#This Row],[Hora de Llegada]] -> 45017.11 | P39: =spaces_3iWczBNnn5rbfoUlE0Jd_uploads_git_blob_9864c7f811c613c3faab876659c6423__25[[#This Row],[Hora de Llegada]] -> 45017.11 | Q39: =spaces_3iWczBNnn5rbfoUlE0Jd_uploads_git_blob_9864c7f811c613c3faab876659c6423__25[[#This Row],[Hora de Salida]] -> 45017.162 | R39: {=_xlfn.IFS(spaces_3iWczBNnn5rbfoUlE0Jd_uploads_git_blob_9864c7f811c613c3faab876659c6423__25[[#This Row],[Estado de la Mesa]]="Ocupada",(15/1440)+spaces_3iWczBNnn5rbfoUlE0Jd_uploads_git_blob_9864c7f811c613c3faab876659c6423__25[[#This Row],[Hora de salida2]]-spaces_3iWczBNnn5rbfoUlE0Jd_uploads_git_blob_9864c7f811c613c3faab876659c6423__25[[#This Row],[Hora de llegada2]],spaces_3iWczBNnn5rbfoUlE0Jd_uploads_git_blob_9864c7f811c613c3faab876659c6423__25[[#This Row],[Estado de la Mesa]]<>"Ocupada",spaces_3iWczBNnn5rbfoUlE0Jd_uploads_git_blob_9864c7f811c613c3faab876659c6423__25[[#This Row],[Hora de salida2]]-spaces_3iWczBNnn5rbfoUlE0Jd_uploads_git_blob_9864c7f811c613c3faab876659c6423__25[[#This Row],[Hora de llegada2]])} -> 0.052083333 | S39: =_xlfn.XLOOKUP(spaces_3iWczBNnn5rbfoUlE0Jd_uploads_git_blob_9864c7f811c613c3faab876659c6423__25[[#This Row],[Número de Orden]],Cocinadinamica!E40:E808,Cocinadinamica!F40:F808)/1440 -> 0.068055556 | T39: {=_xlfn.IFS((spaces_3iWczBNnn5rbfoUlE0Jd_uploads_git_blob_9864c7f811c613c3faab876659c6423__25[[#This Row],[Tiempo de permanencia]]-spaces_3iWczBNnn5rbfoUlE0Jd_uploads_git_blob_9864c7f811c613c3faab876659c6423__25[[#This Row],[Tiempo de preparación total]])>0,spaces_3iWczBNnn5rbfoUlE0Jd_uploads_git_blob_9864c7f811c613c3faab876659c6423__25[[#This Row],[Tiempo de permanencia]]-spaces_3iWczBNnn5rbfoUlE0Jd_uploads_git_blob_9864c7f811c613c3faab876659c6423__25[[#This Row],[Tiempo de preparación total]],spaces_3iWczBNnn5rbfoUlE0Jd_uploads_git_blob_9864c7f811c613c3faab876659c6423__25[[#This Row],[Tiempo de permanencia]]-spaces_3iWczBNnn5rbfoUlE0Jd_uploads_git_blob_9864c7f811c613c3faab876659c6423__25[[#This Row],[Tiempo de preparación total]]<0,0)} -> 0 | U39: {=_xlfn.IFS(spaces_3iWczBNnn5rbfoUlE0Jd_uploads_git_blob_9864c7f811c613c3faab876659c6423__25[[#This Row],[Tiempo degustación]]=0,"NO PAGADA",spaces_3iWczBNnn5rbfoUlE0Jd_uploads_git_blob_9864c7f811c613c3faab876659c6423__25[[#This Row],[Tiempo degustación]]>0, "PAGADA")} -> NO PAGADA
A40: 15 | B40: Cliente_606 | C40: 3 | D40: 45017.153 | E40: 45017.319 | F40: Mesero_2 | G40: Cena | H40: Efectivo | I40: 48.36 | J40: Ocupada | K40: 39 | L40: Bolivia | M40: Plato_19 | N40: =_xlfn.XLOOKUP(spaces_3iWczBNnn5rbfoUlE0Jd_uploads_git_blob_9864c7f811c613c3faab876659c6423__25[[#This Row],[Número de Orden]],Cocinadinamica!B41:B809,Cocinadinamica!C41:C809) -> 42 | O40: =spaces_3iWczBNnn5rbfoUlE0Jd_uploads_git_blob_9864c7f811c613c3faab876659c6423__25[[#This Row],[Hora de Llegada]] -> 45017.153 | P40: =spaces_3iWczBNnn5rbfoUlE0Jd_uploads_git_blob_9864c7f811c613c3faab876659c6423__25[[#This Row],[Hora de Llegada]] -> 45017.153 | Q40: =spaces_3iWczBNnn5rbfoUlE0Jd_uploads_git_blob_9864c7f811c613c3faab876659c6423__25[[#This Row],[Hora de Salida]] -> 45017.319 | R40: {=_xlfn.IFS(spaces_3iWczBNnn5rbfoUlE0Jd_uploads_git_blob_9864c7f811c613c3faab876659c6423__25[[#This Row],[Estado de la Mesa]]="Ocupada",(15/1440)+spaces_3iWczBNnn5rbfoUlE0Jd_uploads_git_blob_9864c7f811c613c3faab876659c6423__25[[#This Row],[Hora de salida2]]-spaces_3iWczBNnn5rbfoUlE0Jd_uploads_git_blob_9864c7f811c613c3faab876659c6423__25[[#This Row],[Hora de llegada2]],spaces_3iWczBNnn5rbfoUlE0Jd_uploads_git_blob_9864c7f811c613c3faab876659c6423__25[[#This Row],[Estado de la Mesa]]<>"Ocupada",spaces_3iWczBNnn5rbfoUlE0Jd_uploads_git_blob_9864c7f811c613c3faab876659c6423__25[[#This Row],[Hora de salida2]]-spaces_3iWczBNnn5rbfoUlE0Jd_uploads_git_blob_9864c7f811c613c3faab876659c6423__25[[#This Row],[Hora de llegada2]])} -> 0.17569444 | S40: =_xlfn.XLOOKUP(spaces_3iWczBNnn5rbfoUlE0Jd_uploads_git_blob_9864c7f811c613c3faab876659c6423__25[[#This Row],[Número de Orden]],Cocinadinamica!E41:E809,Cocinadinamica!F41:F809)/1440 -> 0.039583333 | T40: {=_xlfn.IFS((spaces_3iWczBNnn5rbfoUlE0Jd_uploads_git_blob_9864c7f811c613c3faab876659c6423__25[[#This Row],[Tiempo de permanencia]]-spaces_3iWczBNnn5rbfoUlE0Jd_uploads_git_blob_9864c7f811c613c3faab876659c6423__25[[#This Row],[Tiempo de preparación total]])>0,spaces_3iWczBNnn5rbfoUlE0Jd_uploads_git_blob_9864c7f811c613c3faab876659c6423__25[[#This Row],[Tiempo de permanencia]]-spaces_3iWczBNnn5rbfoUlE0Jd_uploads_git_blob_9864c7f811c613c3faab876659c6423__25[[#This Row],[Tiempo de preparación total]],spaces_3iWczBNnn5rbfoUlE0Jd_uploads_git_blob_9864c7f811c613c3faab876659c6423__25[[#This Row],[Tiempo de permanencia]]-spaces_3iWczBNnn5rbfoUlE0Jd_uploads_git_blob_9864c7f811c613c3faab876659c6423__25[[#This Row],[Tiempo de preparación total]]<0,0)} -> 0.13611111 | U40: {=_xlfn.IFS(spaces_3iWczBNnn5rbfoUlE0Jd_uploads_git_blob_9864c7f811c613c3faab876659c6423__25[[#This Row],[Tiempo degustación]]=0,"NO PAGADA",spaces_3iWczBNnn5rbfoUlE0Jd_uploads_git_blob_9864c7f811c613c3faab876659c6423__25[[#This Row],[Tiempo degustación]]>0, "PAGADA")} -> PAGADA
A41: 1 | B41: Cliente_710 | C41: 1 | D41: 45017.083 | E41: 45017.17 | F41: Mesero_3 | G41: Almuerzo | H41: Efectivo | I41: 13.68 | J41: Libre | K41: 40 | L41: Argentina | M41: Plato_9, Plato_11, Plato_16 | N41: =_xlfn.XLOOKUP(spaces_3iWczBNnn5rbfoUlE0Jd_uploads_git_blob_9864c7f811c613c3faab876659c6423__25[[#This Row],[Número de Orden]],Cocinadinamica!B42:B810,Cocinadinamica!C42:C810) -> 61 | O41: =spaces_3iWczBNnn5rbfoUlE0Jd_uploads_git_blob_9864c7f811c613c3faab876659c6423__25[[#This Row],[Hora de Llegada]] -> 45017.083 | P41: =spaces_3iWczBNnn5rbfoUlE0Jd_uploads_git_blob_9864c7f811c613c3faab876659c6423__25[[#This Row],[Hora de Llegada]] -> 45017.083 | Q41: =spaces_3iWczBNnn5rbfoUlE0Jd_uploads_git_blob_9864c7f811c613c3faab876659c6423__25[[#This Row],[Hora de Salida]] -> 45017.17 | R41: {=_xlfn.IFS(spaces_3iWczBNnn5rbfoUlE0Jd_uploads_git_blob_9864c7f811c613c3faab876659c6423__25[[#This Row],[Estado de la Mesa]]="Ocupada",(15/1440)+spaces_3iWczBNnn5rbfoUlE0Jd_uploads_git_blob_9864c7f811c613c3faab876659c6423__25[[#This Row],[Hora de salida2]]-spaces_3iWczBNnn5rbfoUlE0Jd_uploads_git_blob_9864c7f811c613c3faab876659c6423__25[[#This Row],[Hora de llegada2]],spaces_3iWczBNnn5rbfoUlE0Jd_uploads_git_blob_9864c7f811c613c3faab876659c6423__25[[#This Row],[Estado de la Mesa]]<>"Ocupada",spaces_3iWczBNnn5rbfoUlE0Jd_uploads_git_blob_9864c7f811c613c3faab876659c6423__25[[#This Row],[Hora de salida2]]-spaces_3iWczBNnn5rbfoUlE0Jd_uploads_git_blob_9864c7f811c613c3faab876659c6423__25[[#This Row],[Hora de llegada2]])} -> 0.086805556 | S41: =_xlfn.XLOOKUP(spaces_3iWczBNnn5rbfoUlE0Jd_uploads_git_blob_9864c7f811c613c3faab876659c6423__25[[#This Row],[Número de Orden]],Cocinadinamica!E42:E810,Cocinadinamica!F42:F810)/1440 -> 0.054166667 | T41: {=_xlfn.IFS((spaces_3iWczBNnn5rbfoUlE0Jd_uploads_git_blob_9864c7f811c613c3faab876659c6423__25[[#This Row],[Tiempo de permanencia]]-spaces_3iWczBNnn5rbfoUlE0Jd_uploads_git_blob_9864c7f811c613c3faab876659c6423__25[[#This Row],[Tiempo de preparación total]])>0,spaces_3iWczBNnn5rbfoUlE0Jd_uploads_git_blob_9864c7f811c613c3faab876659c6423__25[[#This Row],[Tiempo de permanencia]]-spaces_3iWczBNnn5rbfoUlE0Jd_uploads_git_blob_9864c7f811c613c3faab876659c6423__25[[#This Row],[Tiempo de preparación total]],spaces_3iWczBNnn5rbfoUlE0Jd_uploads_git_blob_9864c7f811c613c3faab876659c6423__25[[#This Row],[Tiempo de permanencia]]-spaces_3iWczBNnn5rbfoUlE0Jd_uploads_git_blob_9864c7f811c613c3faab876659c6423__25[[#This Row],[Tiempo de preparación total]]<0,0)} -> 0.032638889 | U41: {=_xlfn.IFS(spaces_3iWczBNnn5rbfoUlE0Jd_uploads_git_blob_9864c7f811c613c3faab876659c6423__25[[#This Row],[Tiempo degustación]]=0,"NO PAGADA",spaces_3iWczBNnn5rbfoUlE0Jd_uploads_git_blob_9864c7f811c613c3faab876659c6423__25[[#This Row],[Tiempo degustación]]>0, "PAGADA")} -> PAGADA
A42: 7 | B42: Cliente_870 | C42: 4 | D42: 45017.093 | E42: 45017.181 | F42: Mesero_2 | G42: Almuerzo | H42: Tarjeta de crédito | I42: 15.24 | J42: Ocupada | K42: 41 | L42: Perú | M42: Plato_15, Plato_10, Plato_2 | N42: =_xlfn.XLOOKUP(spaces_3iWczBNnn5rbfoUlE0Jd_uploads_git_blob_9864c7f811c613c3faab876659c6423__25[[#This Row],[Número de Orden]],Cocinadinamica!B43:B811,Cocinadinamica!C43:C811) -> 84 | O42: =spaces_3iWczBNnn5rbfoUlE0Jd_uploads_git_blob_9864c7f811c613c3faab876659c6423__25[[#This Row],[Hora de Llegada]] -> 45017.093 | P42: =spaces_3iWczBNnn5rbfoUlE0Jd_uploads_git_blob_9864c7f811c613c3faab876659c6423__25[[#This Row],[Hora de Llegada]] -> 45017.093 | Q42: =spaces_3iWczBNnn5rbfoUlE0Jd_uploads_git_blob_9864c7f811c613c3faab876659c6423__25[[#This Row],[Hora de Salida]] -> 45017.181 | R42: {=_xlfn.IFS(spaces_3iWczBNnn5rbfoUlE0Jd_uploads_git_blob_9864c7f811c613c3faab876659c6423__25[[#This Row],[Estado de la Mesa]]="Ocupada",(15/1440)+spaces_3iWczBNnn5rbfoUlE0Jd_uploads_git_blob_9864c7f811c613c3faab876659c6423__25[[#This Row],[Hora de salida2]]-spaces_3iWczBNnn5rbfoUlE0Jd_uploads_git_blob_9864c7f811c613c3faab876659c6423__25[[#This Row],[Hora de llegada2]],spaces_3iWczBNnn5rbfoUlE0Jd_uploads_git_blob_9864c7f811c613c3faab876659c6423__25[[#This Row],[Estado de la Mesa]]<>"Ocupada",spaces_3iWczBNnn5rbfoUlE0Jd_uploads_git_blob_9864c7f811c613c3faab876659c6423__25[[#This Row],[Hora de salida2]]-spaces_3iWczBNnn5rbfoUlE0Jd_uploads_git_blob_9864c7f811c613c3faab876659c6423__25[[#This Row],[Hora de llegada2]])} -> 0.097916667 | S42: =_xlfn.XLOOKUP(spaces_3iWczBNnn5rbfoUlE0Jd_uploads_git_blob_9864c7f811c613c3faab876659c6423__25[[#This Row],[Número de Orden]],Cocinadinamica!E43:E811,Cocinadinamica!F43:F811)/1440 -> 0.061805556 | T42: {=_xlfn.IFS((spaces_3iWczBNnn5rbfoUlE0Jd_uploads_git_blob_9864c7f811c613c3faab876659c6423__25[[#This Row],[Tiempo de permanencia]]-spaces_3iWczBNnn5rbfoUlE0Jd_uploads_git_blob_9864c7f811c613c3faab876659c6423__25[[#This Row],[Tiempo de preparación total]])>0,spaces_3iWczBNnn5rbfoUlE0Jd_uploads_git_blob_9864c7f811c613c3faab876659c6423__25[[#This Row],[Tiempo de permanencia]]-spaces_3iWczBNnn5rbfoUlE0Jd_uploads_git_blob_9864c7f811c613c3faab876659c6423__25[[#This Row],[Tiempo de preparación total]],spaces_3iWczBNnn5rbfoUlE0Jd_uploads_git_blob_9864c7f811c613c3faab876659c6423__25[[#This Row],[Tiempo de permanencia]]-spaces_3iWczBNnn5rbfoUlE0Jd_uploads_git_blob_9864c7f811c613c3faab876659c6423__25[[#This Row],[Tiempo de preparación total]]<0,0)} -> 0.036111111 | U42: {=_xlfn.IFS(spaces_3iWczBNnn5rbfoUlE0Jd_uploads_git_blob_9864c7f811c613c3faab876659c6423__25[[#This Row],[Tiempo degustación]]=0,"NO PAGADA",spaces_3iWczBNnn5rbfoUlE0Jd_uploads_git_blob_9864c7f811c613c3faab876659c6423__25[[#This Row],[Tiempo degustación]]>0, "PAGADA")} -> PAGADA
A43: 14 | B43: Cliente_230 | C43: 1 | D43: 45017.017 | E43: 45017.074 | F43: Mesero_2 | G43: Almuerzo | H43: Tarjeta de crédito | I43: 49.58 | J43: Reservada | K43: 42 | L43: Bolivia | M43: Plato_5, Plato_20 | N43: =_xlfn.XLOOKUP(spaces_3iWczBNnn5rbfoUlE0Jd_uploads_git_blob_9864c7f811c613c3faab876659c6423__25[[#This Row],[Número de Orden]],Cocinadinamica!B44:B812,Cocinadinamica!C44:C812) -> 39 | O43: =spaces_3iWczBNnn5rbfoUlE0Jd_uploads_git_blob_9864c7f811c613c3faab876659c6423__25[[#This Row],[Hora de Llegada]] -> 45017.017 | P43: =spaces_3iWczBNnn5rbfoUlE0Jd_uploads_git_blob_9864c7f811c613c3faab876659c6423__25[[#This Row],[Hora de Llegada]] -> 45017.017 | Q43: =spaces_3iWczBNnn5rbfoUlE0Jd_uploads_git_blob_9864c7f811c613c3faab876659c6423__25[[#This Row],[Hora de Salida]] -> 45017.074 | R43: {=_xlfn.IFS(spaces_3iWczBNnn5rbfoUlE0Jd_uploads_git_blob_9864c7f811c613c3faab876659c6423__25[[#This Row],[Estado de la Mesa]]="Ocupada",(15/1440)+spaces_3iWczBNnn5rbfoUlE0Jd_uploads_git_blob_9864c7f811c613c3faab876659c6423__25[[#This Row],[Hora de salida2]]-spaces_3iWczBNnn5rbfoUlE0Jd_uploads_git_blob_9864c7f811c613c3faab876659c6423__25[[#This Row],[Hora de llegada2]],spaces_3iWczBNnn5rbfoUlE0Jd_uploads_git_blob_9864c7f811c613c3faab876659c6423__25[[#This Row],[Estado de la Mesa]]<>"Ocupada",spaces_3iWczBNnn5rbfoUlE0Jd_uploads_git_blob_9864c7f811c613c3faab876659c6423__25[[#This Row],[Hora de salida2]]-spaces_3iWczBNnn5rbfoUlE0Jd_uploads_git_blob_9864c7f811c613c3faab876659c6423__25[[#This Row],[Hora de llegada2]])} -> 0.05625 | S43: =_xlfn.XLOOKUP(spaces_3iWczBNnn5rbfoUlE0Jd_uploads_git_blob_9864c7f811c613c3faab876659c6423__25[[#This Row],[Número de Orden]],Cocinadinamica!E44:E812,Cocinadinamica!F44:F812)/1440 -> 0.047916667 | T43: {=_xlfn.IFS((spaces_3iWczBNnn5rbfoUlE0Jd_uploads_git_blob_9864c7f811c613c3faab876659c6423__25[[#This Row],[Tiempo de permanencia]]-spaces_3iWczBNnn5rbfoUlE0Jd_uploads_git_blob_9864c7f811c613c3faab876659c6423__25[[#This Row],[Tiempo de preparación total]])>0,spaces_3iWczBNnn5rbfoUlE0Jd_uploads_git_blob_9864c7f811c613c3faab876659c6423__25[[#This Row],[Tiempo de permanencia]]-spaces_3iWczBNnn5rbfoUlE0Jd_uploads_git_blob_9864c7f811c613c3faab876659c6423__25[[#This Row],[Tiempo de preparación total]],spaces_3iWczBNnn5rbfoUlE0Jd_uploads_git_blob_9864c7f811c613c3faab876659c6423__25[[#This Row],[Tiempo de permanencia]]-spaces_3iWczBNnn5rbfoUlE0Jd_uploads_git_blob_9864c7f811c613c3faab876659c6423__25[[#This Row],[Tiempo de preparación total]]<0,0)} -> 0.0083333333 | U43: {=_xlfn.IFS(spaces_3iWczBNnn5rbfoUlE0Jd_uploads_git_blob_9864c7f811c613c3faab876659c6423__25[[#This Row],[Tiempo degustación]]=0,"NO PAGADA",spaces_3iWczBNnn5rbfoUlE0Jd_uploads_git_blob_9864c7f811c613c3faab876659c6423__25[[#This Row],[Tiempo degustación]]>0, "PAGADA")} -> PAGADA
A44: 8 | B44: Cliente_814 | C44: 6 | D44: 45017.043 | E44: 45017.135 | F44: Mesero_4 | G44: Almuerzo | H44: Tarjeta de crédito | I44: 32.19 | J44: Ocupada | K44: 43 | L44: Perú | M44: Plato_15, Plato_18, Plato_7, Plato_17 | N44: =_xlfn.XLOOKUP(spaces_3iWczBNnn5rbfoUlE0Jd_uploads_git_blob_9864c7f811c613c3faab876659c6423__25[[#This Row],[Número de Orden]],Cocinadinamica!B45:B813,Cocinadinamica!C45:C813) -> 83 | O44: =spaces_3iWczBNnn5rbfoUlE0Jd_uploads_git_blob_9864c7f811c613c3faab876659c6423__25[[#This Row],[Hora de Llegada]] -> 45017.043 | P44: =spaces_3iWczBNnn5rbfoUlE0Jd_uploads_git_blob_9864c7f811c613c3faab876659c6423__25[[#This Row],[Hora de Llegada]] -> 45017.043 | Q44: =spaces_3iWczBNnn5rbfoUlE0Jd_uploads_git_blob_9864c7f811c613c3faab876659c6423__25[[#This Row],[Hora de Salida]] -> 45017.135 | R44: {=_xlfn.IFS(spaces_3iWczBNnn5rbfoUlE0Jd_uploads_git_blob_9864c7f811c613c3faab876659c6423__25[[#This Row],[Estado de la Mesa]]="Ocupada",(15/1440)+spaces_3iWczBNnn5rbfoUlE0Jd_uploads_git_blob_9864c7f811c613c3faab876659c6423__25[[#This Row],[Hora de salida2]]-spaces_3iWczBNnn5rbfoUlE0Jd_uploads_git_blob_9864c7f811c613c3faab876659c6423__25[[#This Row],[Hora de llegada2]],spaces_3iWczBNnn5rbfoUlE0Jd_uploads_git_blob_9864c7f811c613c3faab876659c6423__25[[#This Row],[Estado de la Mesa]]<>"Ocupada",spaces_3iWczBNnn5rbfoUlE0Jd_uploads_git_blob_9864c7f811c613c3faab876659c6423__25[[#This Row],[Hora de salida2]]-spaces_3iWczBNnn5rbfoUlE0Jd_uploads_git_blob_9864c7f811c613c3faab876659c6423__25[[#This Row],[Hora de llegada2]])} -> 0.10208333 | S44: =_xlfn.XLOOKUP(spaces_3iWczBNnn5rbfoUlE0Jd_uploads_git_blob_9864c7f811c613c3faab876659c6423__25[[#This Row],[Número de Orden]],Cocinadinamica!E45:E813,Cocinadinamica!F45:F813)/1440 -> 0.10138889 | T44: {=_xlfn.IFS((spaces_3iWczBNnn5rbfoUlE0Jd_uploads_git_blob_9864c7f811c613c3faab876659c6423__25[[#This Row],[Tiempo de permanencia]]-spaces_3iWczBNnn5rbfoUlE0Jd_uploads_git_blob_9864c7f811c613c3faab876659c6423__25[[#This Row],[Tiempo de preparación total]])>0,spaces_3iWczBNnn5rbfoUlE0Jd_uploads_git_blob_9864c7f811c613c3faab876659c6423__25[[#This Row],[Tiempo de permanencia]]-spaces_3iWczBNnn5rbfoUlE0Jd_uploads_git_blob_9864c7f811c613c3faab876659c6423__25[[#This Row],[Tiempo de preparación total]],spaces_3iWczBNnn5rbfoUlE0Jd_uploads_git_blob_9864c7f811c613c3faab876659c6423__25[[#This Row],[Tiempo de permanencia]]-spaces_3iWczBNnn5rbfoUlE0Jd_uploads_git_blob_9864c7f811c613c3faab876659c6423__25[[#This Row],[Tiempo de preparación total]]<0,0)} -> 0.00069444444 | U44: {=_xlfn.IFS(spaces_3iWczBNnn5rbfoUlE0Jd_uploads_git_blob_9864c7f811c613c3faab876659c6423__25[[#This Row],[Tiempo degustación]]=0,"NO PAGADA",spaces_3iWczBNnn5rbfoUlE0Jd_uploads_git_blob_9864c7f811c613c3faab876659c6423__25[[#This Row],[Tiempo degustación]]>0, "PAGADA")} -> PAGADA
A45: 18 | B45: Cliente_710 | C45: 1 | D45: 45017.129 | E45: 45017.262 | F45: Mesero_4 | G45: Almuerzo | H45: Tarjeta de crédito | I45: 42.6 | J45: Libre | K45: 44 | L45: España | M45: Plato_10, Plato_1, Plato_13 | N45: =_xlfn.XLOOKUP(spaces_3iWczBNnn5rbfoUlE0Jd_uploads_git_blob_9864c7f811c613c3faab876659c6423__25[[#This Row],[Número de Orden]],Cocinadinamica!B46:B814,Cocinadinamica!C46:C814) -> 49 | O45: =spaces_3iWczBNnn5rbfoUlE0Jd_uploads_git_blob_9864c7f811c613c3faab876659c6423__25[[#This Row],[Hora de Llegada]] -> 45017.129 | P45: =spaces_3iWczBNnn5rbfoUlE0Jd_uploads_git_blob_9864c7f811c613c3faab876659c6423__25[[#This Row],[Hora de Llegada]] -> 45017.129 | Q45: =spaces_3iWczBNnn5rbfoUlE0Jd_uploads_git_blob_9864c7f811c613c3faab876659c6423__25[[#This Row],[Hora de Salida]] -> 45017.262 | R45: {=_xlfn.IFS(spaces_3iWczBNnn5rbfoUlE0Jd_uploads_git_blob_9864c7f811c613c3faab876659c6423__25[[#This Row],[Estado de la Mesa]]="Ocupada",(15/1440)+spaces_3iWczBNnn5rbfoUlE0Jd_uploads_git_blob_9864c7f811c613c3faab876659c6423__25[[#This Row],[Hora de salida2]]-spaces_3iWczBNnn5rbfoUlE0Jd_uploads_git_blob_9864c7f811c613c3faab876659c6423__25[[#This Row],[Hora de llegada2]],spaces_3iWczBNnn5rbfoUlE0Jd_uploads_git_blob_9864c7f811c613c3faab876659c6423__25[[#This Row],[Estado de la Mesa]]<>"Ocupada",spaces_3iWczBNnn5rbfoUlE0Jd_uploads_git_blob_9864c7f811c613c3faab876659c6423__25[[#This Row],[Hora de salida2]]-spaces_3iWczBNnn5rbfoUlE0Jd_uploads_git_blob_9864c7f811c613c3faab876659c6423__25[[#This Row],[Hora de llegada2]])} -> 0.13333333 | S45: =_xlfn.XLOOKUP(spaces_3iWczBNnn5rbfoUlE0Jd_uploads_git_blob_9864c7f811c613c3faab876659c6423__25[[#This Row],[Número de Orden]],Cocinadinamica!E46:E814,Cocinadinamica!F46:F814)/1440 -> 0.059027778 | T45: {=_xlfn.IFS((spaces_3iWczBNnn5rbfoUlE0Jd_uploads_git_blob_9864c7f811c613c3faab876659c6423__25[[#This Row],[Tiempo de permanencia]]-spaces_3iWczBNnn5rbfoUlE0Jd_uploads_git_blob_9864c7f811c613c3faab876659c6423__25[[#This Row],[Tiempo de preparación total]])>0,spaces_3iWczBNnn5rbfoUlE0Jd_uploads_git_blob_9864c7f811c613c3faab876659c6423__25[[#This Row],[Tiempo de permanencia]]-spaces_3iWczBNnn5rbfoUlE0Jd_uploads_git_blob_9864c7f811c613c3faab876659c6423__25[[#This Row],[Tiempo de preparación total]],spaces_3iWczBNnn5rbfoUlE0Jd_uploads_git_blob_9864c7f811c613c3faab876659c6423__25[[#This Row],[Tiempo de permanencia]]-spaces_3iWczBNnn5rbfoUlE0Jd_uploads_git_blob_9864c7f811c613c3faab876659c6423__25[[#This Row],[Tiempo de preparación total]]<0,0)} -> 0.074305556 | U45: {=_xlfn.IFS(spaces_3iWczBNnn5rbfoUlE0Jd_uploads_git_blob_9864c7f811c613c3faab876659c6423__25[[#This Row],[Tiempo degustación]]=0,"NO PAGADA",spaces_3iWczBNnn5rbfoUlE0Jd_uploads_git_blob_9864c7f811c613c3faab876659c6423__25[[#This Row],[Tiempo degustación]]>0, "PAGADA")} -> PAGADA
A46: 17 | B46: Cliente_640 | C46: 2 | D46: 45017.094 | E46: 45017.167 | F46: Mesero_2 | G46: Almuerzo | H46: Tarjeta de crédito | I46: 25.41 | J46: Reservada | K46: 45 | L46: Perú | M46: Plato_4 | N46: =_xlfn.XLOOKUP(spaces_3iWczBNnn5rbfoUlE0Jd_uploads_git_blob_9864c7f811c613c3faab876659c6423__25[[#This Row],[Número de Orden]],Cocinadinamica!B47:B815,Cocinadinamica!C47:C815) -> 24 | O46: =spaces_3iWczBNnn5rbfoUlE0Jd_uploads_git_blob_9864c7f811c613c3faab876659c6423__25[[#This Row],[Hora de Llegada]] -> 45017.094 | P46: =spaces_3iWczBNnn5rbfoUlE0Jd_uploads_git_blob_9864c7f811c613c3faab876659c6423__25[[#This Row],[Hora de Llegada]] -> 45017.094 | Q46: =spaces_3iWczBNnn5rbfoUlE0Jd_uploads_git_blob_9864c7f811c613c3faab876659c6423__25[[#This Row],[Hora de Salida]] -> 45017.167 | R46: {=_xlfn.IFS(spaces_3iWczBNnn5rbfoUlE0Jd_uploads_git_blob_9864c7f811c613c3faab876659c6423__25[[#This Row],[Estado de la Mesa]]="Ocupada",(15/1440)+spaces_3iWczBNnn5rbfoUlE0Jd_uploads_git_blob_9864c7f811c613c3faab876659c6423__25[[#This Row],[Hora de salida2]]-spaces_3iWczBNnn5rbfoUlE0Jd_uploads_git_blob_9864c7f811c613c3faab876659c6423__25[[#This Row],[Hora de llegada2]],spaces_3iWczBNnn5rbfoUlE0Jd_uploads_git_blob_9864c7f811c613c3faab876659c6423__25[[#This Row],[Estado de la Mesa]]<>"Ocupada",spaces_3iWczBNnn5rbfoUlE0Jd_uploads_git_blob_9864c7f811c613c3faab876659c6423__25[[#This Row],[Hora de salida2]]-spaces_3iWczBNnn5rbfoUlE0Jd_uploads_git_blob_9864c7f811c613c3faab876659c6423__25[[#This Row],[Hora de llegada2]])} -> 0.073611111 | S46: =_xlfn.XLOOKUP(spaces_3iWczBNnn5rbfoUlE0Jd_uploads_git_blob_9864c7f811c613c3faab876659c6423__25[[#This Row],[Número de Orden]],Cocinadinamica!E47:E815,Cocinadinamica!F47:F815)/1440 -> 0.032638889 | T46: {=_xlfn.IFS((spaces_3iWczBNnn5rbfoUlE0Jd_uploads_git_blob_9864c7f811c613c3faab876659c6423__25[[#This Row],[Tiempo de permanencia]]-spaces_3iWczBNnn5rbfoUlE0Jd_uploads_git_blob_9864c7f811c613c3faab876659c6423__25[[#This Row],[Tiempo de preparación total]])>0,spaces_3iWczBNnn5rbfoUlE0Jd_uploads_git_blob_9864c7f811c613c3faab876659c6423__25[[#This Row],[Tiempo de permanencia]]-spaces_3iWczBNnn5rbfoUlE0Jd_uploads_git_blob_9864c7f811c613c3faab876659c6423__25[[#This Row],[Tiempo de preparación total]],spaces_3iWczBNnn5rbfoUlE0Jd_uploads_git_blob_9864c7f811c613c3faab876659c6423__25[[#This Row],[Tiempo de permanencia]]-spaces_3iWczBNnn5rbfoUlE0Jd_uploads_git_blob_9864c7f811c613c3faab876659c6423__25[[#This Row],[Tiempo de preparación total]]<0,0)} -> 0.040972222 | U46: {=_xlfn.IFS(spaces_3iWczBNnn5rbfoUlE0Jd_uploads_git_blob_9864c7f811c613c3faab876659c6423__25[[#This Row],[Tiempo degustación]]=0,"NO PAGADA",spaces_3iWczBNnn5rbfoUlE0Jd_uploads_git_blob_9864c7f811c613c3faab876659c6423__25[[#This Row],[Tiempo degustación]]>0, "PAGADA")} -> PAGADA
A47: 10 | B47: Cliente_623 | C47: 1 | D47: 45017.074 | E47: 45017.152 | F47: Mesero_5 | G47: Almuerzo | H47: Tarjeta de crédito | I47: 27.97 | J47: Libre | K47: 46 | L47: Chile | M47: Plato_2, Plato_18, Plato_14 | N47: =_xlfn.XLOOKUP(spaces_3iWczBNnn5rbfoUlE0Jd_uploads_git_blob_9864c7f811c613c3faab876659c6423__25[[#This Row],[Número de Orden]],Cocinadinamica!B48:B816,Cocinadinamica!C48:C816) -> 56 | O47: =spaces_3iWczBNnn5rbfoUlE0Jd_uploads_git_blob_9864c7f811c613c3faab876659c6423__25[[#This Row],[Hora de Llegada]] -> 45017.074 | P47: =spaces_3iWczBNnn5rbfoUlE0Jd_uploads_git_blob_9864c7f811c613c3faab876659c6423__25[[#This Row],[Hora de Llegada]] -> 45017.074 | Q47: =spaces_3iWczBNnn5rbfoUlE0Jd_uploads_git_blob_9864c7f811c613c3faab876659c6423__25[[#This Row],[Hora de Salida]] -> 45017.152 | R47: {=_xlfn.IFS(spaces_3iWczBNnn5rbfoUlE0Jd_uploads_git_blob_9864c7f811c613c3faab876659c6423__25[[#This Row],[Estado de la Mesa]]="Ocupada",(15/1440)+spaces_3iWczBNnn5rbfoUlE0Jd_uploads_git_blob_9864c7f811c613c3faab876659c6423__25[[#This Row],[Hora de salida2]]-spaces_3iWczBNnn5rbfoUlE0Jd_uploads_git_blob_9864c7f811c613c3faab876659c6423__25[[#This Row],[Hora de llegada2]],spaces_3iWczBNnn5rbfoUlE0Jd_uploads_git_blob_9864c7f811c613c3faab876659c6423__25[[#This Row],[Estado de la Mesa]]<>"Ocupada",spaces_3iWczBNnn5rbfoUlE0Jd_uploads_git_blob_9864c7f811c613c3faab876659c6423__25[[#This Row],[Hora de salida2]]-spaces_3iWczBNnn5rbfoUlE0Jd_uploads_git_blob_9864c7f811c613c3faab876659c6423__25[[#This Row],[Hora de llegada2]])} -> 0.077777778 | S47: =_xlfn.XLOOKUP(spaces_3iWczBNnn5rbfoUlE0Jd_uploads_git_blob_9864c7f811c613c3faab876659c6423__25[[#This Row],[Número de Orden]],Cocinadinamica!E48:E816,Cocinadinamica!F48:F816)/1440 -> 0.059722222 | T47: {=_xlfn.IFS((spaces_3iWczBNnn5rbfoUlE0Jd_uploads_git_blob_9864c7f811c613c3faab876659c6423__25[[#This Row],[Tiempo de permanencia]]-spaces_3iWczBNnn5rbfoUlE0Jd_uploads_git_blob_9864c7f811c613c3faab876659c6423__25[[#This Row],[Tiempo de preparación total]])>0,spaces_3iWczBNnn5rbfoUlE0Jd_uploads_git_blob_9864c7f811c613c3faab876659c6423__25[[#This Row],[Tiempo de permanencia]]-spaces_3iWczBNnn5rbfoUlE0Jd_uploads_git_blob_9864c7f811c613c3faab876659c6423__25[[#This Row],[Tiempo de preparación total]],spaces_3iWczBNnn5rbfoUlE0Jd_uploads_git_blob_9864c7f811c613c3faab876659c6423__25[[#This Row],[Tiempo de permanencia]]-spaces_3iWczBNnn5rbfoUlE0Jd_uploads_git_blob_9864c7f811c613c3faab876659c6423__25[[#This Row],[Tiempo de preparación total]]<0,0)} -> 0.018055556 | U47: {=_xlfn.IFS(spaces_3iWczBNnn5rbfoUlE0Jd_uploads_git_blob_9864c7f811c613c3faab876659c6423__25[[#This Row],[Tiempo degustación]]=0,"NO PAGADA",spaces_3iWczBNnn5rbfoUlE0Jd_uploads_git_blob_9864c7f811c613c3faab876659c6423__25[[#This Row],[Tiempo degustación]]>0, "PAGADA")} -> PAGADA
A48: 18 | B48: Cliente_72 | C48: 3 | D48: 45017.146 | E48: 45017.312 | F48: Mesero_2 | G48: Almuerzo | H48: Tarjeta de crédito | I48: 10.98 | J48: Ocupada | K48: 47 | L48: Brasil | M48: Plato_11, Plato_14, Plato_3 | N48: =_xlfn.XLOOKUP(spaces_3iWczBNnn5rbfoUlE0Jd_uploads_git_blob_9864c7f811c613c3faab876659c6423__25[[#This Row],[Número de Orden]],Cocinadinamica!B49:B817,Cocinadinamica!C49:C817) -> 43 | O48: =spaces_3iWczBNnn5rbfoUlE0Jd_uploads_git_blob_9864c7f811c613c3faab876659c6423__25[[#This Row],[Hora de Llegada]] -> 45017.146 | P48: =spaces_3iWczBNnn5rbfoUlE0Jd_uploads_git_blob_9864c7f811c613c3faab876659c6423__25[[#This Row],[Hora de Llegada]] -> 45017.146 | Q48: =spaces_3iWczBNnn5rbfoUlE0Jd_uploads_git_blob_9864c7f811c613c3faab876659c6423__25[[#This Row],[Hora de Salida]] -> 45017.312 | R48: {=_xlfn.IFS(spaces_3iWczBNnn5rbfoUlE0Jd_uploads_git_blob_9864c7f811c613c3faab876659c6423__25[[#This Row],[Estado de la Mesa]]="Ocupada",(15/1440)+spaces_3iWczBNnn5rbfoUlE0Jd_uploads_git_blob_9864c7f811c613c3faab876659c6423__25[[#This Row],[Hora de salida2]]-spaces_3iWczBNnn5rbfoUlE0Jd_uploads_git_blob_9864c7f811c613c3faab876659c6423__25[[#This Row],[Hora de llegada2]],spaces_3iWczBNnn5rbfoUlE0Jd_uploads_git_blob_9864c7f811c613c3faab876659c6423__25[[#This Row],[Estado de la Mesa]]<>"Ocupada",spaces_3iWczBNnn5rbfoUlE0Jd_uploads_git_blob_9864c7f811c613c3faab876659c6423__25[[#This Row],[Hora de salida2]]-spaces_3iWczBNnn5rbfoUlE0Jd_uploads_git_blob_9864c7f811c613c3faab876659c6423__25[[#This Row],[Hora de llegada2]])} -> 0.17638889 | S48: =_xlfn.XLOOKUP(spaces_3iWczBNnn5rbfoUlE0Jd_uploads_git_blob_9864c7f811c613c3faab876659c6423__25[[#This Row],[Número de Orden]],Cocinadinamica!E49:E817,Cocinadinamica!F49:F817)/1440 -> 0.060416667 | T48: {=_xlfn.IFS((spaces_3iWczBNnn5rbfoUlE0Jd_uploads_git_blob_9864c7f811c613c3faab876659c6423__25[[#This Row],[Tiempo de permanencia]]-spaces_3iWczBNnn5rbfoUlE0Jd_uploads_git_blob_9864c7f811c613c3faab876659c6423__25[[#This Row],[Tiempo de preparación total]])>0,spaces_3iWczBNnn5rbfoUlE0Jd_uploads_git_blob_9864c7f811c613c3faab876659c6423__25[[#This Row],[Tiempo de permanencia]]-spaces_3iWczBNnn5rbfoUlE0Jd_uploads_git_blob_9864c7f811c613c3faab876659c6423__25[[#This Row],[Tiempo de preparación total]],spaces_3iWczBNnn5rbfoUlE0Jd_uploads_git_blob_9864c7f811c613c3faab876659c6423__25[[#This Row],[Tiempo de permanencia]]-spaces_3iWczBNnn5rbfoUlE0Jd_uploads_git_blob_9864c7f811c613c3faab876659c6423__25[[#This Row],[Tiempo de preparación total]]<0,0)} -> 0.11597222 | U48: {=_xlfn.IFS(spaces_3iWczBNnn5rbfoUlE0Jd_uploads_git_blob_9864c7f811c613c3faab876659c6423__25[[#This Row],[Tiempo degustación]]=0,"NO PAGADA",spaces_3iWczBNnn5rbfoUlE0Jd_uploads_git_blob_9864c7f811c613c3faab876659c6423__25[[#This Row],[Tiempo degustación]]>0, "PAGADA")} -> PAGADA
A49: 17 | B49: Cliente_963 | C49: 2 | D49: 45017.019 | E49: 45017.168 | F49: Mesero_3 | G49: Desayuno | H49: Tarjeta de crédito | I49: 25.31 | J49: Libre | K49: 48 | L49: Bolivia | M49: Plato_6, Plato_5, Plato_11 | N49: =_xlfn.XLOOKUP(spaces_3iWczBNnn5rbfoUlE0Jd_uploads_git_blob_9864c7f811c613c3faab876659c6423__25[[#This Row],[Número de Orden]],Cocinadinamica!B50:B818,Cocinadinamica!C50:C818) -> 64 | O49: =spaces_3iWczBNnn5rbfoUlE0Jd_uploads_git_blob_9864c7f811c613c3faab876659c6423__25[[#This Row],[Hora de Llegada]] -> 45017.019 | P49: =spaces_3iWczBNnn5rbfoUlE0Jd_uploads_git_blob_9864c7f811c613c3faab876659c6423__25[[#This Row],[Hora de Llegada]] -> 45017.019 | Q49: =spaces_3iWczBNnn5rbfoUlE0Jd_uploads_git_blob_9864c7f811c613c3faab876659c6423__25[[#This Row],[Hora de Salida]] -> 45017.168 | R49: {=_xlfn.IFS(spaces_3iWczBNnn5rbfoUlE0Jd_uploads_git_blob_9864c7f811c613c3faab876659c6423__25[[#This Row],[Estado de la Mesa]]="Ocupada",(15/1440)+spaces_3iWczBNnn5rbfoUlE0Jd_uploads_git_blob_9864c7f811c613c3faab876659c6423__25[[#This Row],[Hora de salida2]]-spaces_3iWczBNnn5rbfoUlE0Jd_uploads_git_blob_9864c7f811c613c3faab876659c6423__25[[#This Row],[Hora de llegada2]],spaces_3iWczBNnn5rbfoUlE0Jd_uploads_git_blob_9864c7f811c613c3faab876659c6423__25[[#This Row],[Estado de la Mesa]]<>"Ocupada",spaces_3iWczBNnn5rbfoUlE0Jd_uploads_git_blob_9864c7f811c613c3faab876659c6423__25[[#This Row],[Hora de salida2]]-spaces_3iWczBNnn5rbfoUlE0Jd_uploads_git_blob_9864c7f811c613c3faab876659c6423__25[[#This Row],[Hora de llegada2]])} -> 0.14861111 | S49: =_xlfn.XLOOKUP(spaces_3iWczBNnn5rbfoUlE0Jd_uploads_git_blob_9864c7f811c613c3faab876659c6423__25[[#This Row],[Número de Orden]],Cocinadinamica!E50:E818,Cocinadinamica!F50:F818)/1440 -> 0.086111111 | T49: {=_xlfn.IFS((spaces_3iWczBNnn5rbfoUlE0Jd_uploads_git_blob_9864c7f811c613c3faab876659c6423__25[[#This Row],[Tiempo de permanencia]]-spaces_3iWczBNnn5rbfoUlE0Jd_uploads_git_blob_9864c7f811c613c3faab876659c6423__25[[#This Row],[Tiempo de preparación total]])>0,spaces_3iWczBNnn5rbfoUlE0Jd_uploads_git_blob_9864c7f811c613c3faab876659c6423__25[[#This Row],[Tiempo de permanencia]]-spaces_3iWczBNnn5rbfoUlE0Jd_uploads_git_blob_9864c7f811c613c3faab876659c6423__25[[#This Row],[Tiempo de preparación total]],spaces_3iWczBNnn5rbfoUlE0Jd_uploads_git_blob_9864c7f811c613c3faab876659c6423__25[[#This Row],[Tiempo de permanencia]]-spaces_3iWczBNnn5rbfoUlE0Jd_uploads_git_blob_9864c7f811c613c3faab876659c6423__25[[#This Row],[Tiempo de preparación total]]<0,0)} -> 0.0625 | U49: {=_xlfn.IFS(spaces_3iWczBNnn5rbfoUlE0Jd_uploads_git_blob_9864c7f811c613c3faab876659c6423__25[[#This Row],[Tiempo degustación]]=0,"NO PAGADA",spaces_3iWczBNnn5rbfoUlE0Jd_uploads_git_blob_9864c7f811c613c3faab876659c6423__25[[#This Row],[Tiempo degustación]]>0, "PAGADA")} -> PAGADA
A50: 8 | B50: Cliente_929 | C50: 3 | D50: 45017.072 | E50: 45017.228 | F50: Mesero_2 | G50: Almuerzo | H50: Tarjeta de crédito | I50: 20.92 | J50: Libre | K50: 49 | L50: Uruguay | M50: Plato_7, Plato_15, Plato_4 | N50: =_xlfn.XLOOKUP(spaces_3iWczBNnn5rbfoUlE0Jd_uploads_git_blob_9864c7f811c613c3faab876659c6423__25[[#This Row],[Número de Orden]],Cocinadinamica!B51:B819,Cocinadinamica!C51:C819) -> 77 | O50: =spaces_3iWczBNnn5rbfoUlE0Jd_uploads_git_blob_9864c7f811c613c3faab876659c6423__25[[#This Row],[Hora de Llegada]] -> 45017.072 | P50: =spaces_3iWczBNnn5rbfoUlE0Jd_uploads_git_blob_9864c7f811c613c3faab876659c6423__25[[#This Row],[Hora de Llegada]] -> 45017.072 | Q50: =spaces_3iWczBNnn5rbfoUlE0Jd_uploads_git_blob_9864c7f811c613c3faab876659c6423__25[[#This Row],[Hora de Salida]] -> 45017.228 | R50: {=_xlfn.IFS(spaces_3iWczBNnn5rbfoUlE0Jd_uploads_git_blob_9864c7f811c613c3faab876659c6423__25[[#This Row],[Estado de la Mesa]]="Ocupada",(15/1440)+spaces_3iWczBNnn5rbfoUlE0Jd_uploads_git_blob_9864c7f811c613c3faab876659c6423__25[[#This Row],[Hora de salida2]]-spaces_3iWczBNnn5rbfoUlE0Jd_uploads_git_blob_9864c7f811c613c3faab876659c6423__25[[#This Row],[Hora de llegada2]],spaces_3iWczBNnn5rbfoUlE0Jd_uploads_git_blob_9864c7f811c613c3faab876659c6423__25[[#This Row],[Estado de la Mesa]]<>"Ocupada",spaces_3iWczBNnn5rbfoUlE0Jd_uploads_git_blob_9864c7f811c613c3faab876659c6423__25[[#This Row],[Hora de salida2]]-spaces_3iWczBNnn5rbfoUlE0Jd_uploads_git_blob_9864c7f811c613c3faab876659c6423__25[[#This Row],[Hora de llegada2]])} -> 0.15625 | S50: =_xlfn.XLOOKUP(spaces_3iWczBNnn5rbfoUlE0Jd_uploads_git_blob_9864c7f811c613c3faab876659c6423__25[[#This Row],[Número de Orden]],Cocinadinamica!E51:E819,Cocinadinamica!F51:F819)/1440 -> 0.05625 | T50: {=_xlfn.IFS((spaces_3iWczBNnn5rbfoUlE0Jd_uploads_git_blob_9864c7f811c613c3faab876659c6423__25[[#This Row],[Tiempo de permanencia]]-spaces_3iWczBNnn5rbfoUlE0Jd_uploads_git_blob_9864c7f811c613c3faab876659c6423__25[[#This Row],[Tiempo de preparación total]])>0,spaces_3iWczBNnn5rbfoUlE0Jd_uploads_git_blob_9864c7f811c613c3faab876659c6423__25[[#This Row],[Tiempo de permanencia]]-spaces_3iWczBNnn5rbfoUlE0Jd_uploads_git_blob_9864c7f811c613c3faab876659c6423__25[[#This Row],[Tiempo de preparación total]],spaces_3iWczBNnn5rbfoUlE0Jd_uploads_git_blob_9864c7f811c613c3faab876659c6423__25[[#This Row],[Tiempo de permanencia]]-spaces_3iWczBNnn5rbfoUlE0Jd_uploads_git_blob_9864c7f811c613c3faab876659c6423__25[[#This Row],[Tiempo de preparación total]]<0,0)} -> 0.1 | U50: {=_xlfn.IFS(spaces_3iWczBNnn5rbfoUlE0Jd_uploads_git_blob_9864c7f811c613c3faab876659c6423__25[[#This Row],[Tiempo degustación]]=0,"NO PAGADA",spaces_3iWczBNnn5rbfoUlE0Jd_uploads_git_blob_9864c7f811c613c3faab876659c6423__25[[#This Row],[Tiempo degustación]]>0, "PAGADA")} -> PAGADA
A51: 19 | B51: Cliente_708 | C51: 5 | D51: 45017.162 | E51: 45017.29 | F51: Mesero_4 | G51: Almuerzo | H51: Tarjeta de débito | I51: 16.74 | J51: Ocupada | K51: 50 | L51: Argentina | M51: Plato_15, Plato_5 | N51: =_xlfn.XLOOKUP(spaces_3iWczBNnn5rbfoUlE0Jd_uploads_git_blob_9864c7f811c613c3faab876659c6423__25[[#This Row],[Número de Orden]],Cocinadinamica!B52:B820,Cocinadinamica!C52:C820) -> 31 | O51: =spaces_3iWczBNnn5rbfoUlE0Jd_uploads_git_blob_9864c7f811c613c3faab876659c6423__25[[#This Row],[Hora de Llegada]] -> 45017.162 | P51: =spaces_3iWczBNnn5rbfoUlE0Jd_uploads_git_blob_9864c7f811c613c3faab876659c6423__25[[#This Row],[Hora de Llegada]] -> 45017.162 | Q51: =spaces_3iWczBNnn5rbfoUlE0Jd_uploads_git_blob_9864c7f811c613c3faab876659c6423__25[[#This Row],[Hora de Salida]] -> 45017.29 | R51: {=_xlfn.IFS(spaces_3iWczBNnn5rbfoUlE0Jd_uploads_git_blob_9864c7f811c613c3faab876659c6423__25[[#This Row],[Estado de la Mesa]]="Ocupada",(15/1440)+spaces_3iWczBNnn5rbfoUlE0Jd_uploads_git_blob_9864c7f811c613c3faab876659c6423__25[[#This Row],[Hora de salida2]]-spaces_3iWczBNnn5rbfoUlE0Jd_uploads_git_blob_9864c7f811c613c3faab876659c6423__25[[#This Row],[Hora de llegada2]],spaces_3iWczBNnn5rbfoUlE0Jd_uploads_git_blob_9864c7f811c613c3faab876659c6423__25[[#This Row],[Estado de la Mesa]]<>"Ocupada",spaces_3iWczBNnn5rbfoUlE0Jd_uploads_git_blob_9864c7f811c613c3faab876659c6423__25[[#This Row],[Hora de salida2]]-spaces_3iWczBNnn5rbfoUlE0Jd_uploads_git_blob_9864c7f811c613c3faab876659c6423__25[[#This Row],[Hora de llegada2]])} -> 0.1375 | S51: =_xlfn.XLOOKUP(spaces_3iWczBNnn5rbfoUlE0Jd_uploads_git_blob_9864c7f811c613c3faab876659c6423__25[[#This Row],[Número de Orden]],Cocinadinamica!E52:E820,Cocinadinamica!F52:F820)/1440 -> 0.014583333 | T51: {=_xlfn.IFS((spaces_3iWczBNnn5rbfoUlE0Jd_uploads_git_blob_9864c7f811c613c3faab876659c6423__25[[#This Row],[Tiempo de permanencia]]-spaces_3iWczBNnn5rbfoUlE0Jd_uploads_git_blob_9864c7f811c613c3faab876659c6423__25[[#This Row],[Tiempo de preparación total]])>0,spaces_3iWczBNnn5rbfoUlE0Jd_uploads_git_blob_9864c7f811c613c3faab876659c6423__25[[#This Row],[Tiempo de permanencia]]-spaces_3iWczBNnn5rbfoUlE0Jd_uploads_git_blob_9864c7f811c613c3faab876659c6423__25[[#This Row],[Tiempo de preparación total]],spaces_3iWczBNnn5rbfoUlE0Jd_uploads_git_blob_9864c7f811c613c3faab876659c6423__25[[#This Row],[Tiempo de permanencia]]-spaces_3iWczBNnn5rbfoUlE0Jd_uploads_git_blob_9864c7f811c613c3faab876659c6423__25[[#This Row],[Tiempo de preparación total]]<0,0)} -> 0.12291667 | U51: {=_xlfn.IFS(spaces_3iWczBNnn5rbfoUlE0Jd_uploads_git_blob_9864c7f811c613c3faab876659c6423__25[[#This Row],[Tiempo degustación]]=0,"NO PAGADA",spaces_3iWczBNnn5rbfoUlE0Jd_uploads_git_blob_9864c7f811c613c3faab876659c6423__25[[#This Row],[Tiempo degustación]]>0, "PAGADA")} -> PAGADA
A52: 12 | B52: Cliente_631 | C52: 1 | D52: 45017.071 | E52: 45017.126 | F52: Mesero_5 | G52: Cena | H52: Tarjeta de crédito | I52: 37.08 | J52: Reservada | K52: 51 | L52: España | M52: Plato_14, Plato_11, Plato_5, Plato_4 | N52: =_xlfn.XLOOKUP(spaces_3iWczBNnn5rbfoUlE0Jd_uploads_git_blob_9864c7f811c613c3faab876659c6423__25[[#This Row],[Número de Orden]],Cocinadinamica!B53:B821,Cocinadinamica!C53:C821) -> 91 | O52: =spaces_3iWczBNnn5rbfoUlE0Jd_uploads_git_blob_9864c7f811c613c3faab876659c6423__25[[#This Row],[Hora de Llegada]] -> 45017.071 | P52: =spaces_3iWczBNnn5rbfoUlE0Jd_uploads_git_blob_9864c7f811c613c3faab876659c6423__25[[#This Row],[Hora de Llegada]] -> 45017.071 | Q52: =spaces_3iWczBNnn5rbfoUlE0Jd_uploads_git_blob_9864c7f811c613c3faab876659c6423__25[[#This Row],[Hora de Salida]] -> 45017.126 | R52: {=_xlfn.IFS(spaces_3iWczBNnn5rbfoUlE0Jd_uploads_git_blob_9864c7f811c613c3faab876659c6423__25[[#This Row],[Estado de la Mesa]]="Ocupada",(15/1440)+spaces_3iWczBNnn5rbfoUlE0Jd_uploads_git_blob_9864c7f811c613c3faab876659c6423__25[[#This Row],[Hora de salida2]]-spaces_3iWczBNnn5rbfoUlE0Jd_uploads_git_blob_9864c7f811c613c3faab876659c6423__25[[#This Row],[Hora de llegada2]],spaces_3iWczBNnn5rbfoUlE0Jd_uploads_git_blob_9864c7f811c613c3faab876659c6423__25[[#This Row],[Estado de la Mesa]]<>"Ocupada",spaces_3iWczBNnn5rbfoUlE0Jd_uploads_git_blob_9864c7f811c613c3faab876659c6423__25[[#This Row],[Hora de salida2]]-spaces_3iWczBNnn5rbfoUlE0Jd_uploads_git_blob_9864c7f811c613c3faab876659c6423__25[[#This Row],[Hora de llegada2]])} -> 0.055555556 | S52: =_xlfn.XLOOKUP(spaces_3iWczBNnn5rbfoUlE0Jd_uploads_git_blob_9864c7f811c613c3faab876659c6423__25[[#This Row],[Número de Orden]],Cocinadinamica!E53:E821,Cocinadinamica!F53:F821)/1440 -> 0.11388889 | T52: {=_xlfn.IFS((spaces_3iWczBNnn5rbfoUlE0Jd_uploads_git_blob_9864c7f811c613c3faab876659c6423__25[[#This Row],[Tiempo de permanencia]]-spaces_3iWczBNnn5rbfoUlE0Jd_uploads_git_blob_9864c7f811c613c3faab876659c6423__25[[#This Row],[Tiempo de preparación total]])>0,spaces_3iWczBNnn5rbfoUlE0Jd_uploads_git_blob_9864c7f811c613c3faab876659c6423__25[[#This Row],[Tiempo de permanencia]]-spaces_3iWczBNnn5rbfoUlE0Jd_uploads_git_blob_9864c7f811c613c3faab876659c6423__25[[#This Row],[Tiempo de preparación total]],spaces_3iWczBNnn5rbfoUlE0Jd_uploads_git_blob_9864c7f811c613c3faab876659c6423__25[[#This Row],[Tiempo de permanencia]]-spaces_3iWczBNnn5rbfoUlE0Jd_uploads_git_blob_9864c7f811c613c3faab876659c6423__25[[#This Row],[Tiempo de preparación total]]<0,0)} -> 0 | U52: {=_xlfn.IFS(spaces_3iWczBNnn5rbfoUlE0Jd_uploads_git_blob_9864c7f811c613c3faab876659c6423__25[[#This Row],[Tiempo degustación]]=0,"NO PAGADA",spaces_3iWczBNnn5rbfoUlE0Jd_uploads_git_blob_9864c7f811c613c3faab876659c6423__25[[#This Row],[Tiempo degustación]]>0, "PAGADA")} -> NO PAGADA
A53: 7 | B53: Cliente_894 | C53: 4 | D53: 45017.001 | E53: 45017.049 | F53: Mesero_3 | G53: Almuerzo | H53: Tarjeta de crédito | I53: 46.88 | J53: Libre | K53: 52 | L53: Paraguay | M53: Plato_11, Plato_17, Plato_18 | N53: =_xlfn.XLOOKUP(spaces_3iWczBNnn5rbfoUlE0Jd_uploads_git_blob_9864c7f811c613c3faab876659c6423__25[[#This Row],[Número de Orden]],Cocinadinamica!B54:B822,Cocinadinamica!C54:C822) -> 105 | O53: =spaces_3iWczBNnn5rbfoUlE0Jd_uploads_git_blob_9864c7f811c613c3faab876659c6423__25[[#This Row],[Hora de Llegada]] -> 45017.001 | P53: =spaces_3iWczBNnn5rbfoUlE0Jd_uploads_git_blob_9864c7f811c613c3faab876659c6423__25[[#This Row],[Hora de Llegada]] -> 45017.001 | Q53: =spaces_3iWczBNnn5rbfoUlE0Jd_uploads_git_blob_9864c7f811c613c3faab876659c6423__25[[#This Row],[Hora de Salida]] -> 45017.049 | R53: {=_xlfn.IFS(spaces_3iWczBNnn5rbfoUlE0Jd_uploads_git_blob_9864c7f811c613c3faab876659c6423__25[[#This Row],[Estado de la Mesa]]="Ocupada",(15/1440)+spaces_3iWczBNnn5rbfoUlE0Jd_uploads_git_blob_9864c7f811c613c3faab876659c6423__25[[#This Row],[Hora de salida2]]-spaces_3iWczBNnn5rbfoUlE0Jd_uploads_git_blob_9864c7f811c613c3faab876659c6423__25[[#This Row],[Hora de llegada2]],spaces_3iWczBNnn5rbfoUlE0Jd_uploads_git_blob_9864c7f811c613c3faab876659c6423__25[[#This Row],[Estado de la Mesa]]<>"Ocupada",spaces_3iWczBNnn5rbfoUlE0Jd_uploads_git_blob_9864c7f811c613c3faab876659c6423__25[[#This Row],[Hora de salida2]]-spaces_3iWczBNnn5rbfoUlE0Jd_uploads_git_blob_9864c7f811c613c3faab876659c6423__25[[#This Row],[Hora de llegada2]])} -> 0.048611111 | S53: =_xlfn.XLOOKUP(spaces_3iWczBNnn5rbfoUlE0Jd_uploads_git_blob_9864c7f811c613c3faab876659c6423__25[[#This Row],[Número de Orden]],Cocinadinamica!E54:E822,Cocinadinamica!F54:F822)/1440 -> 0.043055556 | T53: {=_xlfn.IFS((spaces_3iWczBNnn5rbfoUlE0Jd_uploads_git_blob_9864c7f811c613c3faab876659c6423__25[[#This Row],[Tiempo de permanencia]]-spaces_3iWczBNnn5rbfoUlE0Jd_uploads_git_blob_9864c7f811c613c3faab876659c6423__25[[#This Row],[Tiempo de preparación total]])>0,spaces_3iWczBNnn5rbfoUlE0Jd_uploads_git_blob_9864c7f811c613c3faab876659c6423__25[[#This Row],[Tiempo de permanencia]]-spaces_3iWczBNnn5rbfoUlE0Jd_uploads_git_blob_9864c7f811c613c3faab876659c6423__25[[#This Row],[Tiempo de preparación total]],spaces_3iWczBNnn5rbfoUlE0Jd_uploads_git_blob_9864c7f811c613c3faab876659c6423__25[[#This Row],[Tiempo de permanencia]]-spaces_3iWczBNnn5rbfoUlE0Jd_uploads_git_blob_9864c7f811c613c3faab876659c6423__25[[#This Row],[Tiempo de preparación total]]<0,0)} -> 0.0055555556 | U53: {=_xlfn.IFS(spaces_3iWczBNnn5rbfoUlE0Jd_uploads_git_blob_9864c7f811c613c3faab876659c6423__25[[#This Row],[Tiempo degustación]]=0,"NO PAGADA",spaces_3iWczBNnn5rbfoUlE0Jd_uploads_git_blob_9864c7f811c613c3faab876659c6423__25[[#This Row],[Tiempo degustación]]>0, "PAGADA")} -> PAGADA
A54: 16 | B54: Cliente_63 | C54: 5 | D54: 45017.126 | E54: 45017.197 | F54: Mesero_5 | G54: Almuerzo | H54: Tarjeta de débito | I54: 36.88 | J54: Libre | K54: 53 | L54: Paraguay | M54: Plato_14, Plato_2, Plato_19 | N54: =_xlfn.XLOOKUP(spaces_3iWczBNnn5rbfoUlE0Jd_uploads_git_blob_9864c7f811c613c3faab876659c6423__25[[#This Row],[Número de Orden]],Cocinadinamica!B55:B823,Cocinadinamica!C55:C823) -> 105 | O54: =spaces_3iWczBNnn5rbfoUlE0Jd_uploads_git_blob_9864c7f811c613c3faab876659c6423__25[[#This Row],[Hora de Llegada]] -> 45017.126 | P54: =spaces_3iWczBNnn5rbfoUlE0Jd_uploads_git_blob_9864c7f811c613c3faab876659c6423__25[[#This Row],[Hora de Llegada]] -> 45017.126 | Q54: =spaces_3iWczBNnn5rbfoUlE0Jd_uploads_git_blob_9864c7f811c613c3faab876659c6423__25[[#This Row],[Hora de Salida]] -> 45017.197 | R54: {=_xlfn.IFS(spaces_3iWczBNnn5rbfoUlE0Jd_uploads_git_blob_9864c7f811c613c3faab876659c6423__25[[#This Row],[Estado de la Mesa]]="Ocupada",(15/1440)+spaces_3iWczBNnn5rbfoUlE0Jd_uploads_git_blob_9864c7f811c613c3faab876659c6423__25[[#This Row],[Hora de salida2]]-spaces_3iWczBNnn5rbfoUlE0Jd_uploads_git_blob_9864c7f811c613c3faab876659c6423__25[[#This Row],[Hora de llegada2]],spaces_3iWczBNnn5rbfoUlE0Jd_uploads_git_blob_9864c7f811c613c3faab876659c6423__25[[#This Row],[Estado de la Mesa]]<>"Ocupada",spaces_3iWczBNnn5rbfoUlE0Jd_uploads_git_blob_9864c7f811c613c3faab876659c6423__25[[#This Row],[Hora de salida2]]-spaces_3iWczBNnn5rbfoUlE0Jd_uploads_git_blob_9864c7f811c613c3faab876659c6423__25[[#This Row],[Hora de llegada2]])} -> 0.071527778 | S54: =_xlfn.XLOOKUP(spaces_3iWczBNnn5rbfoUlE0Jd_uploads_git_blob_9864c7f811c613c3faab876659c6423__25[[#This Row],[Número de Orden]],Cocinadinamica!E55:E823,Cocinadinamica!F55:F823)/1440 -> 0.077777778 | T54: {=_xlfn.IFS((spaces_3iWczBNnn5rbfoUlE0Jd_uploads_git_blob_9864c7f811c613c3faab876659c6423__25[[#This Row],[Tiempo de permanencia]]-spaces_3iWczBNnn5rbfoUlE0Jd_uploads_git_blob_9864c7f811c613c3faab876659c6423__25[[#This Row],[Tiempo de preparación total]])>0,spaces_3iWczBNnn5rbfoUlE0Jd_uploads_git_blob_9864c7f811c613c3faab876659c6423__25[[#This Row],[Tiempo de permanencia]]-spaces_3iWczBNnn5rbfoUlE0Jd_uploads_git_blob_9864c7f811c613c3faab876659c6423__25[[#This Row],[Tiempo de preparación total]],spaces_3iWczBNnn5rbfoUlE0Jd_uploads_git_blob_9864c7f811c613c3faab876659c6423__25[[#This Row],[Tiempo de permanencia]]-spaces_3iWczBNnn5rbfoUlE0Jd_uploads_git_blob_9864c7f811c613c3faab876659c6423__25[[#This Row],[Tiempo de preparación total]]<0,0)} -> 0 | U54: {=_xlfn.IFS(spaces_3iWczBNnn5rbfoUlE0Jd_uploads_git_blob_9864c7f811c613c3faab876659c6423__25[[#This Row],[Tiempo degustación]]=0,"NO PAGADA",spaces_3iWczBNnn5rbfoUlE0Jd_uploads_git_blob_9864c7f811c613c3faab876659c6423__25[[#This Row],[Tiempo degustación]]>0, "PAGADA")} -> NO PAGADA
A55: 6 | B55: Cliente_144 | C55: 6 | D55: 45017.028 | E55: 45017.176 | F55: Mesero_4 | G55: Cena | H55: Tarjeta de crédito | I55: 23.36 | J55: Reservada | K55: 54 | L55: Bolivia | M55: Plato_8, Plato_17, Plato_4, Plato_11 | N55: =_xlfn.XLOOKUP(spaces_3iWczBNnn5rbfoUlE0Jd_uploads_git_blob_9864c7f811c613c3faab876659c6423__25[[#This Row],[Número de Orden]],Cocinadinamica!B56:B824,Cocinadinamica!C56:C824) -> 75 | O55: =spaces_3iWczBNnn5rbfoUlE0Jd_uploads_git_blob_9864c7f811c613c3faab876659c6423__25[[#This Row],[Hora de Llegada]] -> 45017.028 | P55: =spaces_3iWczBNnn5rbfoUlE0Jd_uploads_git_blob_9864c7f811c613c3faab876659c6423__25[[#This Row],[Hora de Llegada]] -> 45017.028 | Q55: =spaces_3iWczBNnn5rbfoUlE0Jd_uploads_git_blob_9864c7f811c613c3faab876659c6423__25[[#This Row],[Hora de Salida]] -> 45017.176 | R55: {=_xlfn.IFS(spaces_3iWczBNnn5rbfoUlE0Jd_uploads_git_blob_9864c7f811c613c3faab876659c6423__25[[#This Row],[Estado de la Mesa]]="Ocupada",(15/1440)+spaces_3iWczBNnn5rbfoUlE0Jd_uploads_git_blob_9864c7f811c613c3faab876659c6423__25[[#This Row],[Hora de salida2]]-spaces_3iWczBNnn5rbfoUlE0Jd_uploads_git_blob_9864c7f811c613c3faab876659c6423__25[[#This Row],[Hora de llegada2]],spaces_3iWczBNnn5rbfoUlE0Jd_uploads_git_blob_9864c7f811c613c3faab876659c6423__25[[#This Row],[Estado de la Mesa]]<>"Ocupada",spaces_3iWczBNnn5rbfoUlE0Jd_uploads_git_blob_9864c7f811c613c3faab876659c6423__25[[#This Row],[Hora de salida2]]-spaces_3iWczBNnn5rbfoUlE0Jd_uploads_git_blob_9864c7f811c613c3faab876659c6423__25[[#This Row],[Hora de llegada2]])} -> 0.14861111 | S55: =_xlfn.XLOOKUP(spaces_3iWczBNnn5rbfoUlE0Jd_uploads_git_blob_9864c7f811c613c3faab876659c6423__25[[#This Row],[Número de Orden]],Cocinadinamica!E56:E824,Cocinadinamica!F56:F824)/1440 -> 0.14097222 | T55: {=_xlfn.IFS((spaces_3iWczBNnn5rbfoUlE0Jd_uploads_git_blob_9864c7f811c613c3faab876659c6423__25[[#This Row],[Tiempo de permanencia]]-spaces_3iWczBNnn5rbfoUlE0Jd_uploads_git_blob_9864c7f811c613c3faab876659c6423__25[[#This Row],[Tiempo de preparación total]])>0,spaces_3iWczBNnn5rbfoUlE0Jd_uploads_git_blob_9864c7f811c613c3faab876659c6423__25[[#This Row],[Tiempo de permanencia]]-spaces_3iWczBNnn5rbfoUlE0Jd_uploads_git_blob_9864c7f811c613c3faab876659c6423__25[[#This Row],[Tiempo de preparación total]],spaces_3iWczBNnn5rbfoUlE0Jd_uploads_git_blob_9864c7f811c613c3faab876659c6423__25[[#This Row],[Tiempo de permanencia]]-spaces_3iWczBNnn5rbfoUlE0Jd_uploads_git_blob_9864c7f811c613c3faab876659c6423__25[[#This Row],[Tiempo de preparación total]]<0,0)} -> 0.0076388889 | U55: {=_xlfn.IFS(spaces_3iWczBNnn5rbfoUlE0Jd_uploads_git_blob_9864c7f811c613c3faab876659c6423__25[[#This Row],[Tiempo degustación]]=0,"NO PAGADA",spaces_3iWczBNnn5rbfoUlE0Jd_uploads_git_blob_9864c7f811c613c3faab876659c6423__25[[#This Row],[Tiempo degustación]]>0, "PAGADA")} -> PAGADA
A56: 20 | B56: Cliente_390 | C56: 5 | D56: 45017.062 | E56: 45017.208 | F56: Mesero_4 | G56: Cena | H56: Tarjeta de crédito | I56: 45.49 | J56: Ocupada | K56: 55 | L56: Perú | M56: Plato_11, Plato_7, Plato_19, Plato_15 | N56: =_xlfn.XLOOKUP(spaces_3iWczBNnn5rbfoUlE0Jd_uploads_git_blob_9864c7f811c613c3faab876659c6423__25[[#This Row],[Número de Orden]],Cocinadinamica!B57:B825,Cocinadinamica!C57:C825) -> 102 | O56: =spaces_3iWczBNnn5rbfoUlE0Jd_uploads_git_blob_9864c7f811c613c3faab876659c6423__25[[#This Row],[Hora de Llegada]] -> 45017.062 | P56: =spaces_3iWczBNnn5rbfoUlE0Jd_uploads_git_blob_9864c7f811c613c3faab876659c6423__25[[#This Row],[Hora de Llegada]] -> 45017.062 | Q56: =spaces_3iWczBNnn5rbfoUlE0Jd_uploads_git_blob_9864c7f811c613c3faab876659c6423__25[[#This Row],[Hora de Salida]] -> 45017.208 | R56: {=_xlfn.IFS(spaces_3iWczBNnn5rbfoUlE0Jd_uploads_git_blob_9864c7f811c613c3faab876659c6423__25[[#This Row],[Estado de la Mesa]]="Ocupada",(15/1440)+spaces_3iWczBNnn5rbfoUlE0Jd_uploads_git_blob_9864c7f811c613c3faab876659c6423__25[[#This Row],[Hora de salida2]]-spaces_3iWczBNnn5rbfoUlE0Jd_uploads_git_blob_9864c7f811c613c3faab876659c6423__25[[#This Row],[Hora de llegada2]],spaces_3iWczBNnn5rbfoUlE0Jd_uploads_git_blob_9864c7f811c613c3faab876659c6423__25[[#This Row],[Estado de la Mesa]]<>"Ocupada",spaces_3iWczBNnn5rbfoUlE0Jd_uploads_git_blob_9864c7f811c613c3faab876659c6423__25[[#This Row],[Hora de salida2]]-spaces_3iWczBNnn5rbfoUlE0Jd_uploads_git_blob_9864c7f811c613c3faab876659c6423__25[[#This Row],[Hora de llegada2]])} -> 0.15625 | S56: =_xlfn.XLOOKUP(spaces_3iWczBNnn5rbfoUlE0Jd_uploads_git_blob_9864c7f811c613c3faab876659c6423__25[[#This Row],[Número de Orden]],Cocinadinamica!E57:E825,Cocinadinamica!F57:F825)/1440 -> 0.066666667 | T56: {=_xlfn.IFS((spaces_3iWczBNnn5rbfoUlE0Jd_uploads_git_blob_9864c7f811c613c3faab876659c6423__25[[#This Row],[Tiempo de permanencia]]-spaces_3iWczBNnn5rbfoUlE0Jd_uploads_git_blob_9864c7f811c613c3faab876659c6423__25[[#This Row],[Tiempo de preparación total]])>0,spaces_3iWczBNnn5rbfoUlE0Jd_uploads_git_blob_9864c7f811c613c3faab876659c6423__25[[#This Row],[Tiempo de permanencia]]-spaces_3iWczBNnn5rbfoUlE0Jd_uploads_git_blob_9864c7f811c613c3faab876659c6423__25[[#This Row],[Tiempo de preparación total]],spaces_3iWczBNnn5rbfoUlE0Jd_uploads_git_blob_9864c7f811c613c3faab876659c6423__25[[#This Row],[Tiempo de permanencia]]-spaces_3iWczBNnn5rbfoUlE0Jd_uploads_git_blob_9864c7f811c613c3faab876659c6423__25[[#This Row],[Tiempo de preparación total]]<0,0)} -> 0.089583333 | U56: {=_xlfn.IFS(spaces_3iWczBNnn5rbfoUlE0Jd_uploads_git_blob_9864c7f811c613c3faab876659c6423__25[[#This Row],[Tiempo degustación]]=0,"NO PAGADA",spaces_3iWczBNnn5rbfoUlE0Jd_uploads_git_blob_9864c7f811c613c3faab876659c6423__25[[#This Row],[Tiempo degustación]]>0, "PAGADA")} -> PAGADA
A57: 1 | B57: Cliente_728 | C57: 3 | D57: 45017.056 | E57: 45017.206 | F57: Mesero_5 | G57: Almuerzo | H57: Tarjeta de débito | I57: 43.2 | J57: Libre | K57: 56 | L57: Ecuador | M57: Plato_9, Plato_12 | N57: =_xlfn.XLOOKUP(spaces_3iWczBNnn5rbfoUlE0Jd_uploads_git_blob_9864c7f811c613c3faab876659c6423__25[[#This Row],[Número de Orden]],Cocinadinamica!B58:B826,Cocinadinamica!C58:C826) -> 20 | O57: =spaces_3iWczBNnn5rbfoUlE0Jd_uploads_git_blob_9864c7f811c613c3faab876659c6423__25[[#This Row],[Hora de Llegada]] -> 45017.056 | P57: =spaces_3iWczBNnn5rbfoUlE0Jd_uploads_git_blob_9864c7f811c613c3faab876659c6423__25[[#This Row],[Hora de Llegada]] -> 45017.056 | Q57: =spaces_3iWczBNnn5rbfoUlE0Jd_uploads_git_blob_9864c7f811c613c3faab876659c6423__25[[#This Row],[Hora de Salida]] -> 45017.206 | R57: {=_xlfn.IFS(spaces_3iWczBNnn5rbfoUlE0Jd_uploads_git_blob_9864c7f811c613c3faab876659c6423__25[[#This Row],[Estado de la Mesa]]="Ocupada",(15/1440)+spaces_3iWczBNnn5rbfoUlE0Jd_uploads_git_blob_9864c7f811c613c3faab876659c6423__25[[#This Row],[Hora de salida2]]-spaces_3iWczBNnn5rbfoUlE0Jd_uploads_git_blob_9864c7f811c613c3faab876659c6423__25[[#This Row],[Hora de llegada2]],spaces_3iWczBNnn5rbfoUlE0Jd_uploads_git_blob_9864c7f811c613c3faab876659c6423__25[[#This Row],[Estado de la Mesa]]<>"Ocupada",spaces_3iWczBNnn5rbfoUlE0Jd_uploads_git_blob_9864c7f811c613c3faab876659c6423__25[[#This Row],[Hora de salida2]]-spaces_3iWczBNnn5rbfoUlE0Jd_uploads_git_blob_9864c7f811c613c3faab876659c6423__25[[#This Row],[Hora de llegada2]])} -> 0.15069444 | S57: =_xlfn.XLOOKUP(spaces_3iWczBNnn5rbfoUlE0Jd_uploads_git_blob_9864c7f811c613c3faab876659c6423__25[[#This Row],[Número de Orden]],Cocinadinamica!E58:E826,Cocinadinamica!F58:F826)/1440 -> 0.054166667 | T57: {=_xlfn.IFS((spaces_3iWczBNnn5rbfoUlE0Jd_uploads_git_blob_9864c7f811c613c3faab876659c6423__25[[#This Row],[Tiempo de permanencia]]-spaces_3iWczBNnn5rbfoUlE0Jd_uploads_git_blob_9864c7f811c613c3faab876659c6423__25[[#This Row],[Tiempo de preparación total]])>0,spaces_3iWczBNnn5rbfoUlE0Jd_uploads_git_blob_9864c7f811c613c3faab876659c6423__25[[#This Row],[Tiempo de permanencia]]-spaces_3iWczBNnn5rbfoUlE0Jd_uploads_git_blob_9864c7f811c613c3faab876659c6423__25[[#This Row],[Tiempo de preparación total]],spaces_3iWczBNnn5rbfoUlE0Jd_uploads_git_blob_9864c7f811c613c3faab876659c6423__25[[#This Row],[Tiempo de permanencia]]-spaces_3iWczBNnn5rbfoUlE0Jd_uploads_git_blob_9864c7f811c613c3faab876659c6423__25[[#This Row],[Tiempo de preparación total]]<0,0)} -> 0.096527778 | U57: {=_xlfn.IFS(spaces_3iWczBNnn5rbfoUlE0Jd_uploads_git_blob_9864c7f811c613c3faab876659c6423__25[[#This Row],[Tiempo degustación]]=0,"NO PAGADA",spaces_3iWczBNnn5rbfoUlE0Jd_uploads_git_blob_9864c7f811c613c3faab876659c6423__25[[#This Row],[Tiempo degustación]]>0, "PAGADA")} -> PAGADA
A58: 18 | B58: Cliente_886 | C58: 2 | D58: 45017.128 | E58: 45017.203 | F58: Mesero_2 | G58: Almuerzo | H58: Tarjeta de crédito | I58: 45.45 | J58: Libre | K58: 57 | L58: Colombia | M58: Plato_8, Plato_20, Plato_5, Plato_19 | N58: =_xlfn.XLOOKUP(spaces_3iWczBNnn5rbfoUlE0Jd_uploads_git_blob_9864c7f811c613c3faab876659c6423__25[[#This Row],[Número de Orden]],Cocinadinamica!B59:B827,Cocinadinamica!C59:C827) -> 66 | O58: =spaces_3iWczBNnn5rbfoUlE0Jd_uploads_git_blob_9864c7f811c613c3faab876659c6423__25[[#This Row],[Hora de Llegada]] -> 45017.128 | P58: =spaces_3iWczBNnn5rbfoUlE0Jd_uploads_git_blob_9864c7f811c613c3faab876659c6423__25[[#This Row],[Hora de Llegada]] -> 45017.128 | Q58: =spaces_3iWczBNnn5rbfoUlE0Jd_uploads_git_blob_9864c7f811c613c3faab876659c6423__25[[#This Row],[Hora de Salida]] -> 45017.203 | R58: {=_xlfn.IFS(spaces_3iWczBNnn5rbfoUlE0Jd_uploads_git_blob_9864c7f811c613c3faab876659c6423__25[[#This Row],[Estado de la Mesa]]="Ocupada",(15/1440)+spaces_3iWczBNnn5rbfoUlE0Jd_uploads_git_blob_9864c7f811c613c3faab876659c6423__25[[#This Row],[Hora de salida2]]-spaces_3iWczBNnn5rbfoUlE0Jd_uploads_git_blob_9864c7f811c613c3faab876659c6423__25[[#This Row],[Hora de llegada2]],spaces_3iWczBNnn5rbfoUlE0Jd_uploads_git_blob_9864c7f811c613c3faab876659c6423__25[[#This Row],[Estado de la Mesa]]<>"Ocupada",spaces_3iWczBNnn5rbfoUlE0Jd_uploads_git_blob_9864c7f811c613c3faab876659c6423__25[[#This Row],[Hora de salida2]]-spaces_3iWczBNnn5rbfoUlE0Jd_uploads_git_blob_9864c7f811c613c3faab876659c6423__25[[#This Row],[Hora de llegada2]])} -> 0.075 | S58: =_xlfn.XLOOKUP(spaces_3iWczBNnn5rbfoUlE0Jd_uploads_git_blob_9864c7f811c613c3faab876659c6423__25[[#This Row],[Número de Orden]],Cocinadinamica!E59:E827,Cocinadinamica!F59:F827)/1440 -> 0.047222222 | T58: {=_xlfn.IFS((spaces_3iWczBNnn5rbfoUlE0Jd_uploads_git_blob_9864c7f811c613c3faab876659c6423__25[[#This Row],[Tiempo de permanencia]]-spaces_3iWczBNnn5rbfoUlE0Jd_uploads_git_blob_9864c7f811c613c3faab876659c6423__25[[#This Row],[Tiempo de preparación total]])>0,spaces_3iWczBNnn5rbfoUlE0Jd_uploads_git_blob_9864c7f811c613c3faab876659c6423__25[[#This Row],[Tiempo de permanencia]]-spaces_3iWczBNnn5rbfoUlE0Jd_uploads_git_blob_9864c7f811c613c3faab876659c6423__25[[#This Row],[Tiempo de preparación total]],spaces_3iWczBNnn5rbfoUlE0Jd_uploads_git_blob_9864c7f811c613c3faab876659c6423__25[[#This Row],[Tiempo de permanencia]]-spaces_3iWczBNnn5rbfoUlE0Jd_uploads_git_blob_9864c7f811c613c3faab876659c6423__25[[#This Row],[Tiempo de preparación total]]<0,0)} -> 0.027777778 | U58: {=_xlfn.IFS(spaces_3iWczBNnn5rbfoUlE0Jd_uploads_git_blob_9864c7f811c613c3faab876659c6423__25[[#This Row],[Tiempo degustación]]=0,"NO PAGADA",spaces_3iWczBNnn5rbfoUlE0Jd_uploads_git_blob_9864c7f811c613c3faab876659c6423__25[[#This Row],[Tiempo degustación]]>0, "PAGADA")} -> PAGADA
... A73: 17 | B73: Cliente_258 | C73: 1 | D73: 45017.113 | E73: 45017.244 | F73: Mesero_2 | G73: Almuerzo | H73: Tarjeta de crédito | I73: 15.28 | J73: Reservada | K73: 72 | L73: Perú | M73: Plato_13, Plato_4 | N73: =_xlfn.XLOOKUP(spaces_3iWczBNnn5rbfoUlE0Jd_uploads_git_blob_9864c7f811c613c3faab876659c6423__25[[#This Row],[Número de Orden]],Cocinadinamica!B74:B842,Cocinadinamica!C74:C842) -> 32 | O73: =spaces_3iWczBNnn5rbfoUlE0Jd_uploads_git_blob_9864c7f811c613c3faab876659c6423__25[[#This Row],[Hora de Llegada]] -> 45017.113 | P73: =spaces_3iWczBNnn5rbfoUlE0Jd_uploads_git_blob_9864c7f811c613c3faab876659c6423__25[[#This Row],[Hora de Llegada]] -> 45017.113 | Q73: =spaces_3iWczBNnn5rbfoUlE0Jd_uploads_git_blob_9864c7f811c613c3faab876659c6423__25[[#This Row],[Hora de Salida]] -> 45017.244 | R73: {=_xlfn.IFS(spaces_3iWczBNnn5rbfoUlE0Jd_uploads_git_blob_9864c7f811c613c3faab876659c6423__25[[#This Row],[Estado de la Mesa]]="Ocupada",(15/1440)+spaces_3iWczBNnn5rbfoUlE0Jd_uploads_git_blob_9864c7f811c613c3faab876659c6423__25[[#This Row],[Hora de salida2]]-spaces_3iWczBNnn5rbfoUlE0Jd_uploads_git_blob_9864c7f811c613c3faab876659c6423__25[[#This Row],[Hora de llegada2]],spaces_3iWczBNnn5rbfoUlE0Jd_uploads_git_blob_9864c7f811c613c3faab876659c6423__25[[#This Row],[Estado de la Mesa]]<>"Ocupada",spaces_3iWczBNnn5rbfoUlE0Jd_uploads_git_blob_9864c7f811c613c3faab876659c6423__25[[#This Row],[Hora de salida2]]-spaces_3iWczBNnn5rbfoUlE0Jd_uploads_git_blob_9864c7f811c613c3faab876659c6423__25[[#This Row],[Hora de llegada2]])} -> 0.13125 | S73: =_xlfn.XLOOKUP(spaces_3iWczBNnn5rbfoUlE0Jd_uploads_git_blob_9864c7f811c613c3faab876659c6423__25[[#This Row],[Número de Orden]],Cocinadinamica!E74:E842,Cocinadinamica!F74:F842)/1440 -> 0.0375 | T73: {=_xlfn.IFS((spaces_3iWczBNnn5rbfoUlE0Jd_uploads_git_blob_9864c7f811c613c3faab876659c6423__25[[#This Row],[Tiempo de permanencia]]-spaces_3iWczBNnn5rbfoUlE0Jd_uploads_git_blob_9864c7f811c613c3faab876659c6423__25[[#This Row],[Tiempo de preparación total]])>0,spaces_3iWczBNnn5rbfoUlE0Jd_uploads_git_blob_9864c7f811c613c3faab876659c6423__25[[#This Row],[Tiempo de permanencia]]-spaces_3iWczBNnn5rbfoUlE0Jd_uploads_git_blob_9864c7f811c613c3faab876659c6423__25[[#This Row],[Tiempo de preparación total]],spaces_3iWczBNnn5rbfoUlE0Jd_uploads_git_blob_9864c7f811c613c3faab876659c6423__25[[#This Row],[Tiempo de permanencia]]-spaces_3iWczBNnn5rbfoUlE0Jd_uploads_git_blob_9864c7f811c613c3faab876659c6423__25[[#This Row],[Tiempo de preparación total]]<0,0)} -> 0.09375 | U73: {=_xlfn.IFS(spaces_3iWczBNnn5rbfoUlE0Jd_uploads_git_blob_9864c7f811c613c3faab876659c6423__25[[#This Row],[Tiempo degustación]]=0,"NO PAGADA",spaces_3iWczBNnn5rbfoUlE0Jd_uploads_git_blob_9864c7f811c613c3faab876659c6423__25[[#This Row],[Tiempo degustación]]>0, "PAGADA")} -> PAGADA
A74: 1 | B74: Cliente_742 | C74: 4 | D74: 45017.11 | E74: 45017.256 | F74: Mesero_4 | G74: Desayuno | H74: Tarjeta de crédito | I74: 34.51 | J74: Libre | K74: 73 | L74: Argentina | M74: Plato_6 | N74: =_xlfn.XLOOKUP(spaces_3iWczBNnn5rbfoUlE0Jd_uploads_git_blob_9864c7f811c613c3faab876659c6423__25[[#This Row],[Número de Orden]],Cocinadinamica!B75:B843,Cocinadinamica!C75:C843) -> 33 | O74: =spaces_3iWczBNnn5rbfoUlE0Jd_uploads_git_blob_9864c7f811c613c3faab876659c6423__25[[#This Row],[Hora de Llegada]] -> 45017.11 | P74: =spaces_3iWczBNnn5rbfoUlE0Jd_uploads_git_blob_9864c7f811c613c3faab876659c6423__25[[#This Row],[Hora de Llegada]] -> 45017.11 | Q74: =spaces_3iWczBNnn5rbfoUlE0Jd_uploads_git_blob_9864c7f811c613c3faab876659c6423__25[[#This Row],[Hora de Salida]] -> 45017.256 | R74: {=_xlfn.IFS(spaces_3iWczBNnn5rbfoUlE0Jd_uploads_git_blob_9864c7f811c613c3faab876659c6423__25[[#This Row],[Estado de la Mesa]]="Ocupada",(15/1440)+spaces_3iWczBNnn5rbfoUlE0Jd_uploads_git_blob_9864c7f811c613c3faab876659c6423__25[[#This Row],[Hora de salida2]]-spaces_3iWczBNnn5rbfoUlE0Jd_uploads_git_blob_9864c7f811c613c3faab876659c6423__25[[#This Row],[Hora de llegada2]],spaces_3iWczBNnn5rbfoUlE0Jd_uploads_git_blob_9864c7f811c613c3faab876659c6423__25[[#This Row],[Estado de la Mesa]]<>"Ocupada",spaces_3iWczBNnn5rbfoUlE0Jd_uploads_git_blob_9864c7f811c613c3faab876659c6423__25[[#This Row],[Hora de salida2]]-spaces_3iWczBNnn5rbfoUlE0Jd_uploads_git_blob_9864c7f811c613c3faab876659c6423__25[[#This Row],[Hora de llegada2]])} -> 0.14583333 | S74: =_xlfn.XLOOKUP(spaces_3iWczBNnn5rbfoUlE0Jd_uploads_git_blob_9864c7f811c613c3faab876659c6423__25[[#This Row],[Número de Orden]],Cocinadinamica!E75:E843,Cocinadinamica!F75:F843)/1440 -> 0.013888889 | T74: {=_xlfn.IFS((spaces_3iWczBNnn5rbfoUlE0Jd_uploads_git_blob_9864c7f811c613c3faab876659c6423__25[[#This Row],[Tiempo de permanencia]]-spaces_3iWczBNnn5rbfoUlE0Jd_uploads_git_blob_9864c7f811c613c3faab876659c6423__25[[#This Row],[Tiempo de preparación total]])>0,spaces_3iWczBNnn5rbfoUlE0Jd_uploads_git_blob_9864c7f811c613c3faab876659c6423__25[[#This Row],[Tiempo de permanencia]]-spaces_3iWczBNnn5rbfoUlE0Jd_uploads_git_blob_9864c7f811c613c3faab876659c6423__25[[#This Row],[Tiempo de preparación total]],spaces_3iWczBNnn5rbfoUlE0Jd_uploads_git_blob_9864c7f811c613c3faab876659c6423__25[[#This Row],[Tiempo de permanencia]]-spaces_3iWczBNnn5rbfoUlE0Jd_uploads_git_blob_9864c7f811c613c3faab876659c6423__25[[#This Row],[Tiempo de preparación total]]<0,0)} -> 0.13194444 | U74: {=_xlfn.IFS(spaces_3iWczBNnn5rbfoUlE0Jd_uploads_git_blob_9864c7f811c613c3faab876659c6423__25[[#This Row],[Tiempo degustación]]=0,"NO PAGADA",spaces_3iWczBNnn5rbfoUlE0Jd_uploads_git_blob_9864c7f811c613c3faab876659c6423__25[[#This Row],[Tiempo degustación]]>0, "PAGADA")} -> PAGADA
A75: 19 | B75: Cliente_865 | C75: 4 | D75: 45017.044 | E75: 45017.176 | F75: Mesero_4 | G75: Almuerzo | H75: Tarjeta de crédito | I75: 30.83 | J75: Libre | K75: 74 | L75: Brasil | M75: Plato_10, Plato_18, Plato_15 | N75: =_xlfn.XLOOKUP(spaces_3iWczBNnn5rbfoUlE0Jd_uploads_git_blob_9864c7f811c613c3faab876659c6423__25[[#This Row],[Número de Orden]],Cocinadinamica!B76:B844,Cocinadinamica!C76:C844) -> 90 | O75: =spaces_3iWczBNnn5rbfoUlE0Jd_uploads_git_blob_9864c7f811c613c3faab876659c6423__25[[#This Row],[Hora de Llegada]] -> 45017.044 | P75: =spaces_3iWczBNnn5rbfoUlE0Jd_uploads_git_blob_9864c7f811c613c3faab876659c6423__25[[#This Row],[Hora de Llegada]] -> 45017.044 | Q75: =spaces_3iWczBNnn5rbfoUlE0Jd_uploads_git_blob_9864c7f811c613c3faab876659c6423__25[[#This Row],[Hora de Salida]] -> 45017.176 | R75: {=_xlfn.IFS(spaces_3iWczBNnn5rbfoUlE0Jd_uploads_git_blob_9864c7f811c613c3faab876659c6423__25[[#This Row],[Estado de la Mesa]]="Ocupada",(15/1440)+spaces_3iWczBNnn5rbfoUlE0Jd_uploads_git_blob_9864c7f811c613c3faab876659c6423__25[[#This Row],[Hora de salida2]]-spaces_3iWczBNnn5rbfoUlE0Jd_uploads_git_blob_9864c7f811c613c3faab876659c6423__25[[#This Row],[Hora de llegada2]],spaces_3iWczBNnn5rbfoUlE0Jd_uploads_git_blob_9864c7f811c613c3faab876659c6423__25[[#This Row],[Estado de la Mesa]]<>"Ocupada",spaces_3iWczBNnn5rbfoUlE0Jd_uploads_git_blob_9864c7f811c613c3faab876659c6423__25[[#This Row],[Hora de salida2]]-spaces_3iWczBNnn5rbfoUlE0Jd_uploads_git_blob_9864c7f811c613c3faab876659c6423__25[[#This Row],[Hora de llegada2]])} -> 0.13125 | S75: =_xlfn.XLOOKUP(spaces_3iWczBNnn5rbfoUlE0Jd_uploads_git_blob_9864c7f811c613c3faab876659c6423__25[[#This Row],[Número de Orden]],Cocinadinamica!E76:E844,Cocinadinamica!F76:F844)/1440 -> 0.069444444 | T75: {=_xlfn.IFS((spaces_3iWczBNnn5rbfoUlE0Jd_uploads_git_blob_9864c7f811c613c3faab876659c6423__25[[#This Row],[Tiempo de permanencia]]-spaces_3iWczBNnn5rbfoUlE0Jd_uploads_git_blob_9864c7f811c613c3faab876659c6423__25[[#This Row],[Tiempo de preparación total]])>0,spaces_3iWczBNnn5rbfoUlE0Jd_uploads_git_blob_9864c7f811c613c3faab876659c6423__25[[#This Row],[Tiempo de permanencia]]-spaces_3iWczBNnn5rbfoUlE0Jd_uploads_git_blob_9864c7f811c613c3faab876659c6423__25[[#This Row],[Tiempo de preparación total]],spaces_3iWczBNnn5rbfoUlE0Jd_uploads_git_blob_9864c7f811c613c3faab876659c6423__25[[#This Row],[Tiempo de permanencia]]-spaces_3iWczBNnn5rbfoUlE0Jd_uploads_git_blob_9864c7f811c613c3faab876659c6423__25[[#This Row],[Tiempo de preparación total]]<0,0)} -> 0.061805556 | U75: {=_xlfn.IFS(spaces_3iWczBNnn5rbfoUlE0Jd_uploads_git_blob_9864c7f811c613c3faab876659c6423__25[[#This Row],[Tiempo degustación]]=0,"NO PAGADA",spaces_3iWczBNnn5rbfoUlE0Jd_uploads_git_blob_9864c7f811c613c3faab876659c6423__25[[#This Row],[Tiempo degustación]]>0, "PAGADA")} -> PAGADA
A76: 19 | B76: Cliente_79 | C76: 5 | D76: 45017.15 | E76: 45017.201 | F76: Mesero_5 | G76: Almuerzo | H76: Tarjeta de crédito | I76: 45.23 | J76: Ocupada | K76: 75 | L76: Venezuela | M76: Plato_20, Plato_14 | N76: =_xlfn.XLOOKUP(spaces_3iWczBNnn5rbfoUlE0Jd_uploads_git_blob_9864c7f811c613c3faab876659c6423__25[[#This Row],[Número de Orden]],Cocinadinamica!B77:B845,Cocinadinamica!C77:C845) -> 42 | O76: =spaces_3iWczBNnn5rbfoUlE0Jd_uploads_git_blob_9864c7f811c613c3faab876659c6423__25[[#This Row],[Hora de Llegada]] -> 45017.15 | P76: =spaces_3iWczBNnn5rbfoUlE0Jd_uploads_git_blob_9864c7f811c613c3faab876659c6423__25[[#This Row],[Hora de Llegada]] -> 45017.15 | Q76: =spaces_3iWczBNnn5rbfoUlE0Jd_uploads_git_blob_9864c7f811c613c3faab876659c6423__25[[#This Row],[Hora de Salida]] -> 45017.201 | R76: {=_xlfn.IFS(spaces_3iWczBNnn5rbfoUlE0Jd_uploads_git_blob_9864c7f811c613c3faab876659c6423__25[[#This Row],[Estado de la Mesa]]="Ocupada",(15/1440)+spaces_3iWczBNnn5rbfoUlE0Jd_uploads_git_blob_9864c7f811c613c3faab876659c6423__25[[#This Row],[Hora de salida2]]-spaces_3iWczBNnn5rbfoUlE0Jd_uploads_git_blob_9864c7f811c613c3faab876659c6423__25[[#This Row],[Hora de llegada2]],spaces_3iWczBNnn5rbfoUlE0Jd_uploads_git_blob_9864c7f811c613c3faab876659c6423__25[[#This Row],[Estado de la Mesa]]<>"Ocupada",spaces_3iWczBNnn5rbfoUlE0Jd_uploads_git_blob_9864c7f811c613c3faab876659c6423__25[[#This Row],[Hora de salida2]]-spaces_3iWczBNnn5rbfoUlE0Jd_uploads_git_blob_9864c7f811c613c3faab876659c6423__25[[#This Row],[Hora de llegada2]])} -> 0.061111111 | S76: =_xlfn.XLOOKUP(spaces_3iWczBNnn5rbfoUlE0Jd_uploads_git_blob_9864c7f811c613c3faab876659c6423__25[[#This Row],[Número de Orden]],Cocinadinamica!E77:E845,Cocinadinamica!F77:F845)/1440 -> 0.035416667 | T76: {=_xlfn.IFS((spaces_3iWczBNnn5rbfoUlE0Jd_uploads_git_blob_9864c7f811c613c3faab876659c6423__25[[#This Row],[Tiempo de permanencia]]-spaces_3iWczBNnn5rbfoUlE0Jd_uploads_git_blob_9864c7f811c613c3faab876659c6423__25[[#This Row],[Tiempo de preparación total]])>0,spaces_3iWczBNnn5rbfoUlE0Jd_uploads_git_blob_9864c7f811c613c3faab876659c6423__25[[#This Row],[Tiempo de permanencia]]-spaces_3iWczBNnn5rbfoUlE0Jd_uploads_git_blob_9864c7f811c613c3faab876659c6423__25[[#This Row],[Tiempo de preparación total]],spaces_3iWczBNnn5rbfoUlE0Jd_uploads_git_blob_9864c7f811c613c3faab876659c6423__25[[#This Row],[Tiempo de permanencia]]-spaces_3iWczBNnn5rbfoUlE0Jd_uploads_git_blob_9864c7f811c613c3faab876659c6423__25[[#This Row],[Tiempo de preparación total]]<0,0)} -> 0.025694444 | U76: {=_xlfn.IFS(spaces_3iWczBNnn5rbfoUlE0Jd_uploads_git_blob_9864c7f811c613c3faab876659c6423__25[[#This Row],[Tiempo degustación]]=0,"NO PAGADA",spaces_3iWczBNnn5rbfoUlE0Jd_uploads_git_blob_9864c7f811c613c3faab876659c6423__25[[#This Row],[Tiempo degustación]]>0, "PAGADA")} -> PAGADA
A77: 17 | B77: Cliente_42 | C77: 3 | D77: 45017.123 | E77: 45017.225 | F77: Mesero_1 | G77: Almuerzo | H77: Tarjeta de crédito | I77: 17.76 | J77: Reservada | K77: 76 | L77: Argentina | M77: Plato_2, Plato_4, Plato_7, Plato_10 | N77: =_xlfn.XLOOKUP(spaces_3iWczBNnn5rbfoUlE0Jd_uploads_git_blob_9864c7f811c613c3faab876659c6423__25[[#This Row],[Número de Orden]],Cocinadinamica!B78:B846,Cocinadinamica!C78:C846) -> 65 | O77: =spaces_3iWczBNnn5rbfoUlE0Jd_uploads_git_blob_9864c7f811c613c3faab876659c6423__25[[#This Row],[Hora de Llegada]] -> 45017.123 | P77: =spaces_3iWczBNnn5rbfoUlE0Jd_uploads_git_blob_9864c7f811c613c3faab876659c6423__25[[#This Row],[Hora de Llegada]] -> 45017.123 | Q77: =spaces_3iWczBNnn5rbfoUlE0Jd_uploads_git_blob_9864c7f811c613c3faab876659c6423__25[[#This Row],[Hora de Salida]] -> 45017.225 | R77: {=_xlfn.IFS(spaces_3iWczBNnn5rbfoUlE0Jd_uploads_git_blob_9864c7f811c613c3faab876659c6423__25[[#This Row],[Estado de la Mesa]]="Ocupada",(15/1440)+spaces_3iWczBNnn5rbfoUlE0Jd_uploads_git_blob_9864c7f811c613c3faab876659c6423__25[[#This Row],[Hora de salida2]]-spaces_3iWczBNnn5rbfoUlE0Jd_uploads_git_blob_9864c7f811c613c3faab876659c6423__25[[#This Row],[Hora de llegada2]],spaces_3iWczBNnn5rbfoUlE0Jd_uploads_git_blob_9864c7f811c613c3faab876659c6423__25[[#This Row],[Estado de la Mesa]]<>"Ocupada",spaces_3iWczBNnn5rbfoUlE0Jd_uploads_git_blob_9864c7f811c613c3faab876659c6423__25[[#This Row],[Hora de salida2]]-spaces_3iWczBNnn5rbfoUlE0Jd_uploads_git_blob_9864c7f811c613c3faab876659c6423__25[[#This Row],[Hora de llegada2]])} -> 0.10208333 | S77: =_xlfn.XLOOKUP(spaces_3iWczBNnn5rbfoUlE0Jd_uploads_git_blob_9864c7f811c613c3faab876659c6423__25[[#This Row],[Número de Orden]],Cocinadinamica!E78:E846,Cocinadinamica!F78:F846)/1440 -> 0.067361111 | T77: {=_xlfn.IFS((spaces_3iWczBNnn5rbfoUlE0Jd_uploads_git_blob_9864c7f811c613c3faab876659c6423__25[[#This Row],[Tiempo de permanencia]]-spaces_3iWczBNnn5rbfoUlE0Jd_uploads_git_blob_9864c7f811c613c3faab876659c6423__25[[#This Row],[Tiempo de preparación total]])>0,spaces_3iWczBNnn5rbfoUlE0Jd_uploads_git_blob_9864c7f811c613c3faab876659c6423__25[[#This Row],[Tiempo de permanencia]]-spaces_3iWczBNnn5rbfoUlE0Jd_uploads_git_blob_9864c7f811c613c3faab876659c6423__25[[#This Row],[Tiempo de preparación total]],spaces_3iWczBNnn5rbfoUlE0Jd_uploads_git_blob_9864c7f811c613c3faab876659c6423__25[[#This Row],[Tiempo de permanencia]]-spaces_3iWczBNnn5rbfoUlE0Jd_uploads_git_blob_9864c7f811c613c3faab876659c6423__25[[#This Row],[Tiempo de preparación total]]<0,0)} -> 0.034722222 | U77: {=_xlfn.IFS(spaces_3iWczBNnn5rbfoUlE0Jd_uploads_git_blob_9864c7f811c613c3faab876659c6423__25[[#This Row],[Tiempo degustación]]=0,"NO PAGADA",spaces_3iWczBNnn5rbfoUlE0Jd_uploads_git_blob_9864c7f811c613c3faab876659c6423__25[[#This Row],[Tiempo degustación]]>0, "PAGADA")} -> PAGADA
A78: 3 | B78: Cliente_374 | C78: 1 | D78: 45017.115 | E78: 45017.26 | F78: Mesero_3 | G78: Cena | H78: Tarjeta de crédito | I78: 19.88 | J78: Libre | K78: 77 | L78: Bolivia | M78: Plato_4, Plato_7, Plato_11 | N78: =_xlfn.XLOOKUP(spaces_3iWczBNnn5rbfoUlE0Jd_uploads_git_blob_9864c7f811c613c3faab876659c6423__25[[#This Row],[Número de Orden]],Cocinadinamica!B79:B847,Cocinadinamica!C79:C847) -> 41 | O78: =spaces_3iWczBNnn5rbfoUlE0Jd_uploads_git_blob_9864c7f811c613c3faab876659c6423__25[[#This Row],[Hora de Llegada]] -> 45017.115 | P78: =spaces_3iWczBNnn5rbfoUlE0Jd_uploads_git_blob_9864c7f811c613c3faab876659c6423__25[[#This Row],[Hora de Llegada]] -> 45017.115 | Q78: =spaces_3iWczBNnn5rbfoUlE0Jd_uploads_git_blob_9864c7f811c613c3faab876659c6423__25[[#This Row],[Hora de Salida]] -> 45017.26 | R78: {=_xlfn.IFS(spaces_3iWczBNnn5rbfoUlE0Jd_uploads_git_blob_9864c7f811c613c3faab876659c6423__25[[#This Row],[Estado de la Mesa]]="Ocupada",(15/1440)+spaces_3iWczBNnn5rbfoUlE0Jd_uploads_git_blob_9864c7f811c613c3faab876659c6423__25[[#This Row],[Hora de salida2]]-spaces_3iWczBNnn5rbfoUlE0Jd_uploads_git_blob_9864c7f811c613c3faab876659c6423__25[[#This Row],[Hora de llegada2]],spaces_3iWczBNnn5rbfoUlE0Jd_uploads_git_blob_9864c7f811c613c3faab876659c6423__25[[#This Row],[Estado de la Mesa]]<>"Ocupada",spaces_3iWczBNnn5rbfoUlE0Jd_uploads_git_blob_9864c7f811c613c3faab876659c6423__25[[#This Row],[Hora de salida2]]-spaces_3iWczBNnn5rbfoUlE0Jd_uploads_git_blob_9864c7f811c613c3faab876659c6423__25[[#This Row],[Hora de llegada2]])} -> 0.14513889 | S78: =_xlfn.XLOOKUP(spaces_3iWczBNnn5rbfoUlE0Jd_uploads_git_blob_9864c7f811c613c3faab876659c6423__25[[#This Row],[Número de Orden]],Cocinadinamica!E79:E847,Cocinadinamica!F79:F847)/1440 -> 0.067361111 | T78: {=_xlfn.IFS((spaces_3iWczBNnn5rbfoUlE0Jd_uploads_git_blob_9864c7f811c613c3faab876659c6423__25[[#This Row],[Tiempo de permanencia]]-spaces_3iWczBNnn5rbfoUlE0Jd_uploads_git_blob_9864c7f811c613c3faab876659c6423__25[[#This Row],[Tiempo de preparación total]])>0,spaces_3iWczBNnn5rbfoUlE0Jd_uploads_git_blob_9864c7f811c613c3faab876659c6423__25[[#This Row],[Tiempo de permanencia]]-spaces_3iWczBNnn5rbfoUlE0Jd_uploads_git_blob_9864c7f811c613c3faab876659c6423__25[[#This Row],[Tiempo de preparación total]],spaces_3iWczBNnn5rbfoUlE0Jd_uploads_git_blob_9864c7f811c613c3faab876659c6423__25[[#This Row],[Tiempo de permanencia]]-spaces_3iWczBNnn5rbfoUlE0Jd_uploads_git_blob_9864c7f811c613c3faab876659c6423__25[[#This Row],[Tiempo de preparación total]]<0,0)} -> 0.077777778 | U78: {=_xlfn.IFS(spaces_3iWczBNnn5rbfoUlE0Jd_uploads_git_blob_9864c7f811c613c3faab876659c6423__25[[#This Row],[Tiempo degustación]]=0,"NO PAGADA",spaces_3iWczBNnn5rbfoUlE0Jd_uploads_git_blob_9864c7f811c613c3faab876659c6423__25[[#This Row],[Tiempo degustación]]>0, "PAGADA")} -> PAGADA
A79: 7 | B79: Cliente_636 | C79: 4 | D79: 45017.065 | E79: 45017.127 | F79: Mesero_3 | G79: Almuerzo | H79: Tarjeta de crédito | I79: 20.02 | J79: Libre | K79: 78 | L79: Colombia | M79: Plato_12 | N79: =_xlfn.XLOOKUP(spaces_3iWczBNnn5rbfoUlE0Jd_uploads_git_blob_9864c7f811c613c3faab876659c6423__25[[#This Row],[Número de Orden]],Cocinadinamica!B80:B848,Cocinadinamica!C80:C848) -> 24 | O79: =spaces_3iWczBNnn5rbfoUlE0Jd_uploads_git_blob_9864c7f811c613c3faab876659c6423__25[[#This Row],[Hora de Llegada]] -> 45017.065 | P79: =spaces_3iWczBNnn5rbfoUlE0Jd_uploads_git_blob_9864c7f811c613c3faab876659c6423__25[[#This Row],[Hora de Llegada]] -> 45017.065 | Q79: =spaces_3iWczBNnn5rbfoUlE0Jd_uploads_git_blob_9864c7f811c613c3faab876659c6423__25[[#This Row],[Hora de Salida]] -> 45017.127 | R79: {=_xlfn.IFS(spaces_3iWczBNnn5rbfoUlE0Jd_uploads_git_blob_9864c7f811c613c3faab876659c6423__25[[#This Row],[Estado de la Mesa]]="Ocupada",(15/1440)+spaces_3iWczBNnn5rbfoUlE0Jd_uploads_git_blob_9864c7f811c613c3faab876659c6423__25[[#This Row],[Hora de salida2]]-spaces_3iWczBNnn5rbfoUlE0Jd_uploads_git_blob_9864c7f811c613c3faab876659c6423__25[[#This Row],[Hora de llegada2]],spaces_3iWczBNnn5rbfoUlE0Jd_uploads_git_blob_9864c7f811c613c3faab876659c6423__25[[#This Row],[Estado de la Mesa]]<>"Ocupada",spaces_3iWczBNnn5rbfoUlE0Jd_uploads_git_blob_9864c7f811c613c3faab876659c6423__25[[#This Row],[Hora de salida2]]-spaces_3iWczBNnn5rbfoUlE0Jd_uploads_git_blob_9864c7f811c613c3faab876659c6423__25[[#This Row],[Hora de llegada2]])} -> 0.061805556 | S79: =_xlfn.XLOOKUP(spaces_3iWczBNnn5rbfoUlE0Jd_uploads_git_blob_9864c7f811c613c3faab876659c6423__25[[#This Row],[Número de Orden]],Cocinadinamica!E80:E848,Cocinadinamica!F80:F848)/1440 -> 0.0375 | T79: {=_xlfn.IFS((spaces_3iWczBNnn5rbfoUlE0Jd_uploads_git_blob_9864c7f811c613c3faab876659c6423__25[[#This Row],[Tiempo de permanencia]]-spaces_3iWczBNnn5rbfoUlE0Jd_uploads_git_blob_9864c7f811c613c3faab876659c6423__25[[#This Row],[Tiempo de preparación total]])>0,spaces_3iWczBNnn5rbfoUlE0Jd_uploads_git_blob_9864c7f811c613c3faab876659c6423__25[[#This Row],[Tiempo de permanencia]]-spaces_3iWczBNnn5rbfoUlE0Jd_uploads_git_blob_9864c7f811c613c3faab876659c6423__25[[#This Row],[Tiempo de preparación total]],spaces_3iWczBNnn5rbfoUlE0Jd_uploads_git_blob_9864c7f811c613c3faab876659c6423__25[[#This Row],[Tiempo de permanencia]]-spaces_3iWczBNnn5rbfoUlE0Jd_uploads_git_blob_9864c7f811c613c3faab876659c6423__25[[#This Row],[Tiempo de preparación total]]<0,0)} -> 0.024305556 | U79: {=_xlfn.IFS(spaces_3iWczBNnn5rbfoUlE0Jd_uploads_git_blob_9864c7f811c613c3faab876659c6423__25[[#This Row],[Tiempo degustación]]=0,"NO PAGADA",spaces_3iWczBNnn5rbfoUlE0Jd_uploads_git_blob_9864c7f811c613c3faab876659c6423__25[[#This Row],[Tiempo degustación]]>0, "PAGADA")} -> PAGADA
A80: 16 | B80: Cliente_753 | C80: 2 | D80: 45017.065 | E80: 45017.214 | F80: Mesero_3 | G80: Almuerzo | H80: Tarjeta de crédito | I80: 34.01 | J80: Libre | K80: 79 | L80: Venezuela | M80: Plato_9, Plato_11, Plato_3, Plato_13 | N80: =_xlfn.XLOOKUP(spaces_3iWczBNnn5rbfoUlE0Jd_uploads_git_blob_9864c7f811c613c3faab876659c6423__25[[#This Row],[Número de Orden]],Cocinadinamica!B81:B849,Cocinadinamica!C81:C849) -> 123 | O80: =spaces_3iWczBNnn5rbfoUlE0Jd_uploads_git_blob_9864c7f811c613c3faab876659c6423__25[[#This Row],[Hora de Llegada]] -> 45017.065 | P80: =spaces_3iWczBNnn5rbfoUlE0Jd_uploads_git_blob_9864c7f811c613c3faab876659c6423__25[[#This Row],[Hora de Llegada]] -> 45017.065 | Q80: =spaces_3iWczBNnn5rbfoUlE0Jd_uploads_git_blob_9864c7f811c613c3faab876659c6423__25[[#This Row],[Hora de Salida]] -> 45017.214 | R80: {=_xlfn.IFS(spaces_3iWczBNnn5rbfoUlE0Jd_uploads_git_blob_9864c7f811c613c3faab876659c6423__25[[#This Row],[Estado de la Mesa]]="Ocupada",(15/1440)+spaces_3iWczBNnn5rbfoUlE0Jd_uploads_git_blob_9864c7f811c613c3faab876659c6423__25[[#This Row],[Hora de salida2]]-spaces_3iWczBNnn5rbfoUlE0Jd_uploads_git_blob_9864c7f811c613c3faab876659c6423__25[[#This Row],[Hora de llegada2]],spaces_3iWczBNnn5rbfoUlE0Jd_uploads_git_blob_9864c7f811c613c3faab876659c6423__25[[#This Row],[Estado de la Mesa]]<>"Ocupada",spaces_3iWczBNnn5rbfoUlE0Jd_uploads_git_blob_9864c7f811c613c3faab876659c6423__25[[#This Row],[Hora de salida2]]-spaces_3iWczBNnn5rbfoUlE0Jd_uploads_git_blob_9864c7f811c613c3faab876659c6423__25[[#This Row],[Hora de llegada2]])} -> 0.14861111 | S80: =_xlfn.XLOOKUP(spaces_3iWczBNnn5rbfoUlE0Jd_uploads_git_blob_9864c7f811c613c3faab876659c6423__25[[#This Row],[Número de Orden]],Cocinadinamica!E81:E849,Cocinadinamica!F81:F849)/1440 -> 0.066666667 | T80: {=_xlfn.IFS((spaces_3iWczBNnn5rbfoUlE0Jd_uploads_git_blob_9864c7f811c613c3faab876659c6423__25[[#This Row],[Tiempo de permanencia]]-spaces_3iWczBNnn5rbfoUlE0Jd_uploads_git_blob_9864c7f811c613c3faab876659c6423__25[[#This Row],[Tiempo de preparación total]])>0,spaces_3iWczBNnn5rbfoUlE0Jd_uploads_git_blob_9864c7f811c613c3faab876659c6423__25[[#This Row],[Tiempo de permanencia]]-spaces_3iWczBNnn5rbfoUlE0Jd_uploads_git_blob_9864c7f811c613c3faab876659c6423__25[[#This Row],[Tiempo de preparación total]],spaces_3iWczBNnn5rbfoUlE0Jd_uploads_git_blob_9864c7f811c613c3faab876659c6423__25[[#This Row],[Tiempo de permanencia]]-spaces_3iWczBNnn5rbfoUlE0Jd_uploads_git_blob_9864c7f811c613c3faab876659c6423__25[[#This Row],[Tiempo de preparación total]]<0,0)} -> 0.081944444 | U80: {=_xlfn.IFS(spaces_3iWczBNnn5rbfoUlE0Jd_uploads_git_blob_9864c7f811c613c3faab876659c6423__25[[#This Row],[Tiempo degustación]]=0,"NO PAGADA",spaces_3iWczBNnn5rbfoUlE0Jd_uploads_git_blob_9864c7f811c613c3faab876659c6423__25[[#This Row],[Tiempo degustación]]>0, "PAGADA")} -> PAGADA
A81: 18 | B81: Cliente_632 | C81: 6 | D81: 45017.093 | E81: 45017.157 | F81: Mesero_4 | G81: Almuerzo | H81: Tarjeta de crédito | I81: 39.05 | J81: Libre | K81: 80 | L81: Venezuela | M81: Plato_5, Plato_9, Plato_7 | N81: =_xlfn.XLOOKUP(spaces_3iWczBNnn5rbfoUlE0Jd_uploads_git_blob_9864c7f811c613c3faab876659c6423__25[[#This Row],[Número de Orden]],Cocinadinamica!B82:B850,Cocinadinamica!C82:C850) -> 50 | O81: =spaces_3iWczBNnn5rbfoUlE0Jd_uploads_git_blob_9864c7f811c613c3faab876659c6423__25[[#This Row],[Hora de Llegada]] -> 45017.093 | P81: =spaces_3iWczBNnn5rbfoUlE0Jd_uploads_git_blob_9864c7f811c613c3faab876659c6423__25[[#This Row],[Hora de Llegada]] -> 45017.093 | Q81: =spaces_3iWczBNnn5rbfoUlE0Jd_uploads_git_blob_9864c7f811c613c3faab876659c6423__25[[#This Row],[Hora de Salida]] -> 45017.157 | R81: {=_xlfn.IFS(spaces_3iWczBNnn5rbfoUlE0Jd_uploads_git_blob_9864c7f811c613c3faab876659c6423__25[[#This Row],[Estado de la Mesa]]="Ocupada",(15/1440)+spaces_3iWczBNnn5rbfoUlE0Jd_uploads_git_blob_9864c7f811c613c3faab876659c6423__25[[#This Row],[Hora de salida2]]-spaces_3iWczBNnn5rbfoUlE0Jd_uploads_git_blob_9864c7f811c613c3faab876659c6423__25[[#This Row],[Hora de llegada2]],spaces_3iWczBNnn5rbfoUlE0Jd_uploads_git_blob_9864c7f811c613c3faab876659c6423__25[[#This Row],[Estado de la Mesa]]<>"Ocupada",spaces_3iWczBNnn5rbfoUlE0Jd_uploads_git_blob_9864c7f811c613c3faab876659c6423__25[[#This Row],[Hora de salida2]]-spaces_3iWczBNnn5rbfoUlE0Jd_uploads_git_blob_9864c7f811c613c3faab876659c6423__25[[#This Row],[Hora de llegada2]])} -> 0.063888889 | S81: =_xlfn.XLOOKUP(spaces_3iWczBNnn5rbfoUlE0Jd_uploads_git_blob_9864c7f811c613c3faab876659c6423__25[[#This Row],[Número de Orden]],Cocinadinamica!E82:E850,Cocinadinamica!F82:F850)/1440 -> 0.046527778 | T81: {=_xlfn.IFS((spaces_3iWczBNnn5rbfoUlE0Jd_uploads_git_blob_9864c7f811c613c3faab876659c6423__25[[#This Row],[Tiempo de permanencia]]-spaces_3iWczBNnn5rbfoUlE0Jd_uploads_git_blob_9864c7f811c613c3faab876659c6423__25[[#This Row],[Tiempo de preparación total]])>0,spaces_3iWczBNnn5rbfoUlE0Jd_uploads_git_blob_9864c7f811c613c3faab876659c6423__25[[#This Row],[Tiempo de permanencia]]-spaces_3iWczBNnn5rbfoUlE0Jd_uploads_git_blob_9864c7f811c613c3faab876659c6423__25[[#This Row],[Tiempo de preparación total]],spaces_3iWczBNnn5rbfoUlE0Jd_uploads_git_blob_9864c7f811c613c3faab876659c6423__25[[#This Row],[Tiempo de permanencia]]-spaces_3iWczBNnn5rbfoUlE0Jd_uploads_git_blob_9864c7f811c613c3faab876659c6423__25[[#This Row],[Tiempo de preparación total]]<0,0)} -> 0.017361111 | U81: {=_xlfn.IFS(spaces_3iWczBNnn5rbfoUlE0Jd_uploads_git_blob_9864c7f811c613c3faab876659c6423__25[[#This Row],[Tiempo degustación]]=0,"NO PAGADA",spaces_3iWczBNnn5rbfoUlE0Jd_uploads_git_blob_9864c7f811c613c3faab876659c6423__25[[#This Row],[Tiempo degustación]]>0, "PAGADA")} -> PAGADA
